Workbook

Sheet Inputs
A1: TGP Fund One Model Inputs
A2: Built by Reif Tauati · 4176197004 · reif@thegoodproject.net
A4: Core Assumptions
A5: Max Fund Size ($B) | B5: 1 | C5: Investor-facing guidance
A6: Capital Calls On (1=yes, 0=no) | B6: 1 | C6: Max Fund Size is the hard ceiling on total LP capital called.
A7: Hardcore Mode (1=yes, 0=no) | B7: 0 | C7: Capital Calls On means equity is called only when needed. Hardcore Mode forces fully funded upfront deployment with zero idle cash.
A8: Loan Size ($M) | B8: 25 | C8: Borrower Rate is what the developer pays. Fund Take is what the fund retains after origination partners are paid.
A9: Base Deals / Month | B9: 3 | C9: Debt / Equity of 0.25 means $0.25 of debt for each $1.00 of LP equity.
A10: Loan Term (months) | B10: 18
A11: Debt / Equity | B11: 0
A12: Borrower Rate | B12: 0.25
A13: Fund Take | B13: 0.18
A14: Cost of Debt | B14: 0.08
A15: Target IRR | B15: 0.15
A16: View Months | B16: 120
A18: Derived
A19: Just-in-Time Calls Active | B19: =IF(B7=1,0,B6)
A20: Total Lending Multiple | B20: =1+B11
A21: Shares Outstanding | B21: =B5*1000000000/1000
A22: Initial LP Call ($) | B22: =IF(B19=1,0,B5*1000000000)

Sheet Summary
A1: Fund One Excel Model Summary
A2: Contact Reif Tauati · 4176197004 · reif@thegoodproject.net
A4: Scenario Output
A5: Projected IRR | B5: =Monthly_Model!AI127 | C5: How to use this workbook
A6: Year 10 NAV / Share | B6: =Monthly_Model!AC127 | C6: Yellow cells on Inputs are editable assumptions.
A7: Lowest Cash | B7: =MIN(Monthly_Model!$Z$7:$Z$127) | C7: Green cells are modeled outputs.
A8: Peak LP Capital Out | B8: =MAX(Monthly_Model!$AD$7:$AD$127) | C8: Monthly_Model contains the full 10-year monthly build with formulas.
A9: Peak Debt | B9: =MAX(Monthly_Model!$AE$7:$AE$127) | C9: Hardcore Mode redeploys all available cash immediately and disables just-in-time capital calling.
A10: Peak New Loan Volume / Month | B10: =MAX(Monthly_Model!$V$8:$V$127)
A11: Peak Loans / Month | B11: =MAX(Monthly_Model!$AG$8:$AG$127)
A12: Total LP Called | B12: =MAX(Monthly_Model!$AH$7:$AH$127)
A13: Total Loans Originated | B13: =SUM(Monthly_Model!$AG$8:$AG$127)
A14: Target vs Projected Gap | B14: =Monthly_Model!AI127-Inputs!B15

Sheet Monthly_Model
A1: 10-Year Monthly Projection
A2: Formulas trace the current /model logic. Edit Inputs and Excel will recalculate.
A6: Month | B6: Label | C6: Opening Cash | D6: Opening NAV | E6: Carry Interest | F6: Carry Principal | G6: Active Eq Open | H6: Active Debt Open | I6: Carry Debt Cost | J6: Pre-Deploy Cash | K6: Remaining Callable | L6: Deployable Eq Cap | M6: Loan Size | N6: Base Deals | O6: Pipeline Scale | P6: Ramp | Q6: Scaled Deals | R6: Desired Orig Vol | S6: Desired Eq Deploy | T6: Actual Eq Deploy | U6: LP Call | V6: Actual Orig Vol | W6: Debt Deploy | X6: Immediate Interest | Y6: Immediate Debt Cost | Z6: Ending Cash | AA6: Ending NAV | AB6: Target NAV | AC6: NAV / Share | AD6: Active Eq Close | AE6: Active Debt Close | AF6: Loans Outstanding | AG6: New Loans / Mo | AH6: Cumulative LP Called | AI6: IRR To Date | AJ6: LP Flow Helper
A7: 0 | B7: Start | C7: =Inputs!B22 | D7: =Inputs!B22 | E7: 0 | F7: 0 | G7: 0 | H7: 0 | I7: 0 | J7: 0 | K7: 0 | L7: 0 | M7: 0 | N7: 0 | O7: 0 | P7: 0 | Q7: 0 | R7: 0 | S7: 0 | T7: 0 | U7: 0 | V7: 0 | W7: 0 | X7: 0 | Y7: 0 | Z7: =C7 | AA7: =D7 | AB7: =Inputs!B22 | AC7: =IF(Inputs!B21>0,AA7/Inputs!B21,0) | AD7: 0 | AE7: 0 | AF7: 0 | AG7: =0 | AH7: =Inputs!B22 | AI7: 0 | AJ7: 0
A8: =A7+1 | B8: Month 1 | C8: =Z7 | D8: =AA7 | E8: =IF(A8<=12,0,INDEX($V$8:$V$127,A8-12)*Inputs!B13*MAX(0,Inputs!B10-12)/12) | F8: =IF(A8<=Inputs!B10,0,INDEX($T$8:$T$127,A8-Inputs!B10)) | G8: =AD7-F8 | H8: =AE7-IF(A8<=Inputs!B10,0,INDEX($W$8:$W$127,A8-Inputs!B10)) | I8: =H8*Inputs!B14/12 | J8: =C8+E8+F8-I8 | K8: =IF(Inputs!B19=1,MAX(0,Inputs!B5*1000000000-AH7),0) | L8: =MAX(0,J8+K8) | M8: =Inputs!B8*1000000 | N8: =Inputs!B9 | O8: =MAX(1,SQRT(L8/MAX(M8*MAX(N8,0.01)/(1+Inputs!B11),1))) | P8: =MIN(1,A8/12) | Q8: =IF(Inputs!B7=1,MAX(N8,L8*(1+Inputs!B11)/MAX(M8,1)),N8+(N8*O8-N8)*P8) | R8: =IF(Inputs!B7=1,L8*(1+Inputs!B11),M8*Q8) | S8: =R8/(1+Inputs!B11) | T8: =IF(Inputs!B7=1,L8,MIN(S8,L8)) | U8: =IF(Inputs!B19=1,MAX(0,T8-J8),0) | V8: =T8*(1+Inputs!B11) | W8: =V8-T8 | X8: =V8*Inputs!B13*MIN(12,Inputs!B10)/12 | Y8: =W8*Inputs!B14/12 | Z8: =J8+U8-T8+X8-Y8 | AA8: =D8+E8-I8+U8+X8-Y8 | AB8: =IF(U8>0,AB7*(1+Inputs!B15/12)+U8,AB7*(1+Inputs!B15/12)) | AC8: =IF(Inputs!B21>0,AA8/Inputs!B21,0) | AD8: =G8+T8 | AE8: =H8+W8 | AF8: =AD8+AE8 | AG8: =IF(M8>0,V8/M8,0) | AH8: =AH7+U8 | AI8: 0 | AJ8: =-U8
A9: =A8+1 | B9: Month 2 | C9: =Z8 | D9: =AA8 | E9: =IF(A9<=12,0,INDEX($V$8:$V$127,A9-12)*Inputs!B13*MAX(0,Inputs!B10-12)/12) | F9: =IF(A9<=Inputs!B10,0,INDEX($T$8:$T$127,A9-Inputs!B10)) | G9: =AD8-F9 | H9: =AE8-IF(A9<=Inputs!B10,0,INDEX($W$8:$W$127,A9-Inputs!B10)) | I9: =H9*Inputs!B14/12 | J9: =C9+E9+F9-I9 | K9: =IF(Inputs!B19=1,MAX(0,Inputs!B5*1000000000-AH8),0) | L9: =MAX(0,J9+K9) | M9: =Inputs!B8*1000000 | N9: =Inputs!B9 | O9: =MAX(1,SQRT(L9/MAX(M9*MAX(N9,0.01)/(1+Inputs!B11),1))) | P9: =MIN(1,A9/12) | Q9: =IF(Inputs!B7=1,MAX(N9,L9*(1+Inputs!B11)/MAX(M9,1)),N9+(N9*O9-N9)*P9) | R9: =IF(Inputs!B7=1,L9*(1+Inputs!B11),M9*Q9) | S9: =R9/(1+Inputs!B11) | T9: =IF(Inputs!B7=1,L9,MIN(S9,L9)) | U9: =IF(Inputs!B19=1,MAX(0,T9-J9),0) | V9: =T9*(1+Inputs!B11) | W9: =V9-T9 | X9: =V9*Inputs!B13*MIN(12,Inputs!B10)/12 | Y9: =W9*Inputs!B14/12 | Z9: =J9+U9-T9+X9-Y9 | AA9: =D9+E9-I9+U9+X9-Y9 | AB9: =IF(U9>0,AB8*(1+Inputs!B15/12)+U9,AB8*(1+Inputs!B15/12)) | AC9: =IF(Inputs!B21>0,AA9/Inputs!B21,0) | AD9: =G9+T9 | AE9: =H9+W9 | AF9: =AD9+AE9 | AG9: =IF(M9>0,V9/M9,0) | AH9: =AH8+U9 | AI9: =IFERROR((1+IRR(VSTACK($AJ$8:INDEX($AJ:$AJ,ROW()-1),-U9+AA9)))^12-1,0) | AJ9: =-U9
A10: =A9+1 | B10: Month 3 | C10: =Z9 | D10: =AA9 | E10: =IF(A10<=12,0,INDEX($V$8:$V$127,A10-12)*Inputs!B13*MAX(0,Inputs!B10-12)/12) | F10: =IF(A10<=Inputs!B10,0,INDEX($T$8:$T$127,A10-Inputs!B10)) | G10: =AD9-F10 | H10: =AE9-IF(A10<=Inputs!B10,0,INDEX($W$8:$W$127,A10-Inputs!B10)) | I10: =H10*Inputs!B14/12 | J10: =C10+E10+F10-I10 | K10: =IF(Inputs!B19=1,MAX(0,Inputs!B5*1000000000-AH9),0) | L10: =MAX(0,J10+K10) | M10: =Inputs!B8*1000000 | N10: =Inputs!B9 | O10: =MAX(1,SQRT(L10/MAX(M10*MAX(N10,0.01)/(1+Inputs!B11),1))) | P10: =MIN(1,A10/12) | Q10: =IF(Inputs!B7=1,MAX(N10,L10*(1+Inputs!B11)/MAX(M10,1)),N10+(N10*O10-N10)*P10) | R10: =IF(Inputs!B7=1,L10*(1+Inputs!B11),M10*Q10) | S10: =R10/(1+Inputs!B11) | T10: =IF(Inputs!B7=1,L10,MIN(S10,L10)) | U10: =IF(Inputs!B19=1,MAX(0,T10-J10),0) | V10: =T10*(1+Inputs!B11) | W10: =V10-T10 | X10: =V10*Inputs!B13*MIN(12,Inputs!B10)/12 | Y10: =W10*Inputs!B14/12 | Z10: =J10+U10-T10+X10-Y10 | AA10: =D10+E10-I10+U10+X10-Y10 | AB10: =IF(U10>0,AB9*(1+Inputs!B15/12)+U10,AB9*(1+Inputs!B15/12)) | AC10: =IF(Inputs!B21>0,AA10/Inputs!B21,0) | AD10: =G10+T10 | AE10: =H10+W10 | AF10: =AD10+AE10 | AG10: =IF(M10>0,V10/M10,0) | AH10: =AH9+U10 | AI10: =IFERROR((1+IRR(VSTACK($AJ$8:INDEX($AJ:$AJ,ROW()-1),-U10+AA10)))^12-1,0) | AJ10: =-U10
A11: =A10+1 | B11: Month 4 | C11: =Z10 | D11: =AA10 | E11: =IF(A11<=12,0,INDEX($V$8:$V$127,A11-12)*Inputs!B13*MAX(0,Inputs!B10-12)/12) | F11: =IF(A11<=Inputs!B10,0,INDEX($T$8:$T$127,A11-Inputs!B10)) | G11: =AD10-F11 | H11: =AE10-IF(A11<=Inputs!B10,0,INDEX($W$8:$W$127,A11-Inputs!B10)) | I11: =H11*Inputs!B14/12 | J11: =C11+E11+F11-I11 | K11: =IF(Inputs!B19=1,MAX(0,Inputs!B5*1000000000-AH10),0) | L11: =MAX(0,J11+K11) | M11: =Inputs!B8*1000000 | N11: =Inputs!B9 | O11: =MAX(1,SQRT(L11/MAX(M11*MAX(N11,0.01)/(1+Inputs!B11),1))) | P11: =MIN(1,A11/12) | Q11: =IF(Inputs!B7=1,MAX(N11,L11*(1+Inputs!B11)/MAX(M11,1)),N11+(N11*O11-N11)*P11) | R11: =IF(Inputs!B7=1,L11*(1+Inputs!B11),M11*Q11) | S11: =R11/(1+Inputs!B11) | T11: =IF(Inputs!B7=1,L11,MIN(S11,L11)) | U11: =IF(Inputs!B19=1,MAX(0,T11-J11),0) | V11: =T11*(1+Inputs!B11) | W11: =V11-T11 | X11: =V11*Inputs!B13*MIN(12,Inputs!B10)/12 | Y11: =W11*Inputs!B14/12 | Z11: =J11+U11-T11+X11-Y11 | AA11: =D11+E11-I11+U11+X11-Y11 | AB11: =IF(U11>0,AB10*(1+Inputs!B15/12)+U11,AB10*(1+Inputs!B15/12)) | AC11: =IF(Inputs!B21>0,AA11/Inputs!B21,0) | AD11: =G11+T11 | AE11: =H11+W11 | AF11: =AD11+AE11 | AG11: =IF(M11>0,V11/M11,0) | AH11: =AH10+U11 | AI11: =IFERROR((1+IRR(VSTACK($AJ$8:INDEX($AJ:$AJ,ROW()-1),-U11+AA11)))^12-1,0) | AJ11: =-U11
A12: =A11+1 | B12: Month 5 | C12: =Z11 | D12: =AA11 | E12: =IF(A12<=12,0,INDEX($V$8:$V$127,A12-12)*Inputs!B13*MAX(0,Inputs!B10-12)/12) | F12: =IF(A12<=Inputs!B10,0,INDEX($T$8:$T$127,A12-Inputs!B10)) | G12: =AD11-F12 | H12: =AE11-IF(A12<=Inputs!B10,0,INDEX($W$8:$W$127,A12-Inputs!B10)) | I12: =H12*Inputs!B14/12 | J12: =C12+E12+F12-I12 | K12: =IF(Inputs!B19=1,MAX(0,Inputs!B5*1000000000-AH11),0) | L12: =MAX(0,J12+K12) | M12: =Inputs!B8*1000000 | N12: =Inputs!B9 | O12: =MAX(1,SQRT(L12/MAX(M12*MAX(N12,0.01)/(1+Inputs!B11),1))) | P12: =MIN(1,A12/12) | Q12: =IF(Inputs!B7=1,MAX(N12,L12*(1+Inputs!B11)/MAX(M12,1)),N12+(N12*O12-N12)*P12) | R12: =IF(Inputs!B7=1,L12*(1+Inputs!B11),M12*Q12) | S12: =R12/(1+Inputs!B11) | T12: =IF(Inputs!B7=1,L12,MIN(S12,L12)) | U12: =IF(Inputs!B19=1,MAX(0,T12-J12),0) | V12: =T12*(1+Inputs!B11) | W12: =V12-T12 | X12: =V12*Inputs!B13*MIN(12,Inputs!B10)/12 | Y12: =W12*Inputs!B14/12 | Z12: =J12+U12-T12+X12-Y12 | AA12: =D12+E12-I12+U12+X12-Y12 | AB12: =IF(U12>0,AB11*(1+Inputs!B15/12)+U12,AB11*(1+Inputs!B15/12)) | AC12: =IF(Inputs!B21>0,AA12/Inputs!B21,0) | AD12: =G12+T12 | AE12: =H12+W12 | AF12: =AD12+AE12 | AG12: =IF(M12>0,V12/M12,0) | AH12: =AH11+U12 | AI12: =IFERROR((1+IRR(VSTACK($AJ$8:INDEX($AJ:$AJ,ROW()-1),-U12+AA12)))^12-1,0) | AJ12: =-U12
A13: =A12+1 | B13: Month 6 | C13: =Z12 | D13: =AA12 | E13: =IF(A13<=12,0,INDEX($V$8:$V$127,A13-12)*Inputs!B13*MAX(0,Inputs!B10-12)/12) | F13: =IF(A13<=Inputs!B10,0,INDEX($T$8:$T$127,A13-Inputs!B10)) | G13: =AD12-F13 | H13: =AE12-IF(A13<=Inputs!B10,0,INDEX($W$8:$W$127,A13-Inputs!B10)) | I13: =H13*Inputs!B14/12 | J13: =C13+E13+F13-I13 | K13: =IF(Inputs!B19=1,MAX(0,Inputs!B5*1000000000-AH12),0) | L13: =MAX(0,J13+K13) | M13: =Inputs!B8*1000000 | N13: =Inputs!B9 | O13: =MAX(1,SQRT(L13/MAX(M13*MAX(N13,0.01)/(1+Inputs!B11),1))) | P13: =MIN(1,A13/12) | Q13: =IF(Inputs!B7=1,MAX(N13,L13*(1+Inputs!B11)/MAX(M13,1)),N13+(N13*O13-N13)*P13) | R13: =IF(Inputs!B7=1,L13*(1+Inputs!B11),M13*Q13) | S13: =R13/(1+Inputs!B11) | T13: =IF(Inputs!B7=1,L13,MIN(S13,L13)) | U13: =IF(Inputs!B19=1,MAX(0,T13-J13),0) | V13: =T13*(1+Inputs!B11) | W13: =V13-T13 | X13: =V13*Inputs!B13*MIN(12,Inputs!B10)/12 | Y13: =W13*Inputs!B14/12 | Z13: =J13+U13-T13+X13-Y13 | AA13: =D13+E13-I13+U13+X13-Y13 | AB13: =IF(U13>0,AB12*(1+Inputs!B15/12)+U13,AB12*(1+Inputs!B15/12)) | AC13: =IF(Inputs!B21>0,AA13/Inputs!B21,0) | AD13: =G13+T13 | AE13: =H13+W13 | AF13: =AD13+AE13 | AG13: =IF(M13>0,V13/M13,0) | AH13: =AH12+U13 | AI13: =IFERROR((1+IRR(VSTACK($AJ$8:INDEX($AJ:$AJ,ROW()-1),-U13+AA13)))^12-1,0) | AJ13: =-U13
A14: =A13+1 | B14: Month 7 | C14: =Z13 | D14: =AA13 | E14: =IF(A14<=12,0,INDEX($V$8:$V$127,A14-12)*Inputs!B13*MAX(0,Inputs!B10-12)/12) | F14: =IF(A14<=Inputs!B10,0,INDEX($T$8:$T$127,A14-Inputs!B10)) | G14: =AD13-F14 | H14: =AE13-IF(A14<=Inputs!B10,0,INDEX($W$8:$W$127,A14-Inputs!B10)) | I14: =H14*Inputs!B14/12 | J14: =C14+E14+F14-I14 | K14: =IF(Inputs!B19=1,MAX(0,Inputs!B5*1000000000-AH13),0) | L14: =MAX(0,J14+K14) | M14: =Inputs!B8*1000000 | N14: =Inputs!B9 | O14: =MAX(1,SQRT(L14/MAX(M14*MAX(N14,0.01)/(1+Inputs!B11),1))) | P14: =MIN(1,A14/12) | Q14: =IF(Inputs!B7=1,MAX(N14,L14*(1+Inputs!B11)/MAX(M14,1)),N14+(N14*O14-N14)*P14) | R14: =IF(Inputs!B7=1,L14*(1+Inputs!B11),M14*Q14) | S14: =R14/(1+Inputs!B11) | T14: =IF(Inputs!B7=1,L14,MIN(S14,L14)) | U14: =IF(Inputs!B19=1,MAX(0,T14-J14),0) | V14: =T14*(1+Inputs!B11) | W14: =V14-T14 | X14: =V14*Inputs!B13*MIN(12,Inputs!B10)/12 | Y14: =W14*Inputs!B14/12 | Z14: =J14+U14-T14+X14-Y14 | AA14: =D14+E14-I14+U14+X14-Y14 | AB14: =IF(U14>0,AB13*(1+Inputs!B15/12)+U14,AB13*(1+Inputs!B15/12)) | AC14: =IF(Inputs!B21>0,AA14/Inputs!B21,0) | AD14: =G14+T14 | AE14: =H14+W14 | AF14: =AD14+AE14 | AG14: =IF(M14>0,V14/M14,0) | AH14: =AH13+U14 | AI14: =IFERROR((1+IRR(VSTACK($AJ$8:INDEX($AJ:$AJ,ROW()-1),-U14+AA14)))^12-1,0) | AJ14: =-U14
A15: =A14+1 | B15: Month 8 | C15: =Z14 | D15: =AA14 | E15: =IF(A15<=12,0,INDEX($V$8:$V$127,A15-12)*Inputs!B13*MAX(0,Inputs!B10-12)/12) | F15: =IF(A15<=Inputs!B10,0,INDEX($T$8:$T$127,A15-Inputs!B10)) | G15: =AD14-F15 | H15: =AE14-IF(A15<=Inputs!B10,0,INDEX($W$8:$W$127,A15-Inputs!B10)) | I15: =H15*Inputs!B14/12 | J15: =C15+E15+F15-I15 | K15: =IF(Inputs!B19=1,MAX(0,Inputs!B5*1000000000-AH14),0) | L15: =MAX(0,J15+K15) | M15: =Inputs!B8*1000000 | N15: =Inputs!B9 | O15: =MAX(1,SQRT(L15/MAX(M15*MAX(N15,0.01)/(1+Inputs!B11),1))) | P15: =MIN(1,A15/12) | Q15: =IF(Inputs!B7=1,MAX(N15,L15*(1+Inputs!B11)/MAX(M15,1)),N15+(N15*O15-N15)*P15) | R15: =IF(Inputs!B7=1,L15*(1+Inputs!B11),M15*Q15) | S15: =R15/(1+Inputs!B11) | T15: =IF(Inputs!B7=1,L15,MIN(S15,L15)) | U15: =IF(Inputs!B19=1,MAX(0,T15-J15),0) | V15: =T15*(1+Inputs!B11) | W15: =V15-T15 | X15: =V15*Inputs!B13*MIN(12,Inputs!B10)/12 | Y15: =W15*Inputs!B14/12 | Z15: =J15+U15-T15+X15-Y15 | AA15: =D15+E15-I15+U15+X15-Y15 | AB15: =IF(U15>0,AB14*(1+Inputs!B15/12)+U15,AB14*(1+Inputs!B15/12)) | AC15: =IF(Inputs!B21>0,AA15/Inputs!B21,0) | AD15: =G15+T15 | AE15: =H15+W15 | AF15: =AD15+AE15 | AG15: =IF(M15>0,V15/M15,0) | AH15: =AH14+U15 | AI15: =IFERROR((1+IRR(VSTACK($AJ$8:INDEX($AJ:$AJ,ROW()-1),-U15+AA15)))^12-1,0) | AJ15: =-U15
A16: =A15+1 | B16: Month 9 | C16: =Z15 | D16: =AA15 | E16: =IF(A16<=12,0,INDEX($V$8:$V$127,A16-12)*Inputs!B13*MAX(0,Inputs!B10-12)/12) | F16: =IF(A16<=Inputs!B10,0,INDEX($T$8:$T$127,A16-Inputs!B10)) | G16: =AD15-F16 | H16: =AE15-IF(A16<=Inputs!B10,0,INDEX($W$8:$W$127,A16-Inputs!B10)) | I16: =H16*Inputs!B14/12 | J16: =C16+E16+F16-I16 | K16: =IF(Inputs!B19=1,MAX(0,Inputs!B5*1000000000-AH15),0) | L16: =MAX(0,J16+K16) | M16: =Inputs!B8*1000000 | N16: =Inputs!B9 | O16: =MAX(1,SQRT(L16/MAX(M16*MAX(N16,0.01)/(1+Inputs!B11),1))) | P16: =MIN(1,A16/12) | Q16: =IF(Inputs!B7=1,MAX(N16,L16*(1+Inputs!B11)/MAX(M16,1)),N16+(N16*O16-N16)*P16) | R16: =IF(Inputs!B7=1,L16*(1+Inputs!B11),M16*Q16) | S16: =R16/(1+Inputs!B11) | T16: =IF(Inputs!B7=1,L16,MIN(S16,L16)) | U16: =IF(Inputs!B19=1,MAX(0,T16-J16),0) | V16: =T16*(1+Inputs!B11) | W16: =V16-T16 | X16: =V16*Inputs!B13*MIN(12,Inputs!B10)/12 | Y16: =W16*Inputs!B14/12 | Z16: =J16+U16-T16+X16-Y16 | AA16: =D16+E16-I16+U16+X16-Y16 | AB16: =IF(U16>0,AB15*(1+Inputs!B15/12)+U16,AB15*(1+Inputs!B15/12)) | AC16: =IF(Inputs!B21>0,AA16/Inputs!B21,0) | AD16: =G16+T16 | AE16: =H16+W16 | AF16: =AD16+AE16 | AG16: =IF(M16>0,V16/M16,0) | AH16: =AH15+U16 | AI16: =IFERROR((1+IRR(VSTACK($AJ$8:INDEX($AJ:$AJ,ROW()-1),-U16+AA16)))^12-1,0) | AJ16: =-U16
A17: =A16+1 | B17: Month 10 | C17: =Z16 | D17: =AA16 | E17: =IF(A17<=12,0,INDEX($V$8:$V$127,A17-12)*Inputs!B13*MAX(0,Inputs!B10-12)/12) | F17: =IF(A17<=Inputs!B10,0,INDEX($T$8:$T$127,A17-Inputs!B10)) | G17: =AD16-F17 | H17: =AE16-IF(A17<=Inputs!B10,0,INDEX($W$8:$W$127,A17-Inputs!B10)) | I17: =H17*Inputs!B14/12 | J17: =C17+E17+F17-I17 | K17: =IF(Inputs!B19=1,MAX(0,Inputs!B5*1000000000-AH16),0) | L17: =MAX(0,J17+K17) | M17: =Inputs!B8*1000000 | N17: =Inputs!B9 | O17: =MAX(1,SQRT(L17/MAX(M17*MAX(N17,0.01)/(1+Inputs!B11),1))) | P17: =MIN(1,A17/12) | Q17: =IF(Inputs!B7=1,MAX(N17,L17*(1+Inputs!B11)/MAX(M17,1)),N17+(N17*O17-N17)*P17) | R17: =IF(Inputs!B7=1,L17*(1+Inputs!B11),M17*Q17) | S17: =R17/(1+Inputs!B11) | T17: =IF(Inputs!B7=1,L17,MIN(S17,L17)) | U17: =IF(Inputs!B19=1,MAX(0,T17-J17),0) | V17: =T17*(1+Inputs!B11) | W17: =V17-T17 | X17: =V17*Inputs!B13*MIN(12,Inputs!B10)/12 | Y17: =W17*Inputs!B14/12 | Z17: =J17+U17-T17+X17-Y17 | AA17: =D17+E17-I17+U17+X17-Y17 | AB17: =IF(U17>0,AB16*(1+Inputs!B15/12)+U17,AB16*(1+Inputs!B15/12)) | AC17: =IF(Inputs!B21>0,AA17/Inputs!B21,0) | AD17: =G17+T17 | AE17: =H17+W17 | AF17: =AD17+AE17 | AG17: =IF(M17>0,V17/M17,0) | AH17: =AH16+U17 | AI17: =IFERROR((1+IRR(VSTACK($AJ$8:INDEX($AJ:$AJ,ROW()-1),-U17+AA17)))^12-1,0) | AJ17: =-U17
A18: =A17+1 | B18: Month 11 | C18: =Z17 | D18: =AA17 | E18: =IF(A18<=12,0,INDEX($V$8:$V$127,A18-12)*Inputs!B13*MAX(0,Inputs!B10-12)/12) | F18: =IF(A18<=Inputs!B10,0,INDEX($T$8:$T$127,A18-Inputs!B10)) | G18: =AD17-F18 | H18: =AE17-IF(A18<=Inputs!B10,0,INDEX($W$8:$W$127,A18-Inputs!B10)) | I18: =H18*Inputs!B14/12 | J18: =C18+E18+F18-I18 | K18: =IF(Inputs!B19=1,MAX(0,Inputs!B5*1000000000-AH17),0) | L18: =MAX(0,J18+K18) | M18: =Inputs!B8*1000000 | N18: =Inputs!B9 | O18: =MAX(1,SQRT(L18/MAX(M18*MAX(N18,0.01)/(1+Inputs!B11),1))) | P18: =MIN(1,A18/12) | Q18: =IF(Inputs!B7=1,MAX(N18,L18*(1+Inputs!B11)/MAX(M18,1)),N18+(N18*O18-N18)*P18) | R18: =IF(Inputs!B7=1,L18*(1+Inputs!B11),M18*Q18) | S18: =R18/(1+Inputs!B11) | T18: =IF(Inputs!B7=1,L18,MIN(S18,L18)) | U18: =IF(Inputs!B19=1,MAX(0,T18-J18),0) | V18: =T18*(1+Inputs!B11) | W18: =V18-T18 | X18: =V18*Inputs!B13*MIN(12,Inputs!B10)/12 | Y18: =W18*Inputs!B14/12 | Z18: =J18+U18-T18+X18-Y18 | AA18: =D18+E18-I18+U18+X18-Y18 | AB18: =IF(U18>0,AB17*(1+Inputs!B15/12)+U18,AB17*(1+Inputs!B15/12)) | AC18: =IF(Inputs!B21>0,AA18/Inputs!B21,0) | AD18: =G18+T18 | AE18: =H18+W18 | AF18: =AD18+AE18 | AG18: =IF(M18>0,V18/M18,0) | AH18: =AH17+U18 | AI18: =IFERROR((1+IRR(VSTACK($AJ$8:INDEX($AJ:$AJ,ROW()-1),-U18+AA18)))^12-1,0) | AJ18: =-U18
A19: =A18+1 | B19: Month 12 | C19: =Z18 | D19: =AA18 | E19: =IF(A19<=12,0,INDEX($V$8:$V$127,A19-12)*Inputs!B13*MAX(0,Inputs!B10-12)/12) | F19: =IF(A19<=Inputs!B10,0,INDEX($T$8:$T$127,A19-Inputs!B10)) | G19: =AD18-F19 | H19: =AE18-IF(A19<=Inputs!B10,0,INDEX($W$8:$W$127,A19-Inputs!B10)) | I19: =H19*Inputs!B14/12 | J19: =C19+E19+F19-I19 | K19: =IF(Inputs!B19=1,MAX(0,Inputs!B5*1000000000-AH18),0) | L19: =MAX(0,J19+K19) | M19: =Inputs!B8*1000000 | N19: =Inputs!B9 | O19: =MAX(1,SQRT(L19/MAX(M19*MAX(N19,0.01)/(1+Inputs!B11),1))) | P19: =MIN(1,A19/12) | Q19: =IF(Inputs!B7=1,MAX(N19,L19*(1+Inputs!B11)/MAX(M19,1)),N19+(N19*O19-N19)*P19) | R19: =IF(Inputs!B7=1,L19*(1+Inputs!B11),M19*Q19) | S19: =R19/(1+Inputs!B11) | T19: =IF(Inputs!B7=1,L19,MIN(S19,L19)) | U19: =IF(Inputs!B19=1,MAX(0,T19-J19),0) | V19: =T19*(1+Inputs!B11) | W19: =V19-T19 | X19: =V19*Inputs!B13*MIN(12,Inputs!B10)/12 | Y19: =W19*Inputs!B14/12 | Z19: =J19+U19-T19+X19-Y19 | AA19: =D19+E19-I19+U19+X19-Y19 | AB19: =IF(U19>0,AB18*(1+Inputs!B15/12)+U19,AB18*(1+Inputs!B15/12)) | AC19: =IF(Inputs!B21>0,AA19/Inputs!B21,0) | AD19: =G19+T19 | AE19: =H19+W19 | AF19: =AD19+AE19 | AG19: =IF(M19>0,V19/M19,0) | AH19: =AH18+U19 | AI19: =IFERROR((1+IRR(VSTACK($AJ$8:INDEX($AJ:$AJ,ROW()-1),-U19+AA19)))^12-1,0) | AJ19: =-U19
A20: =A19+1 | B20: Month 13 | C20: =Z19 | D20: =AA19 | E20: =IF(A20<=12,0,INDEX($V$8:$V$127,A20-12)*Inputs!B13*MAX(0,Inputs!B10-12)/12) | F20: =IF(A20<=Inputs!B10,0,INDEX($T$8:$T$127,A20-Inputs!B10)) | G20: =AD19-F20 | H20: =AE19-IF(A20<=Inputs!B10,0,INDEX($W$8:$W$127,A20-Inputs!B10)) | I20: =H20*Inputs!B14/12 | J20: =C20+E20+F20-I20 | K20: =IF(Inputs!B19=1,MAX(0,Inputs!B5*1000000000-AH19),0) | L20: =MAX(0,J20+K20) | M20: =Inputs!B8*1000000 | N20: =Inputs!B9 | O20: =MAX(1,SQRT(L20/MAX(M20*MAX(N20,0.01)/(1+Inputs!B11),1))) | P20: =MIN(1,A20/12) | Q20: =IF(Inputs!B7=1,MAX(N20,L20*(1+Inputs!B11)/MAX(M20,1)),N20+(N20*O20-N20)*P20) | R20: =IF(Inputs!B7=1,L20*(1+Inputs!B11),M20*Q20) | S20: =R20/(1+Inputs!B11) | T20: =IF(Inputs!B7=1,L20,MIN(S20,L20)) | U20: =IF(Inputs!B19=1,MAX(0,T20-J20),0) | V20: =T20*(1+Inputs!B11) | W20: =V20-T20 | X20: =V20*Inputs!B13*MIN(12,Inputs!B10)/12 | Y20: =W20*Inputs!B14/12 | Z20: =J20+U20-T20+X20-Y20 | AA20: =D20+E20-I20+U20+X20-Y20 | AB20: =IF(U20>0,AB19*(1+Inputs!B15/12)+U20,AB19*(1+Inputs!B15/12)) | AC20: =IF(Inputs!B21>0,AA20/Inputs!B21,0) | AD20: =G20+T20 | AE20: =H20+W20 | AF20: =AD20+AE20 | AG20: =IF(M20>0,V20/M20,0) | AH20: =AH19+U20 | AI20: =IFERROR((1+IRR(VSTACK($AJ$8:INDEX($AJ:$AJ,ROW()-1),-U20+AA20)))^12-1,0) | AJ20: =-U20
A21: =A20+1 | B21: Month 14 | C21: =Z20 | D21: =AA20 | E21: =IF(A21<=12,0,INDEX($V$8:$V$127,A21-12)*Inputs!B13*MAX(0,Inputs!B10-12)/12) | F21: =IF(A21<=Inputs!B10,0,INDEX($T$8:$T$127,A21-Inputs!B10)) | G21: =AD20-F21 | H21: =AE20-IF(A21<=Inputs!B10,0,INDEX($W$8:$W$127,A21-Inputs!B10)) | I21: =H21*Inputs!B14/12 | J21: =C21+E21+F21-I21 | K21: =IF(Inputs!B19=1,MAX(0,Inputs!B5*1000000000-AH20),0) | L21: =MAX(0,J21+K21) | M21: =Inputs!B8*1000000 | N21: =Inputs!B9 | O21: =MAX(1,SQRT(L21/MAX(M21*MAX(N21,0.01)/(1+Inputs!B11),1))) | P21: =MIN(1,A21/12) | Q21: =IF(Inputs!B7=1,MAX(N21,L21*(1+Inputs!B11)/MAX(M21,1)),N21+(N21*O21-N21)*P21) | R21: =IF(Inputs!B7=1,L21*(1+Inputs!B11),M21*Q21) | S21: =R21/(1+Inputs!B11) | T21: =IF(Inputs!B7=1,L21,MIN(S21,L21)) | U21: =IF(Inputs!B19=1,MAX(0,T21-J21),0) | V21: =T21*(1+Inputs!B11) | W21: =V21-T21 | X21: =V21*Inputs!B13*MIN(12,Inputs!B10)/12 | Y21: =W21*Inputs!B14/12 | Z21: =J21+U21-T21+X21-Y21 | AA21: =D21+E21-I21+U21+X21-Y21 | AB21: =IF(U21>0,AB20*(1+Inputs!B15/12)+U21,AB20*(1+Inputs!B15/12)) | AC21: =IF(Inputs!B21>0,AA21/Inputs!B21,0) | AD21: =G21+T21 | AE21: =H21+W21 | AF21: =AD21+AE21 | AG21: =IF(M21>0,V21/M21,0) | AH21: =AH20+U21 | AI21: =IFERROR((1+IRR(VSTACK($AJ$8:INDEX($AJ:$AJ,ROW()-1),-U21+AA21)))^12-1,0) | AJ21: =-U21
A22: =A21+1 | B22: Month 15 | C22: =Z21 | D22: =AA21 | E22: =IF(A22<=12,0,INDEX($V$8:$V$127,A22-12)*Inputs!B13*MAX(0,Inputs!B10-12)/12) | F22: =IF(A22<=Inputs!B10,0,INDEX($T$8:$T$127,A22-Inputs!B10)) | G22: =AD21-F22 | H22: =AE21-IF(A22<=Inputs!B10,0,INDEX($W$8:$W$127,A22-Inputs!B10)) | I22: =H22*Inputs!B14/12 | J22: =C22+E22+F22-I22 | K22: =IF(Inputs!B19=1,MAX(0,Inputs!B5*1000000000-AH21),0) | L22: =MAX(0,J22+K22) | M22: =Inputs!B8*1000000 | N22: =Inputs!B9 | O22: =MAX(1,SQRT(L22/MAX(M22*MAX(N22,0.01)/(1+Inputs!B11),1))) | P22: =MIN(1,A22/12) | Q22: =IF(Inputs!B7=1,MAX(N22,L22*(1+Inputs!B11)/MAX(M22,1)),N22+(N22*O22-N22)*P22) | R22: =IF(Inputs!B7=1,L22*(1+Inputs!B11),M22*Q22) | S22: =R22/(1+Inputs!B11) | T22: =IF(Inputs!B7=1,L22,MIN(S22,L22)) | U22: =IF(Inputs!B19=1,MAX(0,T22-J22),0) | V22: =T22*(1+Inputs!B11) | W22: =V22-T22 | X22: =V22*Inputs!B13*MIN(12,Inputs!B10)/12 | Y22: =W22*Inputs!B14/12 | Z22: =J22+U22-T22+X22-Y22 | AA22: =D22+E22-I22+U22+X22-Y22 | AB22: =IF(U22>0,AB21*(1+Inputs!B15/12)+U22,AB21*(1+Inputs!B15/12)) | AC22: =IF(Inputs!B21>0,AA22/Inputs!B21,0) | AD22: =G22+T22 | AE22: =H22+W22 | AF22: =AD22+AE22 | AG22: =IF(M22>0,V22/M22,0) | AH22: =AH21+U22 | AI22: =IFERROR((1+IRR(VSTACK($AJ$8:INDEX($AJ:$AJ,ROW()-1),-U22+AA22)))^12-1,0) | AJ22: =-U22
A23: =A22+1 | B23: Month 16 | C23: =Z22 | D23: =AA22 | E23: =IF(A23<=12,0,INDEX($V$8:$V$127,A23-12)*Inputs!B13*MAX(0,Inputs!B10-12)/12) | F23: =IF(A23<=Inputs!B10,0,INDEX($T$8:$T$127,A23-Inputs!B10)) | G23: =AD22-F23 | H23: =AE22-IF(A23<=Inputs!B10,0,INDEX($W$8:$W$127,A23-Inputs!B10)) | I23: =H23*Inputs!B14/12 | J23: =C23+E23+F23-I23 | K23: =IF(Inputs!B19=1,MAX(0,Inputs!B5*1000000000-AH22),0) | L23: =MAX(0,J23+K23) | M23: =Inputs!B8*1000000 | N23: =Inputs!B9 | O23: =MAX(1,SQRT(L23/MAX(M23*MAX(N23,0.01)/(1+Inputs!B11),1))) | P23: =MIN(1,A23/12) | Q23: =IF(Inputs!B7=1,MAX(N23,L23*(1+Inputs!B11)/MAX(M23,1)),N23+(N23*O23-N23)*P23) | R23: =IF(Inputs!B7=1,L23*(1+Inputs!B11),M23*Q23) | S23: =R23/(1+Inputs!B11) | T23: =IF(Inputs!B7=1,L23,MIN(S23,L23)) | U23: =IF(Inputs!B19=1,MAX(0,T23-J23),0) | V23: =T23*(1+Inputs!B11) | W23: =V23-T23 | X23: =V23*Inputs!B13*MIN(12,Inputs!B10)/12 | Y23: =W23*Inputs!B14/12 | Z23: =J23+U23-T23+X23-Y23 | AA23: =D23+E23-I23+U23+X23-Y23 | AB23: =IF(U23>0,AB22*(1+Inputs!B15/12)+U23,AB22*(1+Inputs!B15/12)) | AC23: =IF(Inputs!B21>0,AA23/Inputs!B21,0) | AD23: =G23+T23 | AE23: =H23+W23 | AF23: =AD23+AE23 | AG23: =IF(M23>0,V23/M23,0) | AH23: =AH22+U23 | AI23: =IFERROR((1+IRR(VSTACK($AJ$8:INDEX($AJ:$AJ,ROW()-1),-U23+AA23)))^12-1,0) | AJ23: =-U23
A24: =A23+1 | B24: Month 17 | C24: =Z23 | D24: =AA23 | E24: =IF(A24<=12,0,INDEX($V$8:$V$127,A24-12)*Inputs!B13*MAX(0,Inputs!B10-12)/12) | F24: =IF(A24<=Inputs!B10,0,INDEX($T$8:$T$127,A24-Inputs!B10)) | G24: =AD23-F24 | H24: =AE23-IF(A24<=Inputs!B10,0,INDEX($W$8:$W$127,A24-Inputs!B10)) | I24: =H24*Inputs!B14/12 | J24: =C24+E24+F24-I24 | K24: =IF(Inputs!B19=1,MAX(0,Inputs!B5*1000000000-AH23),0) | L24: =MAX(0,J24+K24) | M24: =Inputs!B8*1000000 | N24: =Inputs!B9 | O24: =MAX(1,SQRT(L24/MAX(M24*MAX(N24,0.01)/(1+Inputs!B11),1))) | P24: =MIN(1,A24/12) | Q24: =IF(Inputs!B7=1,MAX(N24,L24*(1+Inputs!B11)/MAX(M24,1)),N24+(N24*O24-N24)*P24) | R24: =IF(Inputs!B7=1,L24*(1+Inputs!B11),M24*Q24) | S24: =R24/(1+Inputs!B11) | T24: =IF(Inputs!B7=1,L24,MIN(S24,L24)) | U24: =IF(Inputs!B19=1,MAX(0,T24-J24),0) | V24: =T24*(1+Inputs!B11) | W24: =V24-T24 | X24: =V24*Inputs!B13*MIN(12,Inputs!B10)/12 | Y24: =W24*Inputs!B14/12 | Z24: =J24+U24-T24+X24-Y24 | AA24: =D24+E24-I24+U24+X24-Y24 | AB24: =IF(U24>0,AB23*(1+Inputs!B15/12)+U24,AB23*(1+Inputs!B15/12)) | AC24: =IF(Inputs!B21>0,AA24/Inputs!B21,0) | AD24: =G24+T24 | AE24: =H24+W24 | AF24: =AD24+AE24 | AG24: =IF(M24>0,V24/M24,0) | AH24: =AH23+U24 | AI24: =IFERROR((1+IRR(VSTACK($AJ$8:INDEX($AJ:$AJ,ROW()-1),-U24+AA24)))^12-1,0) | AJ24: =-U24
A25: =A24+1 | B25: Month 18 | C25: =Z24 | D25: =AA24 | E25: =IF(A25<=12,0,INDEX($V$8:$V$127,A25-12)*Inputs!B13*MAX(0,Inputs!B10-12)/12) | F25: =IF(A25<=Inputs!B10,0,INDEX($T$8:$T$127,A25-Inputs!B10)) | G25: =AD24-F25 | H25: =AE24-IF(A25<=Inputs!B10,0,INDEX($W$8:$W$127,A25-Inputs!B10)) | I25: =H25*Inputs!B14/12 | J25: =C25+E25+F25-I25 | K25: =IF(Inputs!B19=1,MAX(0,Inputs!B5*1000000000-AH24),0) | L25: =MAX(0,J25+K25) | M25: =Inputs!B8*1000000 | N25: =Inputs!B9 | O25: =MAX(1,SQRT(L25/MAX(M25*MAX(N25,0.01)/(1+Inputs!B11),1))) | P25: =MIN(1,A25/12) | Q25: =IF(Inputs!B7=1,MAX(N25,L25*(1+Inputs!B11)/MAX(M25,1)),N25+(N25*O25-N25)*P25) | R25: =IF(Inputs!B7=1,L25*(1+Inputs!B11),M25*Q25) | S25: =R25/(1+Inputs!B11) | T25: =IF(Inputs!B7=1,L25,MIN(S25,L25)) | U25: =IF(Inputs!B19=1,MAX(0,T25-J25),0) | V25: =T25*(1+Inputs!B11) | W25: =V25-T25 | X25: =V25*Inputs!B13*MIN(12,Inputs!B10)/12 | Y25: =W25*Inputs!B14/12 | Z25: =J25+U25-T25+X25-Y25 | AA25: =D25+E25-I25+U25+X25-Y25 | AB25: =IF(U25>0,AB24*(1+Inputs!B15/12)+U25,AB24*(1+Inputs!B15/12)) | AC25: =IF(Inputs!B21>0,AA25/Inputs!B21,0) | AD25: =G25+T25 | AE25: =H25+W25 | AF25: =AD25+AE25 | AG25: =IF(M25>0,V25/M25,0) | AH25: =AH24+U25 | AI25: =IFERROR((1+IRR(VSTACK($AJ$8:INDEX($AJ:$AJ,ROW()-1),-U25+AA25)))^12-1,0) | AJ25: =-U25
A26: =A25+1 | B26: Month 19 | C26: =Z25 | D26: =AA25 | E26: =IF(A26<=12,0,INDEX($V$8:$V$127,A26-12)*Inputs!B13*MAX(0,Inputs!B10-12)/12) | F26: =IF(A26<=Inputs!B10,0,INDEX($T$8:$T$127,A26-Inputs!B10)) | G26: =AD25-F26 | H26: =AE25-IF(A26<=Inputs!B10,0,INDEX($W$8:$W$127,A26-Inputs!B10)) | I26: =H26*Inputs!B14/12 | J26: =C26+E26+F26-I26 | K26: =IF(Inputs!B19=1,MAX(0,Inputs!B5*1000000000-AH25),0) | L26: =MAX(0,J26+K26) | M26: =Inputs!B8*1000000 | N26: =Inputs!B9 | O26: =MAX(1,SQRT(L26/MAX(M26*MAX(N26,0.01)/(1+Inputs!B11),1))) | P26: =MIN(1,A26/12) | Q26: =IF(Inputs!B7=1,MAX(N26,L26*(1+Inputs!B11)/MAX(M26,1)),N26+(N26*O26-N26)*P26) | R26: =IF(Inputs!B7=1,L26*(1+Inputs!B11),M26*Q26) | S26: =R26/(1+Inputs!B11) | T26: =IF(Inputs!B7=1,L26,MIN(S26,L26)) | U26: =IF(Inputs!B19=1,MAX(0,T26-J26),0) | V26: =T26*(1+Inputs!B11) | W26: =V26-T26 | X26: =V26*Inputs!B13*MIN(12,Inputs!B10)/12 | Y26: =W26*Inputs!B14/12 | Z26: =J26+U26-T26+X26-Y26 | AA26: =D26+E26-I26+U26+X26-Y26 | AB26: =IF(U26>0,AB25*(1+Inputs!B15/12)+U26,AB25*(1+Inputs!B15/12)) | AC26: =IF(Inputs!B21>0,AA26/Inputs!B21,0) | AD26: =G26+T26 | AE26: =H26+W26 | AF26: =AD26+AE26 | AG26: =IF(M26>0,V26/M26,0) | AH26: =AH25+U26 | AI26: =IFERROR((1+IRR(VSTACK($AJ$8:INDEX($AJ:$AJ,ROW()-1),-U26+AA26)))^12-1,0) | AJ26: =-U26
A27: =A26+1 | B27: Month 20 | C27: =Z26 | D27: =AA26 | E27: =IF(A27<=12,0,INDEX($V$8:$V$127,A27-12)*Inputs!B13*MAX(0,Inputs!B10-12)/12) | F27: =IF(A27<=Inputs!B10,0,INDEX($T$8:$T$127,A27-Inputs!B10)) | G27: =AD26-F27 | H27: =AE26-IF(A27<=Inputs!B10,0,INDEX($W$8:$W$127,A27-Inputs!B10)) | I27: =H27*Inputs!B14/12 | J27: =C27+E27+F27-I27 | K27: =IF(Inputs!B19=1,MAX(0,Inputs!B5*1000000000-AH26),0) | L27: =MAX(0,J27+K27) | M27: =Inputs!B8*1000000 | N27: =Inputs!B9 | O27: =MAX(1,SQRT(L27/MAX(M27*MAX(N27,0.01)/(1+Inputs!B11),1))) | P27: =MIN(1,A27/12) | Q27: =IF(Inputs!B7=1,MAX(N27,L27*(1+Inputs!B11)/MAX(M27,1)),N27+(N27*O27-N27)*P27) | R27: =IF(Inputs!B7=1,L27*(1+Inputs!B11),M27*Q27) | S27: =R27/(1+Inputs!B11) | T27: =IF(Inputs!B7=1,L27,MIN(S27,L27)) | U27: =IF(Inputs!B19=1,MAX(0,T27-J27),0) | V27: =T27*(1+Inputs!B11) | W27: =V27-T27 | X27: =V27*Inputs!B13*MIN(12,Inputs!B10)/12 | Y27: =W27*Inputs!B14/12 | Z27: =J27+U27-T27+X27-Y27 | AA27: =D27+E27-I27+U27+X27-Y27 | AB27: =IF(U27>0,AB26*(1+Inputs!B15/12)+U27,AB26*(1+Inputs!B15/12)) | AC27: =IF(Inputs!B21>0,AA27/Inputs!B21,0) | AD27: =G27+T27 | AE27: =H27+W27 | AF27: =AD27+AE27 | AG27: =IF(M27>0,V27/M27,0) | AH27: =AH26+U27 | AI27: =IFERROR((1+IRR(VSTACK($AJ$8:INDEX($AJ:$AJ,ROW()-1),-U27+AA27)))^12-1,0) | AJ27: =-U27
A28: =A27+1 | B28: Month 21 | C28: =Z27 | D28: =AA27 | E28: =IF(A28<=12,0,INDEX($V$8:$V$127,A28-12)*Inputs!B13*MAX(0,Inputs!B10-12)/12) | F28: =IF(A28<=Inputs!B10,0,INDEX($T$8:$T$127,A28-Inputs!B10)) | G28: =AD27-F28 | H28: =AE27-IF(A28<=Inputs!B10,0,INDEX($W$8:$W$127,A28-Inputs!B10)) | I28: =H28*Inputs!B14/12 | J28: =C28+E28+F28-I28 | K28: =IF(Inputs!B19=1,MAX(0,Inputs!B5*1000000000-AH27),0) | L28: =MAX(0,J28+K28) | M28: =Inputs!B8*1000000 | N28: =Inputs!B9 | O28: =MAX(1,SQRT(L28/MAX(M28*MAX(N28,0.01)/(1+Inputs!B11),1))) | P28: =MIN(1,A28/12) | Q28: =IF(Inputs!B7=1,MAX(N28,L28*(1+Inputs!B11)/MAX(M28,1)),N28+(N28*O28-N28)*P28) | R28: =IF(Inputs!B7=1,L28*(1+Inputs!B11),M28*Q28) | S28: =R28/(1+Inputs!B11) | T28: =IF(Inputs!B7=1,L28,MIN(S28,L28)) | U28: =IF(Inputs!B19=1,MAX(0,T28-J28),0) | V28: =T28*(1+Inputs!B11) | W28: =V28-T28 | X28: =V28*Inputs!B13*MIN(12,Inputs!B10)/12 | Y28: =W28*Inputs!B14/12 | Z28: =J28+U28-T28+X28-Y28 | AA28: =D28+E28-I28+U28+X28-Y28 | AB28: =IF(U28>0,AB27*(1+Inputs!B15/12)+U28,AB27*(1+Inputs!B15/12)) | AC28: =IF(Inputs!B21>0,AA28/Inputs!B21,0) | AD28: =G28+T28 | AE28: =H28+W28 | AF28: =AD28+AE28 | AG28: =IF(M28>0,V28/M28,0) | AH28: =AH27+U28 | AI28: =IFERROR((1+IRR(VSTACK($AJ$8:INDEX($AJ:$AJ,ROW()-1),-U28+AA28)))^12-1,0) | AJ28: =-U28
A29: =A28+1 | B29: Month 22 | C29: =Z28 | D29: =AA28 | E29: =IF(A29<=12,0,INDEX($V$8:$V$127,A29-12)*Inputs!B13*MAX(0,Inputs!B10-12)/12) | F29: =IF(A29<=Inputs!B10,0,INDEX($T$8:$T$127,A29-Inputs!B10)) | G29: =AD28-F29 | H29: =AE28-IF(A29<=Inputs!B10,0,INDEX($W$8:$W$127,A29-Inputs!B10)) | I29: =H29*Inputs!B14/12 | J29: =C29+E29+F29-I29 | K29: =IF(Inputs!B19=1,MAX(0,Inputs!B5*1000000000-AH28),0) | L29: =MAX(0,J29+K29) | M29: =Inputs!B8*1000000 | N29: =Inputs!B9 | O29: =MAX(1,SQRT(L29/MAX(M29*MAX(N29,0.01)/(1+Inputs!B11),1))) | P29: =MIN(1,A29/12) | Q29: =IF(Inputs!B7=1,MAX(N29,L29*(1+Inputs!B11)/MAX(M29,1)),N29+(N29*O29-N29)*P29) | R29: =IF(Inputs!B7=1,L29*(1+Inputs!B11),M29*Q29) | S29: =R29/(1+Inputs!B11) | T29: =IF(Inputs!B7=1,L29,MIN(S29,L29)) | U29: =IF(Inputs!B19=1,MAX(0,T29-J29),0) | V29: =T29*(1+Inputs!B11) | W29: =V29-T29 | X29: =V29*Inputs!B13*MIN(12,Inputs!B10)/12 | Y29: =W29*Inputs!B14/12 | Z29: =J29+U29-T29+X29-Y29 | AA29: =D29+E29-I29+U29+X29-Y29 | AB29: =IF(U29>0,AB28*(1+Inputs!B15/12)+U29,AB28*(1+Inputs!B15/12)) | AC29: =IF(Inputs!B21>0,AA29/Inputs!B21,0) | AD29: =G29+T29 | AE29: =H29+W29 | AF29: =AD29+AE29 | AG29: =IF(M29>0,V29/M29,0) | AH29: =AH28+U29 | AI29: =IFERROR((1+IRR(VSTACK($AJ$8:INDEX($AJ:$AJ,ROW()-1),-U29+AA29)))^12-1,0) | AJ29: =-U29
A30: =A29+1 | B30: Month 23 | C30: =Z29 | D30: =AA29 | E30: =IF(A30<=12,0,INDEX($V$8:$V$127,A30-12)*Inputs!B13*MAX(0,Inputs!B10-12)/12) | F30: =IF(A30<=Inputs!B10,0,INDEX($T$8:$T$127,A30-Inputs!B10)) | G30: =AD29-F30 | H30: =AE29-IF(A30<=Inputs!B10,0,INDEX($W$8:$W$127,A30-Inputs!B10)) | I30: =H30*Inputs!B14/12 | J30: =C30+E30+F30-I30 | K30: =IF(Inputs!B19=1,MAX(0,Inputs!B5*1000000000-AH29),0) | L30: =MAX(0,J30+K30) | M30: =Inputs!B8*1000000 | N30: =Inputs!B9 | O30: =MAX(1,SQRT(L30/MAX(M30*MAX(N30,0.01)/(1+Inputs!B11),1))) | P30: =MIN(1,A30/12) | Q30: =IF(Inputs!B7=1,MAX(N30,L30*(1+Inputs!B11)/MAX(M30,1)),N30+(N30*O30-N30)*P30) | R30: =IF(Inputs!B7=1,L30*(1+Inputs!B11),M30*Q30) | S30: =R30/(1+Inputs!B11) | T30: =IF(Inputs!B7=1,L30,MIN(S30,L30)) | U30: =IF(Inputs!B19=1,MAX(0,T30-J30),0) | V30: =T30*(1+Inputs!B11) | W30: =V30-T30 | X30: =V30*Inputs!B13*MIN(12,Inputs!B10)/12 | Y30: =W30*Inputs!B14/12 | Z30: =J30+U30-T30+X30-Y30 | AA30: =D30+E30-I30+U30+X30-Y30 | AB30: =IF(U30>0,AB29*(1+Inputs!B15/12)+U30,AB29*(1+Inputs!B15/12)) | AC30: =IF(Inputs!B21>0,AA30/Inputs!B21,0) | AD30: =G30+T30 | AE30: =H30+W30 | AF30: =AD30+AE30 | AG30: =IF(M30>0,V30/M30,0) | AH30: =AH29+U30 | AI30: =IFERROR((1+IRR(VSTACK($AJ$8:INDEX($AJ:$AJ,ROW()-1),-U30+AA30)))^12-1,0) | AJ30: =-U30
A31: =A30+1 | B31: Month 24 | C31: =Z30 | D31: =AA30 | E31: =IF(A31<=12,0,INDEX($V$8:$V$127,A31-12)*Inputs!B13*MAX(0,Inputs!B10-12)/12) | F31: =IF(A31<=Inputs!B10,0,INDEX($T$8:$T$127,A31-Inputs!B10)) | G31: =AD30-F31 | H31: =AE30-IF(A31<=Inputs!B10,0,INDEX($W$8:$W$127,A31-Inputs!B10)) | I31: =H31*Inputs!B14/12 | J31: =C31+E31+F31-I31 | K31: =IF(Inputs!B19=1,MAX(0,Inputs!B5*1000000000-AH30),0) | L31: =MAX(0,J31+K31) | M31: =Inputs!B8*1000000 | N31: =Inputs!B9 | O31: =MAX(1,SQRT(L31/MAX(M31*MAX(N31,0.01)/(1+Inputs!B11),1))) | P31: =MIN(1,A31/12) | Q31: =IF(Inputs!B7=1,MAX(N31,L31*(1+Inputs!B11)/MAX(M31,1)),N31+(N31*O31-N31)*P31) | R31: =IF(Inputs!B7=1,L31*(1+Inputs!B11),M31*Q31) | S31: =R31/(1+Inputs!B11) | T31: =IF(Inputs!B7=1,L31,MIN(S31,L31)) | U31: =IF(Inputs!B19=1,MAX(0,T31-J31),0) | V31: =T31*(1+Inputs!B11) | W31: =V31-T31 | X31: =V31*Inputs!B13*MIN(12,Inputs!B10)/12 | Y31: =W31*Inputs!B14/12 | Z31: =J31+U31-T31+X31-Y31 | AA31: =D31+E31-I31+U31+X31-Y31 | AB31: =IF(U31>0,AB30*(1+Inputs!B15/12)+U31,AB30*(1+Inputs!B15/12)) | AC31: =IF(Inputs!B21>0,AA31/Inputs!B21,0) | AD31: =G31+T31 | AE31: =H31+W31 | AF31: =AD31+AE31 | AG31: =IF(M31>0,V31/M31,0) | AH31: =AH30+U31 | AI31: =IFERROR((1+IRR(VSTACK($AJ$8:INDEX($AJ:$AJ,ROW()-1),-U31+AA31)))^12-1,0) | AJ31: =-U31
A32: =A31+1 | B32: Month 25 | C32: =Z31 | D32: =AA31 | E32: =IF(A32<=12,0,INDEX($V$8:$V$127,A32-12)*Inputs!B13*MAX(0,Inputs!B10-12)/12) | F32: =IF(A32<=Inputs!B10,0,INDEX($T$8:$T$127,A32-Inputs!B10)) | G32: =AD31-F32 | H32: =AE31-IF(A32<=Inputs!B10,0,INDEX($W$8:$W$127,A32-Inputs!B10)) | I32: =H32*Inputs!B14/12 | J32: =C32+E32+F32-I32 | K32: =IF(Inputs!B19=1,MAX(0,Inputs!B5*1000000000-AH31),0) | L32: =MAX(0,J32+K32) | M32: =Inputs!B8*1000000 | N32: =Inputs!B9 | O32: =MAX(1,SQRT(L32/MAX(M32*MAX(N32,0.01)/(1+Inputs!B11),1))) | P32: =MIN(1,A32/12) | Q32: =IF(Inputs!B7=1,MAX(N32,L32*(1+Inputs!B11)/MAX(M32,1)),N32+(N32*O32-N32)*P32) | R32: =IF(Inputs!B7=1,L32*(1+Inputs!B11),M32*Q32) | S32: =R32/(1+Inputs!B11) | T32: =IF(Inputs!B7=1,L32,MIN(S32,L32)) | U32: =IF(Inputs!B19=1,MAX(0,T32-J32),0) | V32: =T32*(1+Inputs!B11) | W32: =V32-T32 | X32: =V32*Inputs!B13*MIN(12,Inputs!B10)/12 | Y32: =W32*Inputs!B14/12 | Z32: =J32+U32-T32+X32-Y32 | AA32: =D32+E32-I32+U32+X32-Y32 | AB32: =IF(U32>0,AB31*(1+Inputs!B15/12)+U32,AB31*(1+Inputs!B15/12)) | AC32: =IF(Inputs!B21>0,AA32/Inputs!B21,0) | AD32: =G32+T32 | AE32: =H32+W32 | AF32: =AD32+AE32 | AG32: =IF(M32>0,V32/M32,0) | AH32: =AH31+U32 | AI32: =IFERROR((1+IRR(VSTACK($AJ$8:INDEX($AJ:$AJ,ROW()-1),-U32+AA32)))^12-1,0) | AJ32: =-U32
A33: =A32+1 | B33: Month 26 | C33: =Z32 | D33: =AA32 | E33: =IF(A33<=12,0,INDEX($V$8:$V$127,A33-12)*Inputs!B13*MAX(0,Inputs!B10-12)/12) | F33: =IF(A33<=Inputs!B10,0,INDEX($T$8:$T$127,A33-Inputs!B10)) | G33: =AD32-F33 | H33: =AE32-IF(A33<=Inputs!B10,0,INDEX($W$8:$W$127,A33-Inputs!B10)) | I33: =H33*Inputs!B14/12 | J33: =C33+E33+F33-I33 | K33: =IF(Inputs!B19=1,MAX(0,Inputs!B5*1000000000-AH32),0) | L33: =MAX(0,J33+K33) | M33: =Inputs!B8*1000000 | N33: =Inputs!B9 | O33: =MAX(1,SQRT(L33/MAX(M33*MAX(N33,0.01)/(1+Inputs!B11),1))) | P33: =MIN(1,A33/12) | Q33: =IF(Inputs!B7=1,MAX(N33,L33*(1+Inputs!B11)/MAX(M33,1)),N33+(N33*O33-N33)*P33) | R33: =IF(Inputs!B7=1,L33*(1+Inputs!B11),M33*Q33) | S33: =R33/(1+Inputs!B11) | T33: =IF(Inputs!B7=1,L33,MIN(S33,L33)) | U33: =IF(Inputs!B19=1,MAX(0,T33-J33),0) | V33: =T33*(1+Inputs!B11) | W33: =V33-T33 | X33: =V33*Inputs!B13*MIN(12,Inputs!B10)/12 | Y33: =W33*Inputs!B14/12 | Z33: =J33+U33-T33+X33-Y33 | AA33: =D33+E33-I33+U33+X33-Y33 | AB33: =IF(U33>0,AB32*(1+Inputs!B15/12)+U33,AB32*(1+Inputs!B15/12)) | AC33: =IF(Inputs!B21>0,AA33/Inputs!B21,0) | AD33: =G33+T33 | AE33: =H33+W33 | AF33: =AD33+AE33 | AG33: =IF(M33>0,V33/M33,0) | AH33: =AH32+U33 | AI33: =IFERROR((1+IRR(VSTACK($AJ$8:INDEX($AJ:$AJ,ROW()-1),-U33+AA33)))^12-1,0) | AJ33: =-U33
A34: =A33+1 | B34: Month 27 | C34: =Z33 | D34: =AA33 | E34: =IF(A34<=12,0,INDEX($V$8:$V$127,A34-12)*Inputs!B13*MAX(0,Inputs!B10-12)/12) | F34: =IF(A34<=Inputs!B10,0,INDEX($T$8:$T$127,A34-Inputs!B10)) | G34: =AD33-F34 | H34: =AE33-IF(A34<=Inputs!B10,0,INDEX($W$8:$W$127,A34-Inputs!B10)) | I34: =H34*Inputs!B14/12 | J34: =C34+E34+F34-I34 | K34: =IF(Inputs!B19=1,MAX(0,Inputs!B5*1000000000-AH33),0) | L34: =MAX(0,J34+K34) | M34: =Inputs!B8*1000000 | N34: =Inputs!B9 | O34: =MAX(1,SQRT(L34/MAX(M34*MAX(N34,0.01)/(1+Inputs!B11),1))) | P34: =MIN(1,A34/12) | Q34: =IF(Inputs!B7=1,MAX(N34,L34*(1+Inputs!B11)/MAX(M34,1)),N34+(N34*O34-N34)*P34) | R34: =IF(Inputs!B7=1,L34*(1+Inputs!B11),M34*Q34) | S34: =R34/(1+Inputs!B11) | T34: =IF(Inputs!B7=1,L34,MIN(S34,L34)) | U34: =IF(Inputs!B19=1,MAX(0,T34-J34),0) | V34: =T34*(1+Inputs!B11) | W34: =V34-T34 | X34: =V34*Inputs!B13*MIN(12,Inputs!B10)/12 | Y34: =W34*Inputs!B14/12 | Z34: =J34+U34-T34+X34-Y34 | AA34: =D34+E34-I34+U34+X34-Y34 | AB34: =IF(U34>0,AB33*(1+Inputs!B15/12)+U34,AB33*(1+Inputs!B15/12)) | AC34: =IF(Inputs!B21>0,AA34/Inputs!B21,0) | AD34: =G34+T34 | AE34: =H34+W34 | AF34: =AD34+AE34 | AG34: =IF(M34>0,V34/M34,0) | AH34: =AH33+U34 | AI34: =IFERROR((1+IRR(VSTACK($AJ$8:INDEX($AJ:$AJ,ROW()-1),-U34+AA34)))^12-1,0) | AJ34: =-U34
A35: =A34+1 | B35: Month 28 | C35: =Z34 | D35: =AA34 | E35: =IF(A35<=12,0,INDEX($V$8:$V$127,A35-12)*Inputs!B13*MAX(0,Inputs!B10-12)/12) | F35: =IF(A35<=Inputs!B10,0,INDEX($T$8:$T$127,A35-Inputs!B10)) | G35: =AD34-F35 | H35: =AE34-IF(A35<=Inputs!B10,0,INDEX($W$8:$W$127,A35-Inputs!B10)) | I35: =H35*Inputs!B14/12 | J35: =C35+E35+F35-I35 | K35: =IF(Inputs!B19=1,MAX(0,Inputs!B5*1000000000-AH34),0) | L35: =MAX(0,J35+K35) | M35: =Inputs!B8*1000000 | N35: =Inputs!B9 | O35: =MAX(1,SQRT(L35/MAX(M35*MAX(N35,0.01)/(1+Inputs!B11),1))) | P35: =MIN(1,A35/12) | Q35: =IF(Inputs!B7=1,MAX(N35,L35*(1+Inputs!B11)/MAX(M35,1)),N35+(N35*O35-N35)*P35) | R35: =IF(Inputs!B7=1,L35*(1+Inputs!B11),M35*Q35) | S35: =R35/(1+Inputs!B11) | T35: =IF(Inputs!B7=1,L35,MIN(S35,L35)) | U35: =IF(Inputs!B19=1,MAX(0,T35-J35),0) | V35: =T35*(1+Inputs!B11) | W35: =V35-T35 | X35: =V35*Inputs!B13*MIN(12,Inputs!B10)/12 | Y35: =W35*Inputs!B14/12 | Z35: =J35+U35-T35+X35-Y35 | AA35: =D35+E35-I35+U35+X35-Y35 | AB35: =IF(U35>0,AB34*(1+Inputs!B15/12)+U35,AB34*(1+Inputs!B15/12)) | AC35: =IF(Inputs!B21>0,AA35/Inputs!B21,0) | AD35: =G35+T35 | AE35: =H35+W35 | AF35: =AD35+AE35 | AG35: =IF(M35>0,V35/M35,0) | AH35: =AH34+U35 | AI35: =IFERROR((1+IRR(VSTACK($AJ$8:INDEX($AJ:$AJ,ROW()-1),-U35+AA35)))^12-1,0) | AJ35: =-U35
A36: =A35+1 | B36: Month 29 | C36: =Z35 | D36: =AA35 | E36: =IF(A36<=12,0,INDEX($V$8:$V$127,A36-12)*Inputs!B13*MAX(0,Inputs!B10-12)/12) | F36: =IF(A36<=Inputs!B10,0,INDEX($T$8:$T$127,A36-Inputs!B10)) | G36: =AD35-F36 | H36: =AE35-IF(A36<=Inputs!B10,0,INDEX($W$8:$W$127,A36-Inputs!B10)) | I36: =H36*Inputs!B14/12 | J36: =C36+E36+F36-I36 | K36: =IF(Inputs!B19=1,MAX(0,Inputs!B5*1000000000-AH35),0) | L36: =MAX(0,J36+K36) | M36: =Inputs!B8*1000000 | N36: =Inputs!B9 | O36: =MAX(1,SQRT(L36/MAX(M36*MAX(N36,0.01)/(1+Inputs!B11),1))) | P36: =MIN(1,A36/12) | Q36: =IF(Inputs!B7=1,MAX(N36,L36*(1+Inputs!B11)/MAX(M36,1)),N36+(N36*O36-N36)*P36) | R36: =IF(Inputs!B7=1,L36*(1+Inputs!B11),M36*Q36) | S36: =R36/(1+Inputs!B11) | T36: =IF(Inputs!B7=1,L36,MIN(S36,L36)) | U36: =IF(Inputs!B19=1,MAX(0,T36-J36),0) | V36: =T36*(1+Inputs!B11) | W36: =V36-T36 | X36: =V36*Inputs!B13*MIN(12,Inputs!B10)/12 | Y36: =W36*Inputs!B14/12 | Z36: =J36+U36-T36+X36-Y36 | AA36: =D36+E36-I36+U36+X36-Y36 | AB36: =IF(U36>0,AB35*(1+Inputs!B15/12)+U36,AB35*(1+Inputs!B15/12)) | AC36: =IF(Inputs!B21>0,AA36/Inputs!B21,0) | AD36: =G36+T36 | AE36: =H36+W36 | AF36: =AD36+AE36 | AG36: =IF(M36>0,V36/M36,0) | AH36: =AH35+U36 | AI36: =IFERROR((1+IRR(VSTACK($AJ$8:INDEX($AJ:$AJ,ROW()-1),-U36+AA36)))^12-1,0) | AJ36: =-U36
A37: =A36+1 | B37: Month 30 | C37: =Z36 | D37: =AA36 | E37: =IF(A37<=12,0,INDEX($V$8:$V$127,A37-12)*Inputs!B13*MAX(0,Inputs!B10-12)/12) | F37: =IF(A37<=Inputs!B10,0,INDEX($T$8:$T$127,A37-Inputs!B10)) | G37: =AD36-F37 | H37: =AE36-IF(A37<=Inputs!B10,0,INDEX($W$8:$W$127,A37-Inputs!B10)) | I37: =H37*Inputs!B14/12 | J37: =C37+E37+F37-I37 | K37: =IF(Inputs!B19=1,MAX(0,Inputs!B5*1000000000-AH36),0) | L37: =MAX(0,J37+K37) | M37: =Inputs!B8*1000000 | N37: =Inputs!B9 | O37: =MAX(1,SQRT(L37/MAX(M37*MAX(N37,0.01)/(1+Inputs!B11),1))) | P37: =MIN(1,A37/12) | Q37: =IF(Inputs!B7=1,MAX(N37,L37*(1+Inputs!B11)/MAX(M37,1)),N37+(N37*O37-N37)*P37) | R37: =IF(Inputs!B7=1,L37*(1+Inputs!B11),M37*Q37) | S37: =R37/(1+Inputs!B11) | T37: =IF(Inputs!B7=1,L37,MIN(S37,L37)) | U37: =IF(Inputs!B19=1,MAX(0,T37-J37),0) | V37: =T37*(1+Inputs!B11) | W37: =V37-T37 | X37: =V37*Inputs!B13*MIN(12,Inputs!B10)/12 | Y37: =W37*Inputs!B14/12 | Z37: =J37+U37-T37+X37-Y37 | AA37: =D37+E37-I37+U37+X37-Y37 | AB37: =IF(U37>0,AB36*(1+Inputs!B15/12)+U37,AB36*(1+Inputs!B15/12)) | AC37: =IF(Inputs!B21>0,AA37/Inputs!B21,0) | AD37: =G37+T37 | AE37: =H37+W37 | AF37: =AD37+AE37 | AG37: =IF(M37>0,V37/M37,0) | AH37: =AH36+U37 | AI37: =IFERROR((1+IRR(VSTACK($AJ$8:INDEX($AJ:$AJ,ROW()-1),-U37+AA37)))^12-1,0) | AJ37: =-U37
A38: =A37+1 | B38: Month 31 | C38: =Z37 | D38: =AA37 | E38: =IF(A38<=12,0,INDEX($V$8:$V$127,A38-12)*Inputs!B13*MAX(0,Inputs!B10-12)/12) | F38: =IF(A38<=Inputs!B10,0,INDEX($T$8:$T$127,A38-Inputs!B10)) | G38: =AD37-F38 | H38: =AE37-IF(A38<=Inputs!B10,0,INDEX($W$8:$W$127,A38-Inputs!B10)) | I38: =H38*Inputs!B14/12 | J38: =C38+E38+F38-I38 | K38: =IF(Inputs!B19=1,MAX(0,Inputs!B5*1000000000-AH37),0) | L38: =MAX(0,J38+K38) | M38: =Inputs!B8*1000000 | N38: =Inputs!B9 | O38: =MAX(1,SQRT(L38/MAX(M38*MAX(N38,0.01)/(1+Inputs!B11),1))) | P38: =MIN(1,A38/12) | Q38: =IF(Inputs!B7=1,MAX(N38,L38*(1+Inputs!B11)/MAX(M38,1)),N38+(N38*O38-N38)*P38) | R38: =IF(Inputs!B7=1,L38*(1+Inputs!B11),M38*Q38) | S38: =R38/(1+Inputs!B11) | T38: =IF(Inputs!B7=1,L38,MIN(S38,L38)) | U38: =IF(Inputs!B19=1,MAX(0,T38-J38),0) | V38: =T38*(1+Inputs!B11) | W38: =V38-T38 | X38: =V38*Inputs!B13*MIN(12,Inputs!B10)/12 | Y38: =W38*Inputs!B14/12 | Z38: =J38+U38-T38+X38-Y38 | AA38: =D38+E38-I38+U38+X38-Y38 | AB38: =IF(U38>0,AB37*(1+Inputs!B15/12)+U38,AB37*(1+Inputs!B15/12)) | AC38: =IF(Inputs!B21>0,AA38/Inputs!B21,0) | AD38: =G38+T38 | AE38: =H38+W38 | AF38: =AD38+AE38 | AG38: =IF(M38>0,V38/M38,0) | AH38: =AH37+U38 | AI38: =IFERROR((1+IRR(VSTACK($AJ$8:INDEX($AJ:$AJ,ROW()-1),-U38+AA38)))^12-1,0) | AJ38: =-U38
A39: =A38+1 | B39: Month 32 | C39: =Z38 | D39: =AA38 | E39: =IF(A39<=12,0,INDEX($V$8:$V$127,A39-12)*Inputs!B13*MAX(0,Inputs!B10-12)/12) | F39: =IF(A39<=Inputs!B10,0,INDEX($T$8:$T$127,A39-Inputs!B10)) | G39: =AD38-F39 | H39: =AE38-IF(A39<=Inputs!B10,0,INDEX($W$8:$W$127,A39-Inputs!B10)) | I39: =H39*Inputs!B14/12 | J39: =C39+E39+F39-I39 | K39: =IF(Inputs!B19=1,MAX(0,Inputs!B5*1000000000-AH38),0) | L39: =MAX(0,J39+K39) | M39: =Inputs!B8*1000000 | N39: =Inputs!B9 | O39: =MAX(1,SQRT(L39/MAX(M39*MAX(N39,0.01)/(1+Inputs!B11),1))) | P39: =MIN(1,A39/12) | Q39: =IF(Inputs!B7=1,MAX(N39,L39*(1+Inputs!B11)/MAX(M39,1)),N39+(N39*O39-N39)*P39) | R39: =IF(Inputs!B7=1,L39*(1+Inputs!B11),M39*Q39) | S39: =R39/(1+Inputs!B11) | T39: =IF(Inputs!B7=1,L39,MIN(S39,L39)) | U39: =IF(Inputs!B19=1,MAX(0,T39-J39),0) | V39: =T39*(1+Inputs!B11) | W39: =V39-T39 | X39: =V39*Inputs!B13*MIN(12,Inputs!B10)/12 | Y39: =W39*Inputs!B14/12 | Z39: =J39+U39-T39+X39-Y39 | AA39: =D39+E39-I39+U39+X39-Y39 | AB39: =IF(U39>0,AB38*(1+Inputs!B15/12)+U39,AB38*(1+Inputs!B15/12)) | AC39: =IF(Inputs!B21>0,AA39/Inputs!B21,0) | AD39: =G39+T39 | AE39: =H39+W39 | AF39: =AD39+AE39 | AG39: =IF(M39>0,V39/M39,0) | AH39: =AH38+U39 | AI39: =IFERROR((1+IRR(VSTACK($AJ$8:INDEX($AJ:$AJ,ROW()-1),-U39+AA39)))^12-1,0) | AJ39: =-U39
A40: =A39+1 | B40: Month 33 | C40: =Z39 | D40: =AA39 | E40: =IF(A40<=12,0,INDEX($V$8:$V$127,A40-12)*Inputs!B13*MAX(0,Inputs!B10-12)/12) | F40: =IF(A40<=Inputs!B10,0,INDEX($T$8:$T$127,A40-Inputs!B10)) | G40: =AD39-F40 | H40: =AE39-IF(A40<=Inputs!B10,0,INDEX($W$8:$W$127,A40-Inputs!B10)) | I40: =H40*Inputs!B14/12 | J40: =C40+E40+F40-I40 | K40: =IF(Inputs!B19=1,MAX(0,Inputs!B5*1000000000-AH39),0) | L40: =MAX(0,J40+K40) | M40: =Inputs!B8*1000000 | N40: =Inputs!B9 | O40: =MAX(1,SQRT(L40/MAX(M40*MAX(N40,0.01)/(1+Inputs!B11),1))) | P40: =MIN(1,A40/12) | Q40: =IF(Inputs!B7=1,MAX(N40,L40*(1+Inputs!B11)/MAX(M40,1)),N40+(N40*O40-N40)*P40) | R40: =IF(Inputs!B7=1,L40*(1+Inputs!B11),M40*Q40) | S40: =R40/(1+Inputs!B11) | T40: =IF(Inputs!B7=1,L40,MIN(S40,L40)) | U40: =IF(Inputs!B19=1,MAX(0,T40-J40),0) | V40: =T40*(1+Inputs!B11) | W40: =V40-T40 | X40: =V40*Inputs!B13*MIN(12,Inputs!B10)/12 | Y40: =W40*Inputs!B14/12 | Z40: =J40+U40-T40+X40-Y40 | AA40: =D40+E40-I40+U40+X40-Y40 | AB40: =IF(U40>0,AB39*(1+Inputs!B15/12)+U40,AB39*(1+Inputs!B15/12)) | AC40: =IF(Inputs!B21>0,AA40/Inputs!B21,0) | AD40: =G40+T40 | AE40: =H40+W40 | AF40: =AD40+AE40 | AG40: =IF(M40>0,V40/M40,0) | AH40: =AH39+U40 | AI40: =IFERROR((1+IRR(VSTACK($AJ$8:INDEX($AJ:$AJ,ROW()-1),-U40+AA40)))^12-1,0) | AJ40: =-U40
A41: =A40+1 | B41: Month 34 | C41: =Z40 | D41: =AA40 | E41: =IF(A41<=12,0,INDEX($V$8:$V$127,A41-12)*Inputs!B13*MAX(0,Inputs!B10-12)/12) | F41: =IF(A41<=Inputs!B10,0,INDEX($T$8:$T$127,A41-Inputs!B10)) | G41: =AD40-F41 | H41: =AE40-IF(A41<=Inputs!B10,0,INDEX($W$8:$W$127,A41-Inputs!B10)) | I41: =H41*Inputs!B14/12 | J41: =C41+E41+F41-I41 | K41: =IF(Inputs!B19=1,MAX(0,Inputs!B5*1000000000-AH40),0) | L41: =MAX(0,J41+K41) | M41: =Inputs!B8*1000000 | N41: =Inputs!B9 | O41: =MAX(1,SQRT(L41/MAX(M41*MAX(N41,0.01)/(1+Inputs!B11),1))) | P41: =MIN(1,A41/12) | Q41: =IF(Inputs!B7=1,MAX(N41,L41*(1+Inputs!B11)/MAX(M41,1)),N41+(N41*O41-N41)*P41) | R41: =IF(Inputs!B7=1,L41*(1+Inputs!B11),M41*Q41) | S41: =R41/(1+Inputs!B11) | T41: =IF(Inputs!B7=1,L41,MIN(S41,L41)) | U41: =IF(Inputs!B19=1,MAX(0,T41-J41),0) | V41: =T41*(1+Inputs!B11) | W41: =V41-T41 | X41: =V41*Inputs!B13*MIN(12,Inputs!B10)/12 | Y41: =W41*Inputs!B14/12 | Z41: =J41+U41-T41+X41-Y41 | AA41: =D41+E41-I41+U41+X41-Y41 | AB41: =IF(U41>0,AB40*(1+Inputs!B15/12)+U41,AB40*(1+Inputs!B15/12)) | AC41: =IF(Inputs!B21>0,AA41/Inputs!B21,0) | AD41: =G41+T41 | AE41: =H41+W41 | AF41: =AD41+AE41 | AG41: =IF(M41>0,V41/M41,0) | AH41: =AH40+U41 | AI41: =IFERROR((1+IRR(VSTACK($AJ$8:INDEX($AJ:$AJ,ROW()-1),-U41+AA41)))^12-1,0) | AJ41: =-U41
A42: =A41+1 | B42: Month 35 | C42: =Z41 | D42: =AA41 | E42: =IF(A42<=12,0,INDEX($V$8:$V$127,A42-12)*Inputs!B13*MAX(0,Inputs!B10-12)/12) | F42: =IF(A42<=Inputs!B10,0,INDEX($T$8:$T$127,A42-Inputs!B10)) | G42: =AD41-F42 | H42: =AE41-IF(A42<=Inputs!B10,0,INDEX($W$8:$W$127,A42-Inputs!B10)) | I42: =H42*Inputs!B14/12 | J42: =C42+E42+F42-I42 | K42: =IF(Inputs!B19=1,MAX(0,Inputs!B5*1000000000-AH41),0) | L42: =MAX(0,J42+K42) | M42: =Inputs!B8*1000000 | N42: =Inputs!B9 | O42: =MAX(1,SQRT(L42/MAX(M42*MAX(N42,0.01)/(1+Inputs!B11),1))) | P42: =MIN(1,A42/12) | Q42: =IF(Inputs!B7=1,MAX(N42,L42*(1+Inputs!B11)/MAX(M42,1)),N42+(N42*O42-N42)*P42) | R42: =IF(Inputs!B7=1,L42*(1+Inputs!B11),M42*Q42) | S42: =R42/(1+Inputs!B11) | T42: =IF(Inputs!B7=1,L42,MIN(S42,L42)) | U42: =IF(Inputs!B19=1,MAX(0,T42-J42),0) | V42: =T42*(1+Inputs!B11) | W42: =V42-T42 | X42: =V42*Inputs!B13*MIN(12,Inputs!B10)/12 | Y42: =W42*Inputs!B14/12 | Z42: =J42+U42-T42+X42-Y42 | AA42: =D42+E42-I42+U42+X42-Y42 | AB42: =IF(U42>0,AB41*(1+Inputs!B15/12)+U42,AB41*(1+Inputs!B15/12)) | AC42: =IF(Inputs!B21>0,AA42/Inputs!B21,0) | AD42: =G42+T42 | AE42: =H42+W42 | AF42: =AD42+AE42 | AG42: =IF(M42>0,V42/M42,0) | AH42: =AH41+U42 | AI42: =IFERROR((1+IRR(VSTACK($AJ$8:INDEX($AJ:$AJ,ROW()-1),-U42+AA42)))^12-1,0) | AJ42: =-U42
A43: =A42+1 | B43: Month 36 | C43: =Z42 | D43: =AA42 | E43: =IF(A43<=12,0,INDEX($V$8:$V$127,A43-12)*Inputs!B13*MAX(0,Inputs!B10-12)/12) | F43: =IF(A43<=Inputs!B10,0,INDEX($T$8:$T$127,A43-Inputs!B10)) | G43: =AD42-F43 | H43: =AE42-IF(A43<=Inputs!B10,0,INDEX($W$8:$W$127,A43-Inputs!B10)) | I43: =H43*Inputs!B14/12 | J43: =C43+E43+F43-I43 | K43: =IF(Inputs!B19=1,MAX(0,Inputs!B5*1000000000-AH42),0) | L43: =MAX(0,J43+K43) | M43: =Inputs!B8*1000000 | N43: =Inputs!B9 | O43: =MAX(1,SQRT(L43/MAX(M43*MAX(N43,0.01)/(1+Inputs!B11),1))) | P43: =MIN(1,A43/12) | Q43: =IF(Inputs!B7=1,MAX(N43,L43*(1+Inputs!B11)/MAX(M43,1)),N43+(N43*O43-N43)*P43) | R43: =IF(Inputs!B7=1,L43*(1+Inputs!B11),M43*Q43) | S43: =R43/(1+Inputs!B11) | T43: =IF(Inputs!B7=1,L43,MIN(S43,L43)) | U43: =IF(Inputs!B19=1,MAX(0,T43-J43),0) | V43: =T43*(1+Inputs!B11) | W43: =V43-T43 | X43: =V43*Inputs!B13*MIN(12,Inputs!B10)/12 | Y43: =W43*Inputs!B14/12 | Z43: =J43+U43-T43+X43-Y43 | AA43: =D43+E43-I43+U43+X43-Y43 | AB43: =IF(U43>0,AB42*(1+Inputs!B15/12)+U43,AB42*(1+Inputs!B15/12)) | AC43: =IF(Inputs!B21>0,AA43/Inputs!B21,0) | AD43: =G43+T43 | AE43: =H43+W43 | AF43: =AD43+AE43 | AG43: =IF(M43>0,V43/M43,0) | AH43: =AH42+U43 | AI43: =IFERROR((1+IRR(VSTACK($AJ$8:INDEX($AJ:$AJ,ROW()-1),-U43+AA43)))^12-1,0) | AJ43: =-U43
A44: =A43+1 | B44: Month 37 | C44: =Z43 | D44: =AA43 | E44: =IF(A44<=12,0,INDEX($V$8:$V$127,A44-12)*Inputs!B13*MAX(0,Inputs!B10-12)/12) | F44: =IF(A44<=Inputs!B10,0,INDEX($T$8:$T$127,A44-Inputs!B10)) | G44: =AD43-F44 | H44: =AE43-IF(A44<=Inputs!B10,0,INDEX($W$8:$W$127,A44-Inputs!B10)) | I44: =H44*Inputs!B14/12 | J44: =C44+E44+F44-I44 | K44: =IF(Inputs!B19=1,MAX(0,Inputs!B5*1000000000-AH43),0) | L44: =MAX(0,J44+K44) | M44: =Inputs!B8*1000000 | N44: =Inputs!B9 | O44: =MAX(1,SQRT(L44/MAX(M44*MAX(N44,0.01)/(1+Inputs!B11),1))) | P44: =MIN(1,A44/12) | Q44: =IF(Inputs!B7=1,MAX(N44,L44*(1+Inputs!B11)/MAX(M44,1)),N44+(N44*O44-N44)*P44) | R44: =IF(Inputs!B7=1,L44*(1+Inputs!B11),M44*Q44) | S44: =R44/(1+Inputs!B11) | T44: =IF(Inputs!B7=1,L44,MIN(S44,L44)) | U44: =IF(Inputs!B19=1,MAX(0,T44-J44),0) | V44: =T44*(1+Inputs!B11) | W44: =V44-T44 | X44: =V44*Inputs!B13*MIN(12,Inputs!B10)/12 | Y44: =W44*Inputs!B14/12 | Z44: =J44+U44-T44+X44-Y44 | AA44: =D44+E44-I44+U44+X44-Y44 | AB44: =IF(U44>0,AB43*(1+Inputs!B15/12)+U44,AB43*(1+Inputs!B15/12)) | AC44: =IF(Inputs!B21>0,AA44/Inputs!B21,0) | AD44: =G44+T44 | AE44: =H44+W44 | AF44: =AD44+AE44 | AG44: =IF(M44>0,V44/M44,0) | AH44: =AH43+U44 | AI44: =IFERROR((1+IRR(VSTACK($AJ$8:INDEX($AJ:$AJ,ROW()-1),-U44+AA44)))^12-1,0) | AJ44: =-U44
A45: =A44+1 | B45: Month 38 | C45: =Z44 | D45: =AA44 | E45: =IF(A45<=12,0,INDEX($V$8:$V$127,A45-12)*Inputs!B13*MAX(0,Inputs!B10-12)/12) | F45: =IF(A45<=Inputs!B10,0,INDEX($T$8:$T$127,A45-Inputs!B10)) | G45: =AD44-F45 | H45: =AE44-IF(A45<=Inputs!B10,0,INDEX($W$8:$W$127,A45-Inputs!B10)) | I45: =H45*Inputs!B14/12 | J45: =C45+E45+F45-I45 | K45: =IF(Inputs!B19=1,MAX(0,Inputs!B5*1000000000-AH44),0) | L45: =MAX(0,J45+K45) | M45: =Inputs!B8*1000000 | N45: =Inputs!B9 | O45: =MAX(1,SQRT(L45/MAX(M45*MAX(N45,0.01)/(1+Inputs!B11),1))) | P45: =MIN(1,A45/12) | Q45: =IF(Inputs!B7=1,MAX(N45,L45*(1+Inputs!B11)/MAX(M45,1)),N45+(N45*O45-N45)*P45) | R45: =IF(Inputs!B7=1,L45*(1+Inputs!B11),M45*Q45) | S45: =R45/(1+Inputs!B11) | T45: =IF(Inputs!B7=1,L45,MIN(S45,L45)) | U45: =IF(Inputs!B19=1,MAX(0,T45-J45),0) | V45: =T45*(1+Inputs!B11) | W45: =V45-T45 | X45: =V45*Inputs!B13*MIN(12,Inputs!B10)/12 | Y45: =W45*Inputs!B14/12 | Z45: =J45+U45-T45+X45-Y45 | AA45: =D45+E45-I45+U45+X45-Y45 | AB45: =IF(U45>0,AB44*(1+Inputs!B15/12)+U45,AB44*(1+Inputs!B15/12)) | AC45: =IF(Inputs!B21>0,AA45/Inputs!B21,0) | AD45: =G45+T45 | AE45: =H45+W45 | AF45: =AD45+AE45 | AG45: =IF(M45>0,V45/M45,0) | AH45: =AH44+U45 | AI45: =IFERROR((1+IRR(VSTACK($AJ$8:INDEX($AJ:$AJ,ROW()-1),-U45+AA45)))^12-1,0) | AJ45: =-U45
A46: =A45+1 | B46: Month 39 | C46: =Z45 | D46: =AA45 | E46: =IF(A46<=12,0,INDEX($V$8:$V$127,A46-12)*Inputs!B13*MAX(0,Inputs!B10-12)/12) | F46: =IF(A46<=Inputs!B10,0,INDEX($T$8:$T$127,A46-Inputs!B10)) | G46: =AD45-F46 | H46: =AE45-IF(A46<=Inputs!B10,0,INDEX($W$8:$W$127,A46-Inputs!B10)) | I46: =H46*Inputs!B14/12 | J46: =C46+E46+F46-I46 | K46: =IF(Inputs!B19=1,MAX(0,Inputs!B5*1000000000-AH45),0) | L46: =MAX(0,J46+K46) | M46: =Inputs!B8*1000000 | N46: =Inputs!B9 | O46: =MAX(1,SQRT(L46/MAX(M46*MAX(N46,0.01)/(1+Inputs!B11),1))) | P46: =MIN(1,A46/12) | Q46: =IF(Inputs!B7=1,MAX(N46,L46*(1+Inputs!B11)/MAX(M46,1)),N46+(N46*O46-N46)*P46) | R46: =IF(Inputs!B7=1,L46*(1+Inputs!B11),M46*Q46) | S46: =R46/(1+Inputs!B11) | T46: =IF(Inputs!B7=1,L46,MIN(S46,L46)) | U46: =IF(Inputs!B19=1,MAX(0,T46-J46),0) | V46: =T46*(1+Inputs!B11) | W46: =V46-T46 | X46: =V46*Inputs!B13*MIN(12,Inputs!B10)/12 | Y46: =W46*Inputs!B14/12 | Z46: =J46+U46-T46+X46-Y46 | AA46: =D46+E46-I46+U46+X46-Y46 | AB46: =IF(U46>0,AB45*(1+Inputs!B15/12)+U46,AB45*(1+Inputs!B15/12)) | AC46: =IF(Inputs!B21>0,AA46/Inputs!B21,0) | AD46: =G46+T46 | AE46: =H46+W46 | AF46: =AD46+AE46 | AG46: =IF(M46>0,V46/M46,0) | AH46: =AH45+U46 | AI46: =IFERROR((1+IRR(VSTACK($AJ$8:INDEX($AJ:$AJ,ROW()-1),-U46+AA46)))^12-1,0) | AJ46: =-U46
A47: =A46+1 | B47: Month 40 | C47: =Z46 | D47: =AA46 | E47: =IF(A47<=12,0,INDEX($V$8:$V$127,A47-12)*Inputs!B13*MAX(0,Inputs!B10-12)/12) | F47: =IF(A47<=Inputs!B10,0,INDEX($T$8:$T$127,A47-Inputs!B10)) | G47: =AD46-F47 | H47: =AE46-IF(A47<=Inputs!B10,0,INDEX($W$8:$W$127,A47-Inputs!B10)) | I47: =H47*Inputs!B14/12 | J47: =C47+E47+F47-I47 | K47: =IF(Inputs!B19=1,MAX(0,Inputs!B5*1000000000-AH46),0) | L47: =MAX(0,J47+K47) | M47: =Inputs!B8*1000000 | N47: =Inputs!B9 | O47: =MAX(1,SQRT(L47/MAX(M47*MAX(N47,0.01)/(1+Inputs!B11),1))) | P47: =MIN(1,A47/12) | Q47: =IF(Inputs!B7=1,MAX(N47,L47*(1+Inputs!B11)/MAX(M47,1)),N47+(N47*O47-N47)*P47) | R47: =IF(Inputs!B7=1,L47*(1+Inputs!B11),M47*Q47) | S47: =R47/(1+Inputs!B11) | T47: =IF(Inputs!B7=1,L47,MIN(S47,L47)) | U47: =IF(Inputs!B19=1,MAX(0,T47-J47),0) | V47: =T47*(1+Inputs!B11) | W47: =V47-T47 | X47: =V47*Inputs!B13*MIN(12,Inputs!B10)/12 | Y47: =W47*Inputs!B14/12 | Z47: =J47+U47-T47+X47-Y47 | AA47: =D47+E47-I47+U47+X47-Y47 | AB47: =IF(U47>0,AB46*(1+Inputs!B15/12)+U47,AB46*(1+Inputs!B15/12)) | AC47: =IF(Inputs!B21>0,AA47/Inputs!B21,0) | AD47: =G47+T47 | AE47: =H47+W47 | AF47: =AD47+AE47 | AG47: =IF(M47>0,V47/M47,0) | AH47: =AH46+U47 | AI47: =IFERROR((1+IRR(VSTACK($AJ$8:INDEX($AJ:$AJ,ROW()-1),-U47+AA47)))^12-1,0) | AJ47: =-U47
A48: =A47+1 | B48: Month 41 | C48: =Z47 | D48: =AA47 | E48: =IF(A48<=12,0,INDEX($V$8:$V$127,A48-12)*Inputs!B13*MAX(0,Inputs!B10-12)/12) | F48: =IF(A48<=Inputs!B10,0,INDEX($T$8:$T$127,A48-Inputs!B10)) | G48: =AD47-F48 | H48: =AE47-IF(A48<=Inputs!B10,0,INDEX($W$8:$W$127,A48-Inputs!B10)) | I48: =H48*Inputs!B14/12 | J48: =C48+E48+F48-I48 | K48: =IF(Inputs!B19=1,MAX(0,Inputs!B5*1000000000-AH47),0) | L48: =MAX(0,J48+K48) | M48: =Inputs!B8*1000000 | N48: =Inputs!B9 | O48: =MAX(1,SQRT(L48/MAX(M48*MAX(N48,0.01)/(1+Inputs!B11),1))) | P48: =MIN(1,A48/12) | Q48: =IF(Inputs!B7=1,MAX(N48,L48*(1+Inputs!B11)/MAX(M48,1)),N48+(N48*O48-N48)*P48) | R48: =IF(Inputs!B7=1,L48*(1+Inputs!B11),M48*Q48) | S48: =R48/(1+Inputs!B11) | T48: =IF(Inputs!B7=1,L48,MIN(S48,L48)) | U48: =IF(Inputs!B19=1,MAX(0,T48-J48),0) | V48: =T48*(1+Inputs!B11) | W48: =V48-T48 | X48: =V48*Inputs!B13*MIN(12,Inputs!B10)/12 | Y48: =W48*Inputs!B14/12 | Z48: =J48+U48-T48+X48-Y48 | AA48: =D48+E48-I48+U48+X48-Y48 | AB48: =IF(U48>0,AB47*(1+Inputs!B15/12)+U48,AB47*(1+Inputs!B15/12)) | AC48: =IF(Inputs!B21>0,AA48/Inputs!B21,0) | AD48: =G48+T48 | AE48: =H48+W48 | AF48: =AD48+AE48 | AG48: =IF(M48>0,V48/M48,0) | AH48: =AH47+U48 | AI48: =IFERROR((1+IRR(VSTACK($AJ$8:INDEX($AJ:$AJ,ROW()-1),-U48+AA48)))^12-1,0) | AJ48: =-U48
A49: =A48+1 | B49: Month 42 | C49: =Z48 | D49: =AA48 | E49: =IF(A49<=12,0,INDEX($V$8:$V$127,A49-12)*Inputs!B13*MAX(0,Inputs!B10-12)/12) | F49: =IF(A49<=Inputs!B10,0,INDEX($T$8:$T$127,A49-Inputs!B10)) | G49: =AD48-F49 | H49: =AE48-IF(A49<=Inputs!B10,0,INDEX($W$8:$W$127,A49-Inputs!B10)) | I49: =H49*Inputs!B14/12 | J49: =C49+E49+F49-I49 | K49: =IF(Inputs!B19=1,MAX(0,Inputs!B5*1000000000-AH48),0) | L49: =MAX(0,J49+K49) | M49: =Inputs!B8*1000000 | N49: =Inputs!B9 | O49: =MAX(1,SQRT(L49/MAX(M49*MAX(N49,0.01)/(1+Inputs!B11),1))) | P49: =MIN(1,A49/12) | Q49: =IF(Inputs!B7=1,MAX(N49,L49*(1+Inputs!B11)/MAX(M49,1)),N49+(N49*O49-N49)*P49) | R49: =IF(Inputs!B7=1,L49*(1+Inputs!B11),M49*Q49) | S49: =R49/(1+Inputs!B11) | T49: =IF(Inputs!B7=1,L49,MIN(S49,L49)) | U49: =IF(Inputs!B19=1,MAX(0,T49-J49),0) | V49: =T49*(1+Inputs!B11) | W49: =V49-T49 | X49: =V49*Inputs!B13*MIN(12,Inputs!B10)/12 | Y49: =W49*Inputs!B14/12 | Z49: =J49+U49-T49+X49-Y49 | AA49: =D49+E49-I49+U49+X49-Y49 | AB49: =IF(U49>0,AB48*(1+Inputs!B15/12)+U49,AB48*(1+Inputs!B15/12)) | AC49: =IF(Inputs!B21>0,AA49/Inputs!B21,0) | AD49: =G49+T49 | AE49: =H49+W49 | AF49: =AD49+AE49 | AG49: =IF(M49>0,V49/M49,0) | AH49: =AH48+U49 | AI49: =IFERROR((1+IRR(VSTACK($AJ$8:INDEX($AJ:$AJ,ROW()-1),-U49+AA49)))^12-1,0) | AJ49: =-U49
A50: =A49+1 | B50: Month 43 | C50: =Z49 | D50: =AA49 | E50: =IF(A50<=12,0,INDEX($V$8:$V$127,A50-12)*Inputs!B13*MAX(0,Inputs!B10-12)/12) | F50: =IF(A50<=Inputs!B10,0,INDEX($T$8:$T$127,A50-Inputs!B10)) | G50: =AD49-F50 | H50: =AE49-IF(A50<=Inputs!B10,0,INDEX($W$8:$W$127,A50-Inputs!B10)) | I50: =H50*Inputs!B14/12 | J50: =C50+E50+F50-I50 | K50: =IF(Inputs!B19=1,MAX(0,Inputs!B5*1000000000-AH49),0) | L50: =MAX(0,J50+K50) | M50: =Inputs!B8*1000000 | N50: =Inputs!B9 | O50: =MAX(1,SQRT(L50/MAX(M50*MAX(N50,0.01)/(1+Inputs!B11),1))) | P50: =MIN(1,A50/12) | Q50: =IF(Inputs!B7=1,MAX(N50,L50*(1+Inputs!B11)/MAX(M50,1)),N50+(N50*O50-N50)*P50) | R50: =IF(Inputs!B7=1,L50*(1+Inputs!B11),M50*Q50) | S50: =R50/(1+Inputs!B11) | T50: =IF(Inputs!B7=1,L50,MIN(S50,L50)) | U50: =IF(Inputs!B19=1,MAX(0,T50-J50),0) | V50: =T50*(1+Inputs!B11) | W50: =V50-T50 | X50: =V50*Inputs!B13*MIN(12,Inputs!B10)/12 | Y50: =W50*Inputs!B14/12 | Z50: =J50+U50-T50+X50-Y50 | AA50: =D50+E50-I50+U50+X50-Y50 | AB50: =IF(U50>0,AB49*(1+Inputs!B15/12)+U50,AB49*(1+Inputs!B15/12)) | AC50: =IF(Inputs!B21>0,AA50/Inputs!B21,0) | AD50: =G50+T50 | AE50: =H50+W50 | AF50: =AD50+AE50 | AG50: =IF(M50>0,V50/M50,0) | AH50: =AH49+U50 | AI50: =IFERROR((1+IRR(VSTACK($AJ$8:INDEX($AJ:$AJ,ROW()-1),-U50+AA50)))^12-1,0) | AJ50: =-U50
A51: =A50+1 | B51: Month 44 | C51: =Z50 | D51: =AA50 | E51: =IF(A51<=12,0,INDEX($V$8:$V$127,A51-12)*Inputs!B13*MAX(0,Inputs!B10-12)/12) | F51: =IF(A51<=Inputs!B10,0,INDEX($T$8:$T$127,A51-Inputs!B10)) | G51: =AD50-F51 | H51: =AE50-IF(A51<=Inputs!B10,0,INDEX($W$8:$W$127,A51-Inputs!B10)) | I51: =H51*Inputs!B14/12 | J51: =C51+E51+F51-I51 | K51: =IF(Inputs!B19=1,MAX(0,Inputs!B5*1000000000-AH50),0) | L51: =MAX(0,J51+K51) | M51: =Inputs!B8*1000000 | N51: =Inputs!B9 | O51: =MAX(1,SQRT(L51/MAX(M51*MAX(N51,0.01)/(1+Inputs!B11),1))) | P51: =MIN(1,A51/12) | Q51: =IF(Inputs!B7=1,MAX(N51,L51*(1+Inputs!B11)/MAX(M51,1)),N51+(N51*O51-N51)*P51) | R51: =IF(Inputs!B7=1,L51*(1+Inputs!B11),M51*Q51) | S51: =R51/(1+Inputs!B11) | T51: =IF(Inputs!B7=1,L51,MIN(S51,L51)) | U51: =IF(Inputs!B19=1,MAX(0,T51-J51),0) | V51: =T51*(1+Inputs!B11) | W51: =V51-T51 | X51: =V51*Inputs!B13*MIN(12,Inputs!B10)/12 | Y51: =W51*Inputs!B14/12 | Z51: =J51+U51-T51+X51-Y51 | AA51: =D51+E51-I51+U51+X51-Y51 | AB51: =IF(U51>0,AB50*(1+Inputs!B15/12)+U51,AB50*(1+Inputs!B15/12)) | AC51: =IF(Inputs!B21>0,AA51/Inputs!B21,0) | AD51: =G51+T51 | AE51: =H51+W51 | AF51: =AD51+AE51 | AG51: =IF(M51>0,V51/M51,0) | AH51: =AH50+U51 | AI51: =IFERROR((1+IRR(VSTACK($AJ$8:INDEX($AJ:$AJ,ROW()-1),-U51+AA51)))^12-1,0) | AJ51: =-U51
A52: =A51+1 | B52: Month 45 | C52: =Z51 | D52: =AA51 | E52: =IF(A52<=12,0,INDEX($V$8:$V$127,A52-12)*Inputs!B13*MAX(0,Inputs!B10-12)/12) | F52: =IF(A52<=Inputs!B10,0,INDEX($T$8:$T$127,A52-Inputs!B10)) | G52: =AD51-F52 | H52: =AE51-IF(A52<=Inputs!B10,0,INDEX($W$8:$W$127,A52-Inputs!B10)) | I52: =H52*Inputs!B14/12 | J52: =C52+E52+F52-I52 | K52: =IF(Inputs!B19=1,MAX(0,Inputs!B5*1000000000-AH51),0) | L52: =MAX(0,J52+K52) | M52: =Inputs!B8*1000000 | N52: =Inputs!B9 | O52: =MAX(1,SQRT(L52/MAX(M52*MAX(N52,0.01)/(1+Inputs!B11),1))) | P52: =MIN(1,A52/12) | Q52: =IF(Inputs!B7=1,MAX(N52,L52*(1+Inputs!B11)/MAX(M52,1)),N52+(N52*O52-N52)*P52) | R52: =IF(Inputs!B7=1,L52*(1+Inputs!B11),M52*Q52) | S52: =R52/(1+Inputs!B11) | T52: =IF(Inputs!B7=1,L52,MIN(S52,L52)) | U52: =IF(Inputs!B19=1,MAX(0,T52-J52),0) | V52: =T52*(1+Inputs!B11) | W52: =V52-T52 | X52: =V52*Inputs!B13*MIN(12,Inputs!B10)/12 | Y52: =W52*Inputs!B14/12 | Z52: =J52+U52-T52+X52-Y52 | AA52: =D52+E52-I52+U52+X52-Y52 | AB52: =IF(U52>0,AB51*(1+Inputs!B15/12)+U52,AB51*(1+Inputs!B15/12)) | AC52: =IF(Inputs!B21>0,AA52/Inputs!B21,0) | AD52: =G52+T52 | AE52: =H52+W52 | AF52: =AD52+AE52 | AG52: =IF(M52>0,V52/M52,0) | AH52: =AH51+U52 | AI52: =IFERROR((1+IRR(VSTACK($AJ$8:INDEX($AJ:$AJ,ROW()-1),-U52+AA52)))^12-1,0) | AJ52: =-U52
A53: =A52+1 | B53: Month 46 | C53: =Z52 | D53: =AA52 | E53: =IF(A53<=12,0,INDEX($V$8:$V$127,A53-12)*Inputs!B13*MAX(0,Inputs!B10-12)/12) | F53: =IF(A53<=Inputs!B10,0,INDEX($T$8:$T$127,A53-Inputs!B10)) | G53: =AD52-F53 | H53: =AE52-IF(A53<=Inputs!B10,0,INDEX($W$8:$W$127,A53-Inputs!B10)) | I53: =H53*Inputs!B14/12 | J53: =C53+E53+F53-I53 | K53: =IF(Inputs!B19=1,MAX(0,Inputs!B5*1000000000-AH52),0) | L53: =MAX(0,J53+K53) | M53: =Inputs!B8*1000000 | N53: =Inputs!B9 | O53: =MAX(1,SQRT(L53/MAX(M53*MAX(N53,0.01)/(1+Inputs!B11),1))) | P53: =MIN(1,A53/12) | Q53: =IF(Inputs!B7=1,MAX(N53,L53*(1+Inputs!B11)/MAX(M53,1)),N53+(N53*O53-N53)*P53) | R53: =IF(Inputs!B7=1,L53*(1+Inputs!B11),M53*Q53) | S53: =R53/(1+Inputs!B11) | T53: =IF(Inputs!B7=1,L53,MIN(S53,L53)) | U53: =IF(Inputs!B19=1,MAX(0,T53-J53),0) | V53: =T53*(1+Inputs!B11) | W53: =V53-T53 | X53: =V53*Inputs!B13*MIN(12,Inputs!B10)/12 | Y53: =W53*Inputs!B14/12 | Z53: =J53+U53-T53+X53-Y53 | AA53: =D53+E53-I53+U53+X53-Y53 | AB53: =IF(U53>0,AB52*(1+Inputs!B15/12)+U53,AB52*(1+Inputs!B15/12)) | AC53: =IF(Inputs!B21>0,AA53/Inputs!B21,0) | AD53: =G53+T53 | AE53: =H53+W53 | AF53: =AD53+AE53 | AG53: =IF(M53>0,V53/M53,0) | AH53: =AH52+U53 | AI53: =IFERROR((1+IRR(VSTACK($AJ$8:INDEX($AJ:$AJ,ROW()-1),-U53+AA53)))^12-1,0) | AJ53: =-U53
A54: =A53+1 | B54: Month 47 | C54: =Z53 | D54: =AA53 | E54: =IF(A54<=12,0,INDEX($V$8:$V$127,A54-12)*Inputs!B13*MAX(0,Inputs!B10-12)/12) | F54: =IF(A54<=Inputs!B10,0,INDEX($T$8:$T$127,A54-Inputs!B10)) | G54: =AD53-F54 | H54: =AE53-IF(A54<=Inputs!B10,0,INDEX($W$8:$W$127,A54-Inputs!B10)) | I54: =H54*Inputs!B14/12 | J54: =C54+E54+F54-I54 | K54: =IF(Inputs!B19=1,MAX(0,Inputs!B5*1000000000-AH53),0) | L54: =MAX(0,J54+K54) | M54: =Inputs!B8*1000000 | N54: =Inputs!B9 | O54: =MAX(1,SQRT(L54/MAX(M54*MAX(N54,0.01)/(1+Inputs!B11),1))) | P54: =MIN(1,A54/12) | Q54: =IF(Inputs!B7=1,MAX(N54,L54*(1+Inputs!B11)/MAX(M54,1)),N54+(N54*O54-N54)*P54) | R54: =IF(Inputs!B7=1,L54*(1+Inputs!B11),M54*Q54) | S54: =R54/(1+Inputs!B11) | T54: =IF(Inputs!B7=1,L54,MIN(S54,L54)) | U54: =IF(Inputs!B19=1,MAX(0,T54-J54),0) | V54: =T54*(1+Inputs!B11) | W54: =V54-T54 | X54: =V54*Inputs!B13*MIN(12,Inputs!B10)/12 | Y54: =W54*Inputs!B14/12 | Z54: =J54+U54-T54+X54-Y54 | AA54: =D54+E54-I54+U54+X54-Y54 | AB54: =IF(U54>0,AB53*(1+Inputs!B15/12)+U54,AB53*(1+Inputs!B15/12)) | AC54: =IF(Inputs!B21>0,AA54/Inputs!B21,0) | AD54: =G54+T54 | AE54: =H54+W54 | AF54: =AD54+AE54 | AG54: =IF(M54>0,V54/M54,0) | AH54: =AH53+U54 | AI54: =IFERROR((1+IRR(VSTACK($AJ$8:INDEX($AJ:$AJ,ROW()-1),-U54+AA54)))^12-1,0) | AJ54: =-U54
A55: =A54+1 | B55: Month 48 | C55: =Z54 | D55: =AA54 | E55: =IF(A55<=12,0,INDEX($V$8:$V$127,A55-12)*Inputs!B13*MAX(0,Inputs!B10-12)/12) | F55: =IF(A55<=Inputs!B10,0,INDEX($T$8:$T$127,A55-Inputs!B10)) | G55: =AD54-F55 | H55: =AE54-IF(A55<=Inputs!B10,0,INDEX($W$8:$W$127,A55-Inputs!B10)) | I55: =H55*Inputs!B14/12 | J55: =C55+E55+F55-I55 | K55: =IF(Inputs!B19=1,MAX(0,Inputs!B5*1000000000-AH54),0) | L55: =MAX(0,J55+K55) | M55: =Inputs!B8*1000000 | N55: =Inputs!B9 | O55: =MAX(1,SQRT(L55/MAX(M55*MAX(N55,0.01)/(1+Inputs!B11),1))) | P55: =MIN(1,A55/12) | Q55: =IF(Inputs!B7=1,MAX(N55,L55*(1+Inputs!B11)/MAX(M55,1)),N55+(N55*O55-N55)*P55) | R55: =IF(Inputs!B7=1,L55*(1+Inputs!B11),M55*Q55) | S55: =R55/(1+Inputs!B11) | T55: =IF(Inputs!B7=1,L55,MIN(S55,L55)) | U55: =IF(Inputs!B19=1,MAX(0,T55-J55),0) | V55: =T55*(1+Inputs!B11) | W55: =V55-T55 | X55: =V55*Inputs!B13*MIN(12,Inputs!B10)/12 | Y55: =W55*Inputs!B14/12 | Z55: =J55+U55-T55+X55-Y55 | AA55: =D55+E55-I55+U55+X55-Y55 | AB55: =IF(U55>0,AB54*(1+Inputs!B15/12)+U55,AB54*(1+Inputs!B15/12)) | AC55: =IF(Inputs!B21>0,AA55/Inputs!B21,0) | AD55: =G55+T55 | AE55: =H55+W55 | AF55: =AD55+AE55 | AG55: =IF(M55>0,V55/M55,0) | AH55: =AH54+U55 | AI55: =IFERROR((1+IRR(VSTACK($AJ$8:INDEX($AJ:$AJ,ROW()-1),-U55+AA55)))^12-1,0) | AJ55: =-U55
A56: =A55+1 | B56: Month 49 | C56: =Z55 | D56: =AA55 | E56: =IF(A56<=12,0,INDEX($V$8:$V$127,A56-12)*Inputs!B13*MAX(0,Inputs!B10-12)/12) | F56: =IF(A56<=Inputs!B10,0,INDEX($T$8:$T$127,A56-Inputs!B10)) | G56: =AD55-F56 | H56: =AE55-IF(A56<=Inputs!B10,0,INDEX($W$8:$W$127,A56-Inputs!B10)) | I56: =H56*Inputs!B14/12 | J56: =C56+E56+F56-I56 | K56: =IF(Inputs!B19=1,MAX(0,Inputs!B5*1000000000-AH55),0) | L56: =MAX(0,J56+K56) | M56: =Inputs!B8*1000000 | N56: =Inputs!B9 | O56: =MAX(1,SQRT(L56/MAX(M56*MAX(N56,0.01)/(1+Inputs!B11),1))) | P56: =MIN(1,A56/12) | Q56: =IF(Inputs!B7=1,MAX(N56,L56*(1+Inputs!B11)/MAX(M56,1)),N56+(N56*O56-N56)*P56) | R56: =IF(Inputs!B7=1,L56*(1+Inputs!B11),M56*Q56) | S56: =R56/(1+Inputs!B11) | T56: =IF(Inputs!B7=1,L56,MIN(S56,L56)) | U56: =IF(Inputs!B19=1,MAX(0,T56-J56),0) | V56: =T56*(1+Inputs!B11) | W56: =V56-T56 | X56: =V56*Inputs!B13*MIN(12,Inputs!B10)/12 | Y56: =W56*Inputs!B14/12 | Z56: =J56+U56-T56+X56-Y56 | AA56: =D56+E56-I56+U56+X56-Y56 | AB56: =IF(U56>0,AB55*(1+Inputs!B15/12)+U56,AB55*(1+Inputs!B15/12)) | AC56: =IF(Inputs!B21>0,AA56/Inputs!B21,0) | AD56: =G56+T56 | AE56: =H56+W56 | AF56: =AD56+AE56 | AG56: =IF(M56>0,V56/M56,0) | AH56: =AH55+U56 | AI56: =IFERROR((1+IRR(VSTACK($AJ$8:INDEX($AJ:$AJ,ROW()-1),-U56+AA56)))^12-1,0) | AJ56: =-U56
A57: =A56+1 | B57: Month 50 | C57: =Z56 | D57: =AA56 | E57: =IF(A57<=12,0,INDEX($V$8:$V$127,A57-12)*Inputs!B13*MAX(0,Inputs!B10-12)/12) | F57: =IF(A57<=Inputs!B10,0,INDEX($T$8:$T$127,A57-Inputs!B10)) | G57: =AD56-F57 | H57: =AE56-IF(A57<=Inputs!B10,0,INDEX($W$8:$W$127,A57-Inputs!B10)) | I57: =H57*Inputs!B14/12 | J57: =C57+E57+F57-I57 | K57: =IF(Inputs!B19=1,MAX(0,Inputs!B5*1000000000-AH56),0) | L57: =MAX(0,J57+K57) | M57: =Inputs!B8*1000000 | N57: =Inputs!B9 | O57: =MAX(1,SQRT(L57/MAX(M57*MAX(N57,0.01)/(1+Inputs!B11),1))) | P57: =MIN(1,A57/12) | Q57: =IF(Inputs!B7=1,MAX(N57,L57*(1+Inputs!B11)/MAX(M57,1)),N57+(N57*O57-N57)*P57) | R57: =IF(Inputs!B7=1,L57*(1+Inputs!B11),M57*Q57) | S57: =R57/(1+Inputs!B11) | T57: =IF(Inputs!B7=1,L57,MIN(S57,L57)) | U57: =IF(Inputs!B19=1,MAX(0,T57-J57),0) | V57: =T57*(1+Inputs!B11) | W57: =V57-T57 | X57: =V57*Inputs!B13*MIN(12,Inputs!B10)/12 | Y57: =W57*Inputs!B14/12 | Z57: =J57+U57-T57+X57-Y57 | AA57: =D57+E57-I57+U57+X57-Y57 | AB57: =IF(U57>0,AB56*(1+Inputs!B15/12)+U57,AB56*(1+Inputs!B15/12)) | AC57: =IF(Inputs!B21>0,AA57/Inputs!B21,0) | AD57: =G57+T57 | AE57: =H57+W57 | AF57: =AD57+AE57 | AG57: =IF(M57>0,V57/M57,0) | AH57: =AH56+U57 | AI57: =IFERROR((1+IRR(VSTACK($AJ$8:INDEX($AJ:$AJ,ROW()-1),-U57+AA57)))^12-1,0) | AJ57: =-U57
A58: =A57+1 | B58: Month 51 | C58: =Z57 | D58: =AA57 | E58: =IF(A58<=12,0,INDEX($V$8:$V$127,A58-12)*Inputs!B13*MAX(0,Inputs!B10-12)/12) | F58: =IF(A58<=Inputs!B10,0,INDEX($T$8:$T$127,A58-Inputs!B10)) | G58: =AD57-F58 | H58: =AE57-IF(A58<=Inputs!B10,0,INDEX($W$8:$W$127,A58-Inputs!B10)) | I58: =H58*Inputs!B14/12 | J58: =C58+E58+F58-I58 | K58: =IF(Inputs!B19=1,MAX(0,Inputs!B5*1000000000-AH57),0) | L58: =MAX(0,J58+K58) | M58: =Inputs!B8*1000000 | N58: =Inputs!B9 | O58: =MAX(1,SQRT(L58/MAX(M58*MAX(N58,0.01)/(1+Inputs!B11),1))) | P58: =MIN(1,A58/12) | Q58: =IF(Inputs!B7=1,MAX(N58,L58*(1+Inputs!B11)/MAX(M58,1)),N58+(N58*O58-N58)*P58) | R58: =IF(Inputs!B7=1,L58*(1+Inputs!B11),M58*Q58) | S58: =R58/(1+Inputs!B11) | T58: =IF(Inputs!B7=1,L58,MIN(S58,L58)) | U58: =IF(Inputs!B19=1,MAX(0,T58-J58),0) | V58: =T58*(1+Inputs!B11) | W58: =V58-T58 | X58: =V58*Inputs!B13*MIN(12,Inputs!B10)/12 | Y58: =W58*Inputs!B14/12 | Z58: =J58+U58-T58+X58-Y58 | AA58: =D58+E58-I58+U58+X58-Y58 | AB58: =IF(U58>0,AB57*(1+Inputs!B15/12)+U58,AB57*(1+Inputs!B15/12)) | AC58: =IF(Inputs!B21>0,AA58/Inputs!B21,0) | AD58: =G58+T58 | AE58: =H58+W58 | AF58: =AD58+AE58 | AG58: =IF(M58>0,V58/M58,0) | AH58: =AH57+U58 | AI58: =IFERROR((1+IRR(VSTACK($AJ$8:INDEX($AJ:$AJ,ROW()-1),-U58+AA58)))^12-1,0) | AJ58: =-U58
A59: =A58+1 | B59: Month 52 | C59: =Z58 | D59: =AA58 | E59: =IF(A59<=12,0,INDEX($V$8:$V$127,A59-12)*Inputs!B13*MAX(0,Inputs!B10-12)/12) | F59: =IF(A59<=Inputs!B10,0,INDEX($T$8:$T$127,A59-Inputs!B10)) | G59: =AD58-F59 | H59: =AE58-IF(A59<=Inputs!B10,0,INDEX($W$8:$W$127,A59-Inputs!B10)) | I59: =H59*Inputs!B14/12 | J59: =C59+E59+F59-I59 | K59: =IF(Inputs!B19=1,MAX(0,Inputs!B5*1000000000-AH58),0) | L59: =MAX(0,J59+K59) | M59: =Inputs!B8*1000000 | N59: =Inputs!B9 | O59: =MAX(1,SQRT(L59/MAX(M59*MAX(N59,0.01)/(1+Inputs!B11),1))) | P59: =MIN(1,A59/12) | Q59: =IF(Inputs!B7=1,MAX(N59,L59*(1+Inputs!B11)/MAX(M59,1)),N59+(N59*O59-N59)*P59) | R59: =IF(Inputs!B7=1,L59*(1+Inputs!B11),M59*Q59) | S59: =R59/(1+Inputs!B11) | T59: =IF(Inputs!B7=1,L59,MIN(S59,L59)) | U59: =IF(Inputs!B19=1,MAX(0,T59-J59),0) | V59: =T59*(1+Inputs!B11) | W59: =V59-T59 | X59: =V59*Inputs!B13*MIN(12,Inputs!B10)/12 | Y59: =W59*Inputs!B14/12 | Z59: =J59+U59-T59+X59-Y59 | AA59: =D59+E59-I59+U59+X59-Y59 | AB59: =IF(U59>0,AB58*(1+Inputs!B15/12)+U59,AB58*(1+Inputs!B15/12)) | AC59: =IF(Inputs!B21>0,AA59/Inputs!B21,0) | AD59: =G59+T59 | AE59: =H59+W59 | AF59: =AD59+AE59 | AG59: =IF(M59>0,V59/M59,0) | AH59: =AH58+U59 | AI59: =IFERROR((1+IRR(VSTACK($AJ$8:INDEX($AJ:$AJ,ROW()-1),-U59+AA59)))^12-1,0) | AJ59: =-U59
A60: =A59+1 | B60: Month 53 | C60: =Z59 | D60: =AA59 | E60: =IF(A60<=12,0,INDEX($V$8:$V$127,A60-12)*Inputs!B13*MAX(0,Inputs!B10-12)/12) | F60: =IF(A60<=Inputs!B10,0,INDEX($T$8:$T$127,A60-Inputs!B10)) | G60: =AD59-F60 | H60: =AE59-IF(A60<=Inputs!B10,0,INDEX($W$8:$W$127,A60-Inputs!B10)) | I60: =H60*Inputs!B14/12 | J60: =C60+E60+F60-I60 | K60: =IF(Inputs!B19=1,MAX(0,Inputs!B5*1000000000-AH59),0) | L60: =MAX(0,J60+K60) | M60: =Inputs!B8*1000000 | N60: =Inputs!B9 | O60: =MAX(1,SQRT(L60/MAX(M60*MAX(N60,0.01)/(1+Inputs!B11),1))) | P60: =MIN(1,A60/12) | Q60: =IF(Inputs!B7=1,MAX(N60,L60*(1+Inputs!B11)/MAX(M60,1)),N60+(N60*O60-N60)*P60) | R60: =IF(Inputs!B7=1,L60*(1+Inputs!B11),M60*Q60) | S60: =R60/(1+Inputs!B11) | T60: =IF(Inputs!B7=1,L60,MIN(S60,L60)) | U60: =IF(Inputs!B19=1,MAX(0,T60-J60),0) | V60: =T60*(1+Inputs!B11) | W60: =V60-T60 | X60: =V60*Inputs!B13*MIN(12,Inputs!B10)/12 | Y60: =W60*Inputs!B14/12 | Z60: =J60+U60-T60+X60-Y60 | AA60: =D60+E60-I60+U60+X60-Y60 | AB60: =IF(U60>0,AB59*(1+Inputs!B15/12)+U60,AB59*(1+Inputs!B15/12)) | AC60: =IF(Inputs!B21>0,AA60/Inputs!B21,0) | AD60: =G60+T60 | AE60: =H60+W60 | AF60: =AD60+AE60 | AG60: =IF(M60>0,V60/M60,0) | AH60: =AH59+U60 | AI60: =IFERROR((1+IRR(VSTACK($AJ$8:INDEX($AJ:$AJ,ROW()-1),-U60+AA60)))^12-1,0) | AJ60: =-U60
A61: =A60+1 | B61: Month 54 | C61: =Z60 | D61: =AA60 | E61: =IF(A61<=12,0,INDEX($V$8:$V$127,A61-12)*Inputs!B13*MAX(0,Inputs!B10-12)/12) | F61: =IF(A61<=Inputs!B10,0,INDEX($T$8:$T$127,A61-Inputs!B10)) | G61: =AD60-F61 | H61: =AE60-IF(A61<=Inputs!B10,0,INDEX($W$8:$W$127,A61-Inputs!B10)) | I61: =H61*Inputs!B14/12 | J61: =C61+E61+F61-I61 | K61: =IF(Inputs!B19=1,MAX(0,Inputs!B5*1000000000-AH60),0) | L61: =MAX(0,J61+K61) | M61: =Inputs!B8*1000000 | N61: =Inputs!B9 | O61: =MAX(1,SQRT(L61/MAX(M61*MAX(N61,0.01)/(1+Inputs!B11),1))) | P61: =MIN(1,A61/12) | Q61: =IF(Inputs!B7=1,MAX(N61,L61*(1+Inputs!B11)/MAX(M61,1)),N61+(N61*O61-N61)*P61) | R61: =IF(Inputs!B7=1,L61*(1+Inputs!B11),M61*Q61) | S61: =R61/(1+Inputs!B11) | T61: =IF(Inputs!B7=1,L61,MIN(S61,L61)) | U61: =IF(Inputs!B19=1,MAX(0,T61-J61),0) | V61: =T61*(1+Inputs!B11) | W61: =V61-T61 | X61: =V61*Inputs!B13*MIN(12,Inputs!B10)/12 | Y61: =W61*Inputs!B14/12 | Z61: =J61+U61-T61+X61-Y61 | AA61: =D61+E61-I61+U61+X61-Y61 | AB61: =IF(U61>0,AB60*(1+Inputs!B15/12)+U61,AB60*(1+Inputs!B15/12)) | AC61: =IF(Inputs!B21>0,AA61/Inputs!B21,0) | AD61: =G61+T61 | AE61: =H61+W61 | AF61: =AD61+AE61 | AG61: =IF(M61>0,V61/M61,0) | AH61: =AH60+U61 | AI61: =IFERROR((1+IRR(VSTACK($AJ$8:INDEX($AJ:$AJ,ROW()-1),-U61+AA61)))^12-1,0) | AJ61: =-U61
A62: =A61+1 | B62: Month 55 | C62: =Z61 | D62: =AA61 | E62: =IF(A62<=12,0,INDEX($V$8:$V$127,A62-12)*Inputs!B13*MAX(0,Inputs!B10-12)/12) | F62: =IF(A62<=Inputs!B10,0,INDEX($T$8:$T$127,A62-Inputs!B10)) | G62: =AD61-F62 | H62: =AE61-IF(A62<=Inputs!B10,0,INDEX($W$8:$W$127,A62-Inputs!B10)) | I62: =H62*Inputs!B14/12 | J62: =C62+E62+F62-I62 | K62: =IF(Inputs!B19=1,MAX(0,Inputs!B5*1000000000-AH61),0) | L62: =MAX(0,J62+K62) | M62: =Inputs!B8*1000000 | N62: =Inputs!B9 | O62: =MAX(1,SQRT(L62/MAX(M62*MAX(N62,0.01)/(1+Inputs!B11),1))) | P62: =MIN(1,A62/12) | Q62: =IF(Inputs!B7=1,MAX(N62,L62*(1+Inputs!B11)/MAX(M62,1)),N62+(N62*O62-N62)*P62) | R62: =IF(Inputs!B7=1,L62*(1+Inputs!B11),M62*Q62) | S62: =R62/(1+Inputs!B11) | T62: =IF(Inputs!B7=1,L62,MIN(S62,L62)) | U62: =IF(Inputs!B19=1,MAX(0,T62-J62),0) | V62: =T62*(1+Inputs!B11) | W62: =V62-T62 | X62: =V62*Inputs!B13*MIN(12,Inputs!B10)/12 | Y62: =W62*Inputs!B14/12 | Z62: =J62+U62-T62+X62-Y62 | AA62: =D62+E62-I62+U62+X62-Y62 | AB62: =IF(U62>0,AB61*(1+Inputs!B15/12)+U62,AB61*(1+Inputs!B15/12)) | AC62: =IF(Inputs!B21>0,AA62/Inputs!B21,0) | AD62: =G62+T62 | AE62: =H62+W62 | AF62: =AD62+AE62 | AG62: =IF(M62>0,V62/M62,0) | AH62: =AH61+U62 | AI62: =IFERROR((1+IRR(VSTACK($AJ$8:INDEX($AJ:$AJ,ROW()-1),-U62+AA62)))^12-1,0) | AJ62: =-U62
A63: =A62+1 | B63: Month 56 | C63: =Z62 | D63: =AA62 | E63: =IF(A63<=12,0,INDEX($V$8:$V$127,A63-12)*Inputs!B13*MAX(0,Inputs!B10-12)/12) | F63: =IF(A63<=Inputs!B10,0,INDEX($T$8:$T$127,A63-Inputs!B10)) | G63: =AD62-F63 | H63: =AE62-IF(A63<=Inputs!B10,0,INDEX($W$8:$W$127,A63-Inputs!B10)) | I63: =H63*Inputs!B14/12 | J63: =C63+E63+F63-I63 | K63: =IF(Inputs!B19=1,MAX(0,Inputs!B5*1000000000-AH62),0) | L63: =MAX(0,J63+K63) | M63: =Inputs!B8*1000000 | N63: =Inputs!B9 | O63: =MAX(1,SQRT(L63/MAX(M63*MAX(N63,0.01)/(1+Inputs!B11),1))) | P63: =MIN(1,A63/12) | Q63: =IF(Inputs!B7=1,MAX(N63,L63*(1+Inputs!B11)/MAX(M63,1)),N63+(N63*O63-N63)*P63) | R63: =IF(Inputs!B7=1,L63*(1+Inputs!B11),M63*Q63) | S63: =R63/(1+Inputs!B11) | T63: =IF(Inputs!B7=1,L63,MIN(S63,L63)) | U63: =IF(Inputs!B19=1,MAX(0,T63-J63),0) | V63: =T63*(1+Inputs!B11) | W63: =V63-T63 | X63: =V63*Inputs!B13*MIN(12,Inputs!B10)/12 | Y63: =W63*Inputs!B14/12 | Z63: =J63+U63-T63+X63-Y63 | AA63: =D63+E63-I63+U63+X63-Y63 | AB63: =IF(U63>0,AB62*(1+Inputs!B15/12)+U63,AB62*(1+Inputs!B15/12)) | AC63: =IF(Inputs!B21>0,AA63/Inputs!B21,0) | AD63: =G63+T63 | AE63: =H63+W63 | AF63: =AD63+AE63 | AG63: =IF(M63>0,V63/M63,0) | AH63: =AH62+U63 | AI63: =IFERROR((1+IRR(VSTACK($AJ$8:INDEX($AJ:$AJ,ROW()-1),-U63+AA63)))^12-1,0) | AJ63: =-U63
A64: =A63+1 | B64: Month 57 | C64: =Z63 | D64: =AA63 | E64: =IF(A64<=12,0,INDEX($V$8:$V$127,A64-12)*Inputs!B13*MAX(0,Inputs!B10-12)/12) | F64: =IF(A64<=Inputs!B10,0,INDEX($T$8:$T$127,A64-Inputs!B10)) | G64: =AD63-F64 | H64: =AE63-IF(A64<=Inputs!B10,0,INDEX($W$8:$W$127,A64-Inputs!B10)) | I64: =H64*Inputs!B14/12 | J64: =C64+E64+F64-I64 | K64: =IF(Inputs!B19=1,MAX(0,Inputs!B5*1000000000-AH63),0) | L64: =MAX(0,J64+K64) | M64: =Inputs!B8*1000000 | N64: =Inputs!B9 | O64: =MAX(1,SQRT(L64/MAX(M64*MAX(N64,0.01)/(1+Inputs!B11),1))) | P64: =MIN(1,A64/12) | Q64: =IF(Inputs!B7=1,MAX(N64,L64*(1+Inputs!B11)/MAX(M64,1)),N64+(N64*O64-N64)*P64) | R64: =IF(Inputs!B7=1,L64*(1+Inputs!B11),M64*Q64) | S64: =R64/(1+Inputs!B11) | T64: =IF(Inputs!B7=1,L64,MIN(S64,L64)) | U64: =IF(Inputs!B19=1,MAX(0,T64-J64),0) | V64: =T64*(1+Inputs!B11) | W64: =V64-T64 | X64: =V64*Inputs!B13*MIN(12,Inputs!B10)/12 | Y64: =W64*Inputs!B14/12 | Z64: =J64+U64-T64+X64-Y64 | AA64: =D64+E64-I64+U64+X64-Y64 | AB64: =IF(U64>0,AB63*(1+Inputs!B15/12)+U64,AB63*(1+Inputs!B15/12)) | AC64: =IF(Inputs!B21>0,AA64/Inputs!B21,0) | AD64: =G64+T64 | AE64: =H64+W64 | AF64: =AD64+AE64 | AG64: =IF(M64>0,V64/M64,0) | AH64: =AH63+U64 | AI64: =IFERROR((1+IRR(VSTACK($AJ$8:INDEX($AJ:$AJ,ROW()-1),-U64+AA64)))^12-1,0) | AJ64: =-U64
A65: =A64+1 | B65: Month 58 | C65: =Z64 | D65: =AA64 | E65: =IF(A65<=12,0,INDEX($V$8:$V$127,A65-12)*Inputs!B13*MAX(0,Inputs!B10-12)/12) | F65: =IF(A65<=Inputs!B10,0,INDEX($T$8:$T$127,A65-Inputs!B10)) | G65: =AD64-F65 | H65: =AE64-IF(A65<=Inputs!B10,0,INDEX($W$8:$W$127,A65-Inputs!B10)) | I65: =H65*Inputs!B14/12 | J65: =C65+E65+F65-I65 | K65: =IF(Inputs!B19=1,MAX(0,Inputs!B5*1000000000-AH64),0) | L65: =MAX(0,J65+K65) | M65: =Inputs!B8*1000000 | N65: =Inputs!B9 | O65: =MAX(1,SQRT(L65/MAX(M65*MAX(N65,0.01)/(1+Inputs!B11),1))) | P65: =MIN(1,A65/12) | Q65: =IF(Inputs!B7=1,MAX(N65,L65*(1+Inputs!B11)/MAX(M65,1)),N65+(N65*O65-N65)*P65) | R65: =IF(Inputs!B7=1,L65*(1+Inputs!B11),M65*Q65) | S65: =R65/(1+Inputs!B11) | T65: =IF(Inputs!B7=1,L65,MIN(S65,L65)) | U65: =IF(Inputs!B19=1,MAX(0,T65-J65),0) | V65: =T65*(1+Inputs!B11) | W65: =V65-T65 | X65: =V65*Inputs!B13*MIN(12,Inputs!B10)/12 | Y65: =W65*Inputs!B14/12 | Z65: =J65+U65-T65+X65-Y65 | AA65: =D65+E65-I65+U65+X65-Y65 | AB65: =IF(U65>0,AB64*(1+Inputs!B15/12)+U65,AB64*(1+Inputs!B15/12)) | AC65: =IF(Inputs!B21>0,AA65/Inputs!B21,0) | AD65: =G65+T65 | AE65: =H65+W65 | AF65: =AD65+AE65 | AG65: =IF(M65>0,V65/M65,0) | AH65: =AH64+U65 | AI65: =IFERROR((1+IRR(VSTACK($AJ$8:INDEX($AJ:$AJ,ROW()-1),-U65+AA65)))^12-1,0) | AJ65: =-U65
A66: =A65+1 | B66: Month 59 | C66: =Z65 | D66: =AA65 | E66: =IF(A66<=12,0,INDEX($V$8:$V$127,A66-12)*Inputs!B13*MAX(0,Inputs!B10-12)/12) | F66: =IF(A66<=Inputs!B10,0,INDEX($T$8:$T$127,A66-Inputs!B10)) | G66: =AD65-F66 | H66: =AE65-IF(A66<=Inputs!B10,0,INDEX($W$8:$W$127,A66-Inputs!B10)) | I66: =H66*Inputs!B14/12 | J66: =C66+E66+F66-I66 | K66: =IF(Inputs!B19=1,MAX(0,Inputs!B5*1000000000-AH65),0) | L66: =MAX(0,J66+K66) | M66: =Inputs!B8*1000000 | N66: =Inputs!B9 | O66: =MAX(1,SQRT(L66/MAX(M66*MAX(N66,0.01)/(1+Inputs!B11),1))) | P66: =MIN(1,A66/12) | Q66: =IF(Inputs!B7=1,MAX(N66,L66*(1+Inputs!B11)/MAX(M66,1)),N66+(N66*O66-N66)*P66) | R66: =IF(Inputs!B7=1,L66*(1+Inputs!B11),M66*Q66) | S66: =R66/(1+Inputs!B11) | T66: =IF(Inputs!B7=1,L66,MIN(S66,L66)) | U66: =IF(Inputs!B19=1,MAX(0,T66-J66),0) | V66: =T66*(1+Inputs!B11) | W66: =V66-T66 | X66: =V66*Inputs!B13*MIN(12,Inputs!B10)/12 | Y66: =W66*Inputs!B14/12 | Z66: =J66+U66-T66+X66-Y66 | AA66: =D66+E66-I66+U66+X66-Y66 | AB66: =IF(U66>0,AB65*(1+Inputs!B15/12)+U66,AB65*(1+Inputs!B15/12)) | AC66: =IF(Inputs!B21>0,AA66/Inputs!B21,0) | AD66: =G66+T66 | AE66: =H66+W66 | AF66: =AD66+AE66 | AG66: =IF(M66>0,V66/M66,0) | AH66: =AH65+U66 | AI66: =IFERROR((1+IRR(VSTACK($AJ$8:INDEX($AJ:$AJ,ROW()-1),-U66+AA66)))^12-1,0) | AJ66: =-U66
A67: =A66+1 | B67: Month 60 | C67: =Z66 | D67: =AA66 | E67: =IF(A67<=12,0,INDEX($V$8:$V$127,A67-12)*Inputs!B13*MAX(0,Inputs!B10-12)/12) | F67: =IF(A67<=Inputs!B10,0,INDEX($T$8:$T$127,A67-Inputs!B10)) | G67: =AD66-F67 | H67: =AE66-IF(A67<=Inputs!B10,0,INDEX($W$8:$W$127,A67-Inputs!B10)) | I67: =H67*Inputs!B14/12 | J67: =C67+E67+F67-I67 | K67: =IF(Inputs!B19=1,MAX(0,Inputs!B5*1000000000-AH66),0) | L67: =MAX(0,J67+K67) | M67: =Inputs!B8*1000000 | N67: =Inputs!B9 | O67: =MAX(1,SQRT(L67/MAX(M67*MAX(N67,0.01)/(1+Inputs!B11),1))) | P67: =MIN(1,A67/12) | Q67: =IF(Inputs!B7=1,MAX(N67,L67*(1+Inputs!B11)/MAX(M67,1)),N67+(N67*O67-N67)*P67) | R67: =IF(Inputs!B7=1,L67*(1+Inputs!B11),M67*Q67) | S67: =R67/(1+Inputs!B11) | T67: =IF(Inputs!B7=1,L67,MIN(S67,L67)) | U67: =IF(Inputs!B19=1,MAX(0,T67-J67),0) | V67: =T67*(1+Inputs!B11) | W67: =V67-T67 | X67: =V67*Inputs!B13*MIN(12,Inputs!B10)/12 | Y67: =W67*Inputs!B14/12 | Z67: =J67+U67-T67+X67-Y67 | AA67: =D67+E67-I67+U67+X67-Y67 | AB67: =IF(U67>0,AB66*(1+Inputs!B15/12)+U67,AB66*(1+Inputs!B15/12)) | AC67: =IF(Inputs!B21>0,AA67/Inputs!B21,0) | AD67: =G67+T67 | AE67: =H67+W67 | AF67: =AD67+AE67 | AG67: =IF(M67>0,V67/M67,0) | AH67: =AH66+U67 | AI67: =IFERROR((1+IRR(VSTACK($AJ$8:INDEX($AJ:$AJ,ROW()-1),-U67+AA67)))^12-1,0) | AJ67: =-U67
A68: =A67+1 | B68: Month 61 | C68: =Z67 | D68: =AA67 | E68: =IF(A68<=12,0,INDEX($V$8:$V$127,A68-12)*Inputs!B13*MAX(0,Inputs!B10-12)/12) | F68: =IF(A68<=Inputs!B10,0,INDEX($T$8:$T$127,A68-Inputs!B10)) | G68: =AD67-F68 | H68: =AE67-IF(A68<=Inputs!B10,0,INDEX($W$8:$W$127,A68-Inputs!B10)) | I68: =H68*Inputs!B14/12 | J68: =C68+E68+F68-I68 | K68: =IF(Inputs!B19=1,MAX(0,Inputs!B5*1000000000-AH67),0) | L68: =MAX(0,J68+K68) | M68: =Inputs!B8*1000000 | N68: =Inputs!B9 | O68: =MAX(1,SQRT(L68/MAX(M68*MAX(N68,0.01)/(1+Inputs!B11),1))) | P68: =MIN(1,A68/12) | Q68: =IF(Inputs!B7=1,MAX(N68,L68*(1+Inputs!B11)/MAX(M68,1)),N68+(N68*O68-N68)*P68) | R68: =IF(Inputs!B7=1,L68*(1+Inputs!B11),M68*Q68) | S68: =R68/(1+Inputs!B11) | T68: =IF(Inputs!B7=1,L68,MIN(S68,L68)) | U68: =IF(Inputs!B19=1,MAX(0,T68-J68),0) | V68: =T68*(1+Inputs!B11) | W68: =V68-T68 | X68: =V68*Inputs!B13*MIN(12,Inputs!B10)/12 | Y68: =W68*Inputs!B14/12 | Z68: =J68+U68-T68+X68-Y68 | AA68: =D68+E68-I68+U68+X68-Y68 | AB68: =IF(U68>0,AB67*(1+Inputs!B15/12)+U68,AB67*(1+Inputs!B15/12)) | AC68: =IF(Inputs!B21>0,AA68/Inputs!B21,0) | AD68: =G68+T68 | AE68: =H68+W68 | AF68: =AD68+AE68 | AG68: =IF(M68>0,V68/M68,0) | AH68: =AH67+U68 | AI68: =IFERROR((1+IRR(VSTACK($AJ$8:INDEX($AJ:$AJ,ROW()-1),-U68+AA68)))^12-1,0) | AJ68: =-U68
A69: =A68+1 | B69: Month 62 | C69: =Z68 | D69: =AA68 | E69: =IF(A69<=12,0,INDEX($V$8:$V$127,A69-12)*Inputs!B13*MAX(0,Inputs!B10-12)/12) | F69: =IF(A69<=Inputs!B10,0,INDEX($T$8:$T$127,A69-Inputs!B10)) | G69: =AD68-F69 | H69: =AE68-IF(A69<=Inputs!B10,0,INDEX($W$8:$W$127,A69-Inputs!B10)) | I69: =H69*Inputs!B14/12 | J69: =C69+E69+F69-I69 | K69: =IF(Inputs!B19=1,MAX(0,Inputs!B5*1000000000-AH68),0) | L69: =MAX(0,J69+K69) | M69: =Inputs!B8*1000000 | N69: =Inputs!B9 | O69: =MAX(1,SQRT(L69/MAX(M69*MAX(N69,0.01)/(1+Inputs!B11),1))) | P69: =MIN(1,A69/12) | Q69: =IF(Inputs!B7=1,MAX(N69,L69*(1+Inputs!B11)/MAX(M69,1)),N69+(N69*O69-N69)*P69) | R69: =IF(Inputs!B7=1,L69*(1+Inputs!B11),M69*Q69) | S69: =R69/(1+Inputs!B11) | T69: =IF(Inputs!B7=1,L69,MIN(S69,L69)) | U69: =IF(Inputs!B19=1,MAX(0,T69-J69),0) | V69: =T69*(1+Inputs!B11) | W69: =V69-T69 | X69: =V69*Inputs!B13*MIN(12,Inputs!B10)/12 | Y69: =W69*Inputs!B14/12 | Z69: =J69+U69-T69+X69-Y69 | AA69: =D69+E69-I69+U69+X69-Y69 | AB69: =IF(U69>0,AB68*(1+Inputs!B15/12)+U69,AB68*(1+Inputs!B15/12)) | AC69: =IF(Inputs!B21>0,AA69/Inputs!B21,0) | AD69: =G69+T69 | AE69: =H69+W69 | AF69: =AD69+AE69 | AG69: =IF(M69>0,V69/M69,0) | AH69: =AH68+U69 | AI69: =IFERROR((1+IRR(VSTACK($AJ$8:INDEX($AJ:$AJ,ROW()-1),-U69+AA69)))^12-1,0) | AJ69: =-U69
A70: =A69+1 | B70: Month 63 | C70: =Z69 | D70: =AA69 | E70: =IF(A70<=12,0,INDEX($V$8:$V$127,A70-12)*Inputs!B13*MAX(0,Inputs!B10-12)/12) | F70: =IF(A70<=Inputs!B10,0,INDEX($T$8:$T$127,A70-Inputs!B10)) | G70: =AD69-F70 | H70: =AE69-IF(A70<=Inputs!B10,0,INDEX($W$8:$W$127,A70-Inputs!B10)) | I70: =H70*Inputs!B14/12 | J70: =C70+E70+F70-I70 | K70: =IF(Inputs!B19=1,MAX(0,Inputs!B5*1000000000-AH69),0) | L70: =MAX(0,J70+K70) | M70: =Inputs!B8*1000000 | N70: =Inputs!B9 | O70: =MAX(1,SQRT(L70/MAX(M70*MAX(N70,0.01)/(1+Inputs!B11),1))) | P70: =MIN(1,A70/12) | Q70: =IF(Inputs!B7=1,MAX(N70,L70*(1+Inputs!B11)/MAX(M70,1)),N70+(N70*O70-N70)*P70) | R70: =IF(Inputs!B7=1,L70*(1+Inputs!B11),M70*Q70) | S70: =R70/(1+Inputs!B11) | T70: =IF(Inputs!B7=1,L70,MIN(S70,L70)) | U70: =IF(Inputs!B19=1,MAX(0,T70-J70),0) | V70: =T70*(1+Inputs!B11) | W70: =V70-T70 | X70: =V70*Inputs!B13*MIN(12,Inputs!B10)/12 | Y70: =W70*Inputs!B14/12 | Z70: =J70+U70-T70+X70-Y70 | AA70: =D70+E70-I70+U70+X70-Y70 | AB70: =IF(U70>0,AB69*(1+Inputs!B15/12)+U70,AB69*(1+Inputs!B15/12)) | AC70: =IF(Inputs!B21>0,AA70/Inputs!B21,0) | AD70: =G70+T70 | AE70: =H70+W70 | AF70: =AD70+AE70 | AG70: =IF(M70>0,V70/M70,0) | AH70: =AH69+U70 | AI70: =IFERROR((1+IRR(VSTACK($AJ$8:INDEX($AJ:$AJ,ROW()-1),-U70+AA70)))^12-1,0) | AJ70: =-U70
A71: =A70+1 | B71: Month 64 | C71: =Z70 | D71: =AA70 | E71: =IF(A71<=12,0,INDEX($V$8:$V$127,A71-12)*Inputs!B13*MAX(0,Inputs!B10-12)/12) | F71: =IF(A71<=Inputs!B10,0,INDEX($T$8:$T$127,A71-Inputs!B10)) | G71: =AD70-F71 | H71: =AE70-IF(A71<=Inputs!B10,0,INDEX($W$8:$W$127,A71-Inputs!B10)) | I71: =H71*Inputs!B14/12 | J71: =C71+E71+F71-I71 | K71: =IF(Inputs!B19=1,MAX(0,Inputs!B5*1000000000-AH70),0) | L71: =MAX(0,J71+K71) | M71: =Inputs!B8*1000000 | N71: =Inputs!B9 | O71: =MAX(1,SQRT(L71/MAX(M71*MAX(N71,0.01)/(1+Inputs!B11),1))) | P71: =MIN(1,A71/12) | Q71: =IF(Inputs!B7=1,MAX(N71,L71*(1+Inputs!B11)/MAX(M71,1)),N71+(N71*O71-N71)*P71) | R71: =IF(Inputs!B7=1,L71*(1+Inputs!B11),M71*Q71) | S71: =R71/(1+Inputs!B11) | T71: =IF(Inputs!B7=1,L71,MIN(S71,L71)) | U71: =IF(Inputs!B19=1,MAX(0,T71-J71),0) | V71: =T71*(1+Inputs!B11) | W71: =V71-T71 | X71: =V71*Inputs!B13*MIN(12,Inputs!B10)/12 | Y71: =W71*Inputs!B14/12 | Z71: =J71+U71-T71+X71-Y71 | AA71: =D71+E71-I71+U71+X71-Y71 | AB71: =IF(U71>0,AB70*(1+Inputs!B15/12)+U71,AB70*(1+Inputs!B15/12)) | AC71: =IF(Inputs!B21>0,AA71/Inputs!B21,0) | AD71: =G71+T71 | AE71: =H71+W71 | AF71: =AD71+AE71 | AG71: =IF(M71>0,V71/M71,0) | AH71: =AH70+U71 | AI71: =IFERROR((1+IRR(VSTACK($AJ$8:INDEX($AJ:$AJ,ROW()-1),-U71+AA71)))^12-1,0) | AJ71: =-U71
A72: =A71+1 | B72: Month 65 | C72: =Z71 | D72: =AA71 | E72: =IF(A72<=12,0,INDEX($V$8:$V$127,A72-12)*Inputs!B13*MAX(0,Inputs!B10-12)/12) | F72: =IF(A72<=Inputs!B10,0,INDEX($T$8:$T$127,A72-Inputs!B10)) | G72: =AD71-F72 | H72: =AE71-IF(A72<=Inputs!B10,0,INDEX($W$8:$W$127,A72-Inputs!B10)) | I72: =H72*Inputs!B14/12 | J72: =C72+E72+F72-I72 | K72: =IF(Inputs!B19=1,MAX(0,Inputs!B5*1000000000-AH71),0) | L72: =MAX(0,J72+K72) | M72: =Inputs!B8*1000000 | N72: =Inputs!B9 | O72: =MAX(1,SQRT(L72/MAX(M72*MAX(N72,0.01)/(1+Inputs!B11),1))) | P72: =MIN(1,A72/12) | Q72: =IF(Inputs!B7=1,MAX(N72,L72*(1+Inputs!B11)/MAX(M72,1)),N72+(N72*O72-N72)*P72) | R72: =IF(Inputs!B7=1,L72*(1+Inputs!B11),M72*Q72) | S72: =R72/(1+Inputs!B11) | T72: =IF(Inputs!B7=1,L72,MIN(S72,L72)) | U72: =IF(Inputs!B19=1,MAX(0,T72-J72),0) | V72: =T72*(1+Inputs!B11) | W72: =V72-T72 | X72: =V72*Inputs!B13*MIN(12,Inputs!B10)/12 | Y72: =W72*Inputs!B14/12 | Z72: =J72+U72-T72+X72-Y72 | AA72: =D72+E72-I72+U72+X72-Y72 | AB72: =IF(U72>0,AB71*(1+Inputs!B15/12)+U72,AB71*(1+Inputs!B15/12)) | AC72: =IF(Inputs!B21>0,AA72/Inputs!B21,0) | AD72: =G72+T72 | AE72: =H72+W72 | AF72: =AD72+AE72 | AG72: =IF(M72>0,V72/M72,0) | AH72: =AH71+U72 | AI72: =IFERROR((1+IRR(VSTACK($AJ$8:INDEX($AJ:$AJ,ROW()-1),-U72+AA72)))^12-1,0) | AJ72: =-U72
A73: =A72+1 | B73: Month 66 | C73: =Z72 | D73: =AA72 | E73: =IF(A73<=12,0,INDEX($V$8:$V$127,A73-12)*Inputs!B13*MAX(0,Inputs!B10-12)/12) | F73: =IF(A73<=Inputs!B10,0,INDEX($T$8:$T$127,A73-Inputs!B10)) | G73: =AD72-F73 | H73: =AE72-IF(A73<=Inputs!B10,0,INDEX($W$8:$W$127,A73-Inputs!B10)) | I73: =H73*Inputs!B14/12 | J73: =C73+E73+F73-I73 | K73: =IF(Inputs!B19=1,MAX(0,Inputs!B5*1000000000-AH72),0) | L73: =MAX(0,J73+K73) | M73: =Inputs!B8*1000000 | N73: =Inputs!B9 | O73: =MAX(1,SQRT(L73/MAX(M73*MAX(N73,0.01)/(1+Inputs!B11),1))) | P73: =MIN(1,A73/12) | Q73: =IF(Inputs!B7=1,MAX(N73,L73*(1+Inputs!B11)/MAX(M73,1)),N73+(N73*O73-N73)*P73) | R73: =IF(Inputs!B7=1,L73*(1+Inputs!B11),M73*Q73) | S73: =R73/(1+Inputs!B11) | T73: =IF(Inputs!B7=1,L73,MIN(S73,L73)) | U73: =IF(Inputs!B19=1,MAX(0,T73-J73),0) | V73: =T73*(1+Inputs!B11) | W73: =V73-T73 | X73: =V73*Inputs!B13*MIN(12,Inputs!B10)/12 | Y73: =W73*Inputs!B14/12 | Z73: =J73+U73-T73+X73-Y73 | AA73: =D73+E73-I73+U73+X73-Y73 | AB73: =IF(U73>0,AB72*(1+Inputs!B15/12)+U73,AB72*(1+Inputs!B15/12)) | AC73: =IF(Inputs!B21>0,AA73/Inputs!B21,0) | AD73: =G73+T73 | AE73: =H73+W73 | AF73: =AD73+AE73 | AG73: =IF(M73>0,V73/M73,0) | AH73: =AH72+U73 | AI73: =IFERROR((1+IRR(VSTACK($AJ$8:INDEX($AJ:$AJ,ROW()-1),-U73+AA73)))^12-1,0) | AJ73: =-U73
A74: =A73+1 | B74: Month 67 | C74: =Z73 | D74: =AA73 | E74: =IF(A74<=12,0,INDEX($V$8:$V$127,A74-12)*Inputs!B13*MAX(0,Inputs!B10-12)/12) | F74: =IF(A74<=Inputs!B10,0,INDEX($T$8:$T$127,A74-Inputs!B10)) | G74: =AD73-F74 | H74: =AE73-IF(A74<=Inputs!B10,0,INDEX($W$8:$W$127,A74-Inputs!B10)) | I74: =H74*Inputs!B14/12 | J74: =C74+E74+F74-I74 | K74: =IF(Inputs!B19=1,MAX(0,Inputs!B5*1000000000-AH73),0) | L74: =MAX(0,J74+K74) | M74: =Inputs!B8*1000000 | N74: =Inputs!B9 | O74: =MAX(1,SQRT(L74/MAX(M74*MAX(N74,0.01)/(1+Inputs!B11),1))) | P74: =MIN(1,A74/12) | Q74: =IF(Inputs!B7=1,MAX(N74,L74*(1+Inputs!B11)/MAX(M74,1)),N74+(N74*O74-N74)*P74) | R74: =IF(Inputs!B7=1,L74*(1+Inputs!B11),M74*Q74) | S74: =R74/(1+Inputs!B11) | T74: =IF(Inputs!B7=1,L74,MIN(S74,L74)) | U74: =IF(Inputs!B19=1,MAX(0,T74-J74),0) | V74: =T74*(1+Inputs!B11) | W74: =V74-T74 | X74: =V74*Inputs!B13*MIN(12,Inputs!B10)/12 | Y74: =W74*Inputs!B14/12 | Z74: =J74+U74-T74+X74-Y74 | AA74: =D74+E74-I74+U74+X74-Y74 | AB74: =IF(U74>0,AB73*(1+Inputs!B15/12)+U74,AB73*(1+Inputs!B15/12)) | AC74: =IF(Inputs!B21>0,AA74/Inputs!B21,0) | AD74: =G74+T74 | AE74: =H74+W74 | AF74: =AD74+AE74 | AG74: =IF(M74>0,V74/M74,0) | AH74: =AH73+U74 | AI74: =IFERROR((1+IRR(VSTACK($AJ$8:INDEX($AJ:$AJ,ROW()-1),-U74+AA74)))^12-1,0) | AJ74: =-U74
A75: =A74+1 | B75: Month 68 | C75: =Z74 | D75: =AA74 | E75: =IF(A75<=12,0,INDEX($V$8:$V$127,A75-12)*Inputs!B13*MAX(0,Inputs!B10-12)/12) | F75: =IF(A75<=Inputs!B10,0,INDEX($T$8:$T$127,A75-Inputs!B10)) | G75: =AD74-F75 | H75: =AE74-IF(A75<=Inputs!B10,0,INDEX($W$8:$W$127,A75-Inputs!B10)) | I75: =H75*Inputs!B14/12 | J75: =C75+E75+F75-I75 | K75: =IF(Inputs!B19=1,MAX(0,Inputs!B5*1000000000-AH74),0) | L75: =MAX(0,J75+K75) | M75: =Inputs!B8*1000000 | N75: =Inputs!B9 | O75: =MAX(1,SQRT(L75/MAX(M75*MAX(N75,0.01)/(1+Inputs!B11),1))) | P75: =MIN(1,A75/12) | Q75: =IF(Inputs!B7=1,MAX(N75,L75*(1+Inputs!B11)/MAX(M75,1)),N75+(N75*O75-N75)*P75) | R75: =IF(Inputs!B7=1,L75*(1+Inputs!B11),M75*Q75) | S75: =R75/(1+Inputs!B11) | T75: =IF(Inputs!B7=1,L75,MIN(S75,L75)) | U75: =IF(Inputs!B19=1,MAX(0,T75-J75),0) | V75: =T75*(1+Inputs!B11) | W75: =V75-T75 | X75: =V75*Inputs!B13*MIN(12,Inputs!B10)/12 | Y75: =W75*Inputs!B14/12 | Z75: =J75+U75-T75+X75-Y75 | AA75: =D75+E75-I75+U75+X75-Y75 | AB75: =IF(U75>0,AB74*(1+Inputs!B15/12)+U75,AB74*(1+Inputs!B15/12)) | AC75: =IF(Inputs!B21>0,AA75/Inputs!B21,0) | AD75: =G75+T75 | AE75: =H75+W75 | AF75: =AD75+AE75 | AG75: =IF(M75>0,V75/M75,0) | AH75: =AH74+U75 | AI75: =IFERROR((1+IRR(VSTACK($AJ$8:INDEX($AJ:$AJ,ROW()-1),-U75+AA75)))^12-1,0) | AJ75: =-U75
A76: =A75+1 | B76: Month 69 | C76: =Z75 | D76: =AA75 | E76: =IF(A76<=12,0,INDEX($V$8:$V$127,A76-12)*Inputs!B13*MAX(0,Inputs!B10-12)/12) | F76: =IF(A76<=Inputs!B10,0,INDEX($T$8:$T$127,A76-Inputs!B10)) | G76: =AD75-F76 | H76: =AE75-IF(A76<=Inputs!B10,0,INDEX($W$8:$W$127,A76-Inputs!B10)) | I76: =H76*Inputs!B14/12 | J76: =C76+E76+F76-I76 | K76: =IF(Inputs!B19=1,MAX(0,Inputs!B5*1000000000-AH75),0) | L76: =MAX(0,J76+K76) | M76: =Inputs!B8*1000000 | N76: =Inputs!B9 | O76: =MAX(1,SQRT(L76/MAX(M76*MAX(N76,0.01)/(1+Inputs!B11),1))) | P76: =MIN(1,A76/12) | Q76: =IF(Inputs!B7=1,MAX(N76,L76*(1+Inputs!B11)/MAX(M76,1)),N76+(N76*O76-N76)*P76) | R76: =IF(Inputs!B7=1,L76*(1+Inputs!B11),M76*Q76) | S76: =R76/(1+Inputs!B11) | T76: =IF(Inputs!B7=1,L76,MIN(S76,L76)) | U76: =IF(Inputs!B19=1,MAX(0,T76-J76),0) | V76: =T76*(1+Inputs!B11) | W76: =V76-T76 | X76: =V76*Inputs!B13*MIN(12,Inputs!B10)/12 | Y76: =W76*Inputs!B14/12 | Z76: =J76+U76-T76+X76-Y76 | AA76: =D76+E76-I76+U76+X76-Y76 | AB76: =IF(U76>0,AB75*(1+Inputs!B15/12)+U76,AB75*(1+Inputs!B15/12)) | AC76: =IF(Inputs!B21>0,AA76/Inputs!B21,0) | AD76: =G76+T76 | AE76: =H76+W76 | AF76: =AD76+AE76 | AG76: =IF(M76>0,V76/M76,0) | AH76: =AH75+U76 | AI76: =IFERROR((1+IRR(VSTACK($AJ$8:INDEX($AJ:$AJ,ROW()-1),-U76+AA76)))^12-1,0) | AJ76: =-U76
A77: =A76+1 | B77: Month 70 | C77: =Z76 | D77: =AA76 | E77: =IF(A77<=12,0,INDEX($V$8:$V$127,A77-12)*Inputs!B13*MAX(0,Inputs!B10-12)/12) | F77: =IF(A77<=Inputs!B10,0,INDEX($T$8:$T$127,A77-Inputs!B10)) | G77: =AD76-F77 | H77: =AE76-IF(A77<=Inputs!B10,0,INDEX($W$8:$W$127,A77-Inputs!B10)) | I77: =H77*Inputs!B14/12 | J77: =C77+E77+F77-I77 | K77: =IF(Inputs!B19=1,MAX(0,Inputs!B5*1000000000-AH76),0) | L77: =MAX(0,J77+K77) | M77: =Inputs!B8*1000000 | N77: =Inputs!B9 | O77: =MAX(1,SQRT(L77/MAX(M77*MAX(N77,0.01)/(1+Inputs!B11),1))) | P77: =MIN(1,A77/12) | Q77: =IF(Inputs!B7=1,MAX(N77,L77*(1+Inputs!B11)/MAX(M77,1)),N77+(N77*O77-N77)*P77) | R77: =IF(Inputs!B7=1,L77*(1+Inputs!B11),M77*Q77) | S77: =R77/(1+Inputs!B11) | T77: =IF(Inputs!B7=1,L77,MIN(S77,L77)) | U77: =IF(Inputs!B19=1,MAX(0,T77-J77),0) | V77: =T77*(1+Inputs!B11) | W77: =V77-T77 | X77: =V77*Inputs!B13*MIN(12,Inputs!B10)/12 | Y77: =W77*Inputs!B14/12 | Z77: =J77+U77-T77+X77-Y77 | AA77: =D77+E77-I77+U77+X77-Y77 | AB77: =IF(U77>0,AB76*(1+Inputs!B15/12)+U77,AB76*(1+Inputs!B15/12)) | AC77: =IF(Inputs!B21>0,AA77/Inputs!B21,0) | AD77: =G77+T77 | AE77: =H77+W77 | AF77: =AD77+AE77 | AG77: =IF(M77>0,V77/M77,0) | AH77: =AH76+U77 | AI77: =IFERROR((1+IRR(VSTACK($AJ$8:INDEX($AJ:$AJ,ROW()-1),-U77+AA77)))^12-1,0) | AJ77: =-U77
A78: =A77+1 | B78: Month 71 | C78: =Z77 | D78: =AA77 | E78: =IF(A78<=12,0,INDEX($V$8:$V$127,A78-12)*Inputs!B13*MAX(0,Inputs!B10-12)/12) | F78: =IF(A78<=Inputs!B10,0,INDEX($T$8:$T$127,A78-Inputs!B10)) | G78: =AD77-F78 | H78: =AE77-IF(A78<=Inputs!B10,0,INDEX($W$8:$W$127,A78-Inputs!B10)) | I78: =H78*Inputs!B14/12 | J78: =C78+E78+F78-I78 | K78: =IF(Inputs!B19=1,MAX(0,Inputs!B5*1000000000-AH77),0) | L78: =MAX(0,J78+K78) | M78: =Inputs!B8*1000000 | N78: =Inputs!B9 | O78: =MAX(1,SQRT(L78/MAX(M78*MAX(N78,0.01)/(1+Inputs!B11),1))) | P78: =MIN(1,A78/12) | Q78: =IF(Inputs!B7=1,MAX(N78,L78*(1+Inputs!B11)/MAX(M78,1)),N78+(N78*O78-N78)*P78) | R78: =IF(Inputs!B7=1,L78*(1+Inputs!B11),M78*Q78) | S78: =R78/(1+Inputs!B11) | T78: =IF(Inputs!B7=1,L78,MIN(S78,L78)) | U78: =IF(Inputs!B19=1,MAX(0,T78-J78),0) | V78: =T78*(1+Inputs!B11) | W78: =V78-T78 | X78: =V78*Inputs!B13*MIN(12,Inputs!B10)/12 | Y78: =W78*Inputs!B14/12 | Z78: =J78+U78-T78+X78-Y78 | AA78: =D78+E78-I78+U78+X78-Y78 | AB78: =IF(U78>0,AB77*(1+Inputs!B15/12)+U78,AB77*(1+Inputs!B15/12)) | AC78: =IF(Inputs!B21>0,AA78/Inputs!B21,0) | AD78: =G78+T78 | AE78: =H78+W78 | AF78: =AD78+AE78 | AG78: =IF(M78>0,V78/M78,0) | AH78: =AH77+U78 | AI78: =IFERROR((1+IRR(VSTACK($AJ$8:INDEX($AJ:$AJ,ROW()-1),-U78+AA78)))^12-1,0) | AJ78: =-U78
A79: =A78+1 | B79: Month 72 | C79: =Z78 | D79: =AA78 | E79: =IF(A79<=12,0,INDEX($V$8:$V$127,A79-12)*Inputs!B13*MAX(0,Inputs!B10-12)/12) | F79: =IF(A79<=Inputs!B10,0,INDEX($T$8:$T$127,A79-Inputs!B10)) | G79: =AD78-F79 | H79: =AE78-IF(A79<=Inputs!B10,0,INDEX($W$8:$W$127,A79-Inputs!B10)) | I79: =H79*Inputs!B14/12 | J79: =C79+E79+F79-I79 | K79: =IF(Inputs!B19=1,MAX(0,Inputs!B5*1000000000-AH78),0) | L79: =MAX(0,J79+K79) | M79: =Inputs!B8*1000000 | N79: =Inputs!B9 | O79: =MAX(1,SQRT(L79/MAX(M79*MAX(N79,0.01)/(1+Inputs!B11),1))) | P79: =MIN(1,A79/12) | Q79: =IF(Inputs!B7=1,MAX(N79,L79*(1+Inputs!B11)/MAX(M79,1)),N79+(N79*O79-N79)*P79) | R79: =IF(Inputs!B7=1,L79*(1+Inputs!B11),M79*Q79) | S79: =R79/(1+Inputs!B11) | T79: =IF(Inputs!B7=1,L79,MIN(S79,L79)) | U79: =IF(Inputs!B19=1,MAX(0,T79-J79),0) | V79: =T79*(1+Inputs!B11) | W79: =V79-T79 | X79: =V79*Inputs!B13*MIN(12,Inputs!B10)/12 | Y79: =W79*Inputs!B14/12 | Z79: =J79+U79-T79+X79-Y79 | AA79: =D79+E79-I79+U79+X79-Y79 | AB79: =IF(U79>0,AB78*(1+Inputs!B15/12)+U79,AB78*(1+Inputs!B15/12)) | AC79: =IF(Inputs!B21>0,AA79/Inputs!B21,0) | AD79: =G79+T79 | AE79: =H79+W79 | AF79: =AD79+AE79 | AG79: =IF(M79>0,V79/M79,0) | AH79: =AH78+U79 | AI79: =IFERROR((1+IRR(VSTACK($AJ$8:INDEX($AJ:$AJ,ROW()-1),-U79+AA79)))^12-1,0) | AJ79: =-U79
A80: =A79+1 | B80: Month 73 | C80: =Z79 | D80: =AA79 | E80: =IF(A80<=12,0,INDEX($V$8:$V$127,A80-12)*Inputs!B13*MAX(0,Inputs!B10-12)/12) | F80: =IF(A80<=Inputs!B10,0,INDEX($T$8:$T$127,A80-Inputs!B10)) | G80: =AD79-F80 | H80: =AE79-IF(A80<=Inputs!B10,0,INDEX($W$8:$W$127,A80-Inputs!B10)) | I80: =H80*Inputs!B14/12 | J80: =C80+E80+F80-I80 | K80: =IF(Inputs!B19=1,MAX(0,Inputs!B5*1000000000-AH79),0) | L80: =MAX(0,J80+K80) | M80: =Inputs!B8*1000000 | N80: =Inputs!B9 | O80: =MAX(1,SQRT(L80/MAX(M80*MAX(N80,0.01)/(1+Inputs!B11),1))) | P80: =MIN(1,A80/12) | Q80: =IF(Inputs!B7=1,MAX(N80,L80*(1+Inputs!B11)/MAX(M80,1)),N80+(N80*O80-N80)*P80) | R80: =IF(Inputs!B7=1,L80*(1+Inputs!B11),M80*Q80) | S80: =R80/(1+Inputs!B11) | T80: =IF(Inputs!B7=1,L80,MIN(S80,L80)) | U80: =IF(Inputs!B19=1,MAX(0,T80-J80),0) | V80: =T80*(1+Inputs!B11) | W80: =V80-T80 | X80: =V80*Inputs!B13*MIN(12,Inputs!B10)/12 | Y80: =W80*Inputs!B14/12 | Z80: =J80+U80-T80+X80-Y80 | AA80: =D80+E80-I80+U80+X80-Y80 | AB80: =IF(U80>0,AB79*(1+Inputs!B15/12)+U80,AB79*(1+Inputs!B15/12)) | AC80: =IF(Inputs!B21>0,AA80/Inputs!B21,0) | AD80: =G80+T80 | AE80: =H80+W80 | AF80: =AD80+AE80 | AG80: =IF(M80>0,V80/M80,0) | AH80: =AH79+U80 | AI80: =IFERROR((1+IRR(VSTACK($AJ$8:INDEX($AJ:$AJ,ROW()-1),-U80+AA80)))^12-1,0) | AJ80: =-U80
A81: =A80+1 | B81: Month 74 | C81: =Z80 | D81: =AA80 | E81: =IF(A81<=12,0,INDEX($V$8:$V$127,A81-12)*Inputs!B13*MAX(0,Inputs!B10-12)/12) | F81: =IF(A81<=Inputs!B10,0,INDEX($T$8:$T$127,A81-Inputs!B10)) | G81: =AD80-F81 | H81: =AE80-IF(A81<=Inputs!B10,0,INDEX($W$8:$W$127,A81-Inputs!B10)) | I81: =H81*Inputs!B14/12 | J81: =C81+E81+F81-I81 | K81: =IF(Inputs!B19=1,MAX(0,Inputs!B5*1000000000-AH80),0) | L81: =MAX(0,J81+K81) | M81: =Inputs!B8*1000000 | N81: =Inputs!B9 | O81: =MAX(1,SQRT(L81/MAX(M81*MAX(N81,0.01)/(1+Inputs!B11),1))) | P81: =MIN(1,A81/12) | Q81: =IF(Inputs!B7=1,MAX(N81,L81*(1+Inputs!B11)/MAX(M81,1)),N81+(N81*O81-N81)*P81) | R81: =IF(Inputs!B7=1,L81*(1+Inputs!B11),M81*Q81) | S81: =R81/(1+Inputs!B11) | T81: =IF(Inputs!B7=1,L81,MIN(S81,L81)) | U81: =IF(Inputs!B19=1,MAX(0,T81-J81),0) | V81: =T81*(1+Inputs!B11) | W81: =V81-T81 | X81: =V81*Inputs!B13*MIN(12,Inputs!B10)/12 | Y81: =W81*Inputs!B14/12 | Z81: =J81+U81-T81+X81-Y81 | AA81: =D81+E81-I81+U81+X81-Y81 | AB81: =IF(U81>0,AB80*(1+Inputs!B15/12)+U81,AB80*(1+Inputs!B15/12)) | AC81: =IF(Inputs!B21>0,AA81/Inputs!B21,0) | AD81: =G81+T81 | AE81: =H81+W81 | AF81: =AD81+AE81 | AG81: =IF(M81>0,V81/M81,0) | AH81: =AH80+U81 | AI81: =IFERROR((1+IRR(VSTACK($AJ$8:INDEX($AJ:$AJ,ROW()-1),-U81+AA81)))^12-1,0) | AJ81: =-U81
A82: =A81+1 | B82: Month 75 | C82: =Z81 | D82: =AA81 | E82: =IF(A82<=12,0,INDEX($V$8:$V$127,A82-12)*Inputs!B13*MAX(0,Inputs!B10-12)/12) | F82: =IF(A82<=Inputs!B10,0,INDEX($T$8:$T$127,A82-Inputs!B10)) | G82: =AD81-F82 | H82: =AE81-IF(A82<=Inputs!B10,0,INDEX($W$8:$W$127,A82-Inputs!B10)) | I82: =H82*Inputs!B14/12 | J82: =C82+E82+F82-I82 | K82: =IF(Inputs!B19=1,MAX(0,Inputs!B5*1000000000-AH81),0) | L82: =MAX(0,J82+K82) | M82: =Inputs!B8*1000000 | N82: =Inputs!B9 | O82: =MAX(1,SQRT(L82/MAX(M82*MAX(N82,0.01)/(1+Inputs!B11),1))) | P82: =MIN(1,A82/12) | Q82: =IF(Inputs!B7=1,MAX(N82,L82*(1+Inputs!B11)/MAX(M82,1)),N82+(N82*O82-N82)*P82) | R82: =IF(Inputs!B7=1,L82*(1+Inputs!B11),M82*Q82) | S82: =R82/(1+Inputs!B11) | T82: =IF(Inputs!B7=1,L82,MIN(S82,L82)) | U82: =IF(Inputs!B19=1,MAX(0,T82-J82),0) | V82: =T82*(1+Inputs!B11) | W82: =V82-T82 | X82: =V82*Inputs!B13*MIN(12,Inputs!B10)/12 | Y82: =W82*Inputs!B14/12 | Z82: =J82+U82-T82+X82-Y82 | AA82: =D82+E82-I82+U82+X82-Y82 | AB82: =IF(U82>0,AB81*(1+Inputs!B15/12)+U82,AB81*(1+Inputs!B15/12)) | AC82: =IF(Inputs!B21>0,AA82/Inputs!B21,0) | AD82: =G82+T82 | AE82: =H82+W82 | AF82: =AD82+AE82 | AG82: =IF(M82>0,V82/M82,0) | AH82: =AH81+U82 | AI82: =IFERROR((1+IRR(VSTACK($AJ$8:INDEX($AJ:$AJ,ROW()-1),-U82+AA82)))^12-1,0) | AJ82: =-U82
A83: =A82+1 | B83: Month 76 | C83: =Z82 | D83: =AA82 | E83: =IF(A83<=12,0,INDEX($V$8:$V$127,A83-12)*Inputs!B13*MAX(0,Inputs!B10-12)/12) | F83: =IF(A83<=Inputs!B10,0,INDEX($T$8:$T$127,A83-Inputs!B10)) | G83: =AD82-F83 | H83: =AE82-IF(A83<=Inputs!B10,0,INDEX($W$8:$W$127,A83-Inputs!B10)) | I83: =H83*Inputs!B14/12 | J83: =C83+E83+F83-I83 | K83: =IF(Inputs!B19=1,MAX(0,Inputs!B5*1000000000-AH82),0) | L83: =MAX(0,J83+K83) | M83: =Inputs!B8*1000000 | N83: =Inputs!B9 | O83: =MAX(1,SQRT(L83/MAX(M83*MAX(N83,0.01)/(1+Inputs!B11),1))) | P83: =MIN(1,A83/12) | Q83: =IF(Inputs!B7=1,MAX(N83,L83*(1+Inputs!B11)/MAX(M83,1)),N83+(N83*O83-N83)*P83) | R83: =IF(Inputs!B7=1,L83*(1+Inputs!B11),M83*Q83) | S83: =R83/(1+Inputs!B11) | T83: =IF(Inputs!B7=1,L83,MIN(S83,L83)) | U83: =IF(Inputs!B19=1,MAX(0,T83-J83),0) | V83: =T83*(1+Inputs!B11) | W83: =V83-T83 | X83: =V83*Inputs!B13*MIN(12,Inputs!B10)/12 | Y83: =W83*Inputs!B14/12 | Z83: =J83+U83-T83+X83-Y83 | AA83: =D83+E83-I83+U83+X83-Y83 | AB83: =IF(U83>0,AB82*(1+Inputs!B15/12)+U83,AB82*(1+Inputs!B15/12)) | AC83: =IF(Inputs!B21>0,AA83/Inputs!B21,0) | AD83: =G83+T83 | AE83: =H83+W83 | AF83: =AD83+AE83 | AG83: =IF(M83>0,V83/M83,0) | AH83: =AH82+U83 | AI83: =IFERROR((1+IRR(VSTACK($AJ$8:INDEX($AJ:$AJ,ROW()-1),-U83+AA83)))^12-1,0) | AJ83: =-U83
A84: =A83+1 | B84: Month 77 | C84: =Z83 | D84: =AA83 | E84: =IF(A84<=12,0,INDEX($V$8:$V$127,A84-12)*Inputs!B13*MAX(0,Inputs!B10-12)/12) | F84: =IF(A84<=Inputs!B10,0,INDEX($T$8:$T$127,A84-Inputs!B10)) | G84: =AD83-F84 | H84: =AE83-IF(A84<=Inputs!B10,0,INDEX($W$8:$W$127,A84-Inputs!B10)) | I84: =H84*Inputs!B14/12 | J84: =C84+E84+F84-I84 | K84: =IF(Inputs!B19=1,MAX(0,Inputs!B5*1000000000-AH83),0) | L84: =MAX(0,J84+K84) | M84: =Inputs!B8*1000000 | N84: =Inputs!B9 | O84: =MAX(1,SQRT(L84/MAX(M84*MAX(N84,0.01)/(1+Inputs!B11),1))) | P84: =MIN(1,A84/12) | Q84: =IF(Inputs!B7=1,MAX(N84,L84*(1+Inputs!B11)/MAX(M84,1)),N84+(N84*O84-N84)*P84) | R84: =IF(Inputs!B7=1,L84*(1+Inputs!B11),M84*Q84) | S84: =R84/(1+Inputs!B11) | T84: =IF(Inputs!B7=1,L84,MIN(S84,L84)) | U84: =IF(Inputs!B19=1,MAX(0,T84-J84),0) | V84: =T84*(1+Inputs!B11) | W84: =V84-T84 | X84: =V84*Inputs!B13*MIN(12,Inputs!B10)/12 | Y84: =W84*Inputs!B14/12 | Z84: =J84+U84-T84+X84-Y84 | AA84: =D84+E84-I84+U84+X84-Y84 | AB84: =IF(U84>0,AB83*(1+Inputs!B15/12)+U84,AB83*(1+Inputs!B15/12)) | AC84: =IF(Inputs!B21>0,AA84/Inputs!B21,0) | AD84: =G84+T84 | AE84: =H84+W84 | AF84: =AD84+AE84 | AG84: =IF(M84>0,V84/M84,0) | AH84: =AH83+U84 | AI84: =IFERROR((1+IRR(VSTACK($AJ$8:INDEX($AJ:$AJ,ROW()-1),-U84+AA84)))^12-1,0) | AJ84: =-U84
A85: =A84+1 | B85: Month 78 | C85: =Z84 | D85: =AA84 | E85: =IF(A85<=12,0,INDEX($V$8:$V$127,A85-12)*Inputs!B13*MAX(0,Inputs!B10-12)/12) | F85: =IF(A85<=Inputs!B10,0,INDEX($T$8:$T$127,A85-Inputs!B10)) | G85: =AD84-F85 | H85: =AE84-IF(A85<=Inputs!B10,0,INDEX($W$8:$W$127,A85-Inputs!B10)) | I85: =H85*Inputs!B14/12 | J85: =C85+E85+F85-I85 | K85: =IF(Inputs!B19=1,MAX(0,Inputs!B5*1000000000-AH84),0) | L85: =MAX(0,J85+K85) | M85: =Inputs!B8*1000000 | N85: =Inputs!B9 | O85: =MAX(1,SQRT(L85/MAX(M85*MAX(N85,0.01)/(1+Inputs!B11),1))) | P85: =MIN(1,A85/12) | Q85: =IF(Inputs!B7=1,MAX(N85,L85*(1+Inputs!B11)/MAX(M85,1)),N85+(N85*O85-N85)*P85) | R85: =IF(Inputs!B7=1,L85*(1+Inputs!B11),M85*Q85) | S85: =R85/(1+Inputs!B11) | T85: =IF(Inputs!B7=1,L85,MIN(S85,L85)) | U85: =IF(Inputs!B19=1,MAX(0,T85-J85),0) | V85: =T85*(1+Inputs!B11) | W85: =V85-T85 | X85: =V85*Inputs!B13*MIN(12,Inputs!B10)/12 | Y85: =W85*Inputs!B14/12 | Z85: =J85+U85-T85+X85-Y85 | AA85: =D85+E85-I85+U85+X85-Y85 | AB85: =IF(U85>0,AB84*(1+Inputs!B15/12)+U85,AB84*(1+Inputs!B15/12)) | AC85: =IF(Inputs!B21>0,AA85/Inputs!B21,0) | AD85: =G85+T85 | AE85: =H85+W85 | AF85: =AD85+AE85 | AG85: =IF(M85>0,V85/M85,0) | AH85: =AH84+U85 | AI85: =IFERROR((1+IRR(VSTACK($AJ$8:INDEX($AJ:$AJ,ROW()-1),-U85+AA85)))^12-1,0) | AJ85: =-U85
A86: =A85+1 | B86: Month 79 | C86: =Z85 | D86: =AA85 | E86: =IF(A86<=12,0,INDEX($V$8:$V$127,A86-12)*Inputs!B13*MAX(0,Inputs!B10-12)/12) | F86: =IF(A86<=Inputs!B10,0,INDEX($T$8:$T$127,A86-Inputs!B10)) | G86: =AD85-F86 | H86: =AE85-IF(A86<=Inputs!B10,0,INDEX($W$8:$W$127,A86-Inputs!B10)) | I86: =H86*Inputs!B14/12 | J86: =C86+E86+F86-I86 | K86: =IF(Inputs!B19=1,MAX(0,Inputs!B5*1000000000-AH85),0) | L86: =MAX(0,J86+K86) | M86: =Inputs!B8*1000000 | N86: =Inputs!B9 | O86: =MAX(1,SQRT(L86/MAX(M86*MAX(N86,0.01)/(1+Inputs!B11),1))) | P86: =MIN(1,A86/12) | Q86: =IF(Inputs!B7=1,MAX(N86,L86*(1+Inputs!B11)/MAX(M86,1)),N86+(N86*O86-N86)*P86) | R86: =IF(Inputs!B7=1,L86*(1+Inputs!B11),M86*Q86) | S86: =R86/(1+Inputs!B11) | T86: =IF(Inputs!B7=1,L86,MIN(S86,L86)) | U86: =IF(Inputs!B19=1,MAX(0,T86-J86),0) | V86: =T86*(1+Inputs!B11) | W86: =V86-T86 | X86: =V86*Inputs!B13*MIN(12,Inputs!B10)/12 | Y86: =W86*Inputs!B14/12 | Z86: =J86+U86-T86+X86-Y86 | AA86: =D86+E86-I86+U86+X86-Y86 | AB86: =IF(U86>0,AB85*(1+Inputs!B15/12)+U86,AB85*(1+Inputs!B15/12)) | AC86: =IF(Inputs!B21>0,AA86/Inputs!B21,0) | AD86: =G86+T86 | AE86: =H86+W86 | AF86: =AD86+AE86 | AG86: =IF(M86>0,V86/M86,0) | AH86: =AH85+U86 | AI86: =IFERROR((1+IRR(VSTACK($AJ$8:INDEX($AJ:$AJ,ROW()-1),-U86+AA86)))^12-1,0) | AJ86: =-U86
A87: =A86+1 | B87: Month 80 | C87: =Z86 | D87: =AA86 | E87: =IF(A87<=12,0,INDEX($V$8:$V$127,A87-12)*Inputs!B13*MAX(0,Inputs!B10-12)/12) | F87: =IF(A87<=Inputs!B10,0,INDEX($T$8:$T$127,A87-Inputs!B10)) | G87: =AD86-F87 | H87: =AE86-IF(A87<=Inputs!B10,0,INDEX($W$8:$W$127,A87-Inputs!B10)) | I87: =H87*Inputs!B14/12 | J87: =C87+E87+F87-I87 | K87: =IF(Inputs!B19=1,MAX(0,Inputs!B5*1000000000-AH86),0) | L87: =MAX(0,J87+K87) | M87: =Inputs!B8*1000000 | N87: =Inputs!B9 | O87: =MAX(1,SQRT(L87/MAX(M87*MAX(N87,0.01)/(1+Inputs!B11),1))) | P87: =MIN(1,A87/12) | Q87: =IF(Inputs!B7=1,MAX(N87,L87*(1+Inputs!B11)/MAX(M87,1)),N87+(N87*O87-N87)*P87) | R87: =IF(Inputs!B7=1,L87*(1+Inputs!B11),M87*Q87) | S87: =R87/(1+Inputs!B11) | T87: =IF(Inputs!B7=1,L87,MIN(S87,L87)) | U87: =IF(Inputs!B19=1,MAX(0,T87-J87),0) | V87: =T87*(1+Inputs!B11) | W87: =V87-T87 | X87: =V87*Inputs!B13*MIN(12,Inputs!B10)/12 | Y87: =W87*Inputs!B14/12 | Z87: =J87+U87-T87+X87-Y87 | AA87: =D87+E87-I87+U87+X87-Y87 | AB87: =IF(U87>0,AB86*(1+Inputs!B15/12)+U87,AB86*(1+Inputs!B15/12)) | AC87: =IF(Inputs!B21>0,AA87/Inputs!B21,0) | AD87: =G87+T87 | AE87: =H87+W87 | AF87: =AD87+AE87 | AG87: =IF(M87>0,V87/M87,0) | AH87: =AH86+U87 | AI87: =IFERROR((1+IRR(VSTACK($AJ$8:INDEX($AJ:$AJ,ROW()-1),-U87+AA87)))^12-1,0) | AJ87: =-U87
A88: =A87+1 | B88: Month 81 | C88: =Z87 | D88: =AA87 | E88: =IF(A88<=12,0,INDEX($V$8:$V$127,A88-12)*Inputs!B13*MAX(0,Inputs!B10-12)/12) | F88: =IF(A88<=Inputs!B10,0,INDEX($T$8:$T$127,A88-Inputs!B10)) | G88: =AD87-F88 | H88: =AE87-IF(A88<=Inputs!B10,0,INDEX($W$8:$W$127,A88-Inputs!B10)) | I88: =H88*Inputs!B14/12 | J88: =C88+E88+F88-I88 | K88: =IF(Inputs!B19=1,MAX(0,Inputs!B5*1000000000-AH87),0) | L88: =MAX(0,J88+K88) | M88: =Inputs!B8*1000000 | N88: =Inputs!B9 | O88: =MAX(1,SQRT(L88/MAX(M88*MAX(N88,0.01)/(1+Inputs!B11),1))) | P88: =MIN(1,A88/12) | Q88: =IF(Inputs!B7=1,MAX(N88,L88*(1+Inputs!B11)/MAX(M88,1)),N88+(N88*O88-N88)*P88) | R88: =IF(Inputs!B7=1,L88*(1+Inputs!B11),M88*Q88) | S88: =R88/(1+Inputs!B11) | T88: =IF(Inputs!B7=1,L88,MIN(S88,L88)) | U88: =IF(Inputs!B19=1,MAX(0,T88-J88),0) | V88: =T88*(1+Inputs!B11) | W88: =V88-T88 | X88: =V88*Inputs!B13*MIN(12,Inputs!B10)/12 | Y88: =W88*Inputs!B14/12 | Z88: =J88+U88-T88+X88-Y88 | AA88: =D88+E88-I88+U88+X88-Y88 | AB88: =IF(U88>0,AB87*(1+Inputs!B15/12)+U88,AB87*(1+Inputs!B15/12)) | AC88: =IF(Inputs!B21>0,AA88/Inputs!B21,0) | AD88: =G88+T88 | AE88: =H88+W88 | AF88: =AD88+AE88 | AG88: =IF(M88>0,V88/M88,0) | AH88: =AH87+U88 | AI88: =IFERROR((1+IRR(VSTACK($AJ$8:INDEX($AJ:$AJ,ROW()-1),-U88+AA88)))^12-1,0) | AJ88: =-U88
A89: =A88+1 | B89: Month 82 | C89: =Z88 | D89: =AA88 | E89: =IF(A89<=12,0,INDEX($V$8:$V$127,A89-12)*Inputs!B13*MAX(0,Inputs!B10-12)/12) | F89: =IF(A89<=Inputs!B10,0,INDEX($T$8:$T$127,A89-Inputs!B10)) | G89: =AD88-F89 | H89: =AE88-IF(A89<=Inputs!B10,0,INDEX($W$8:$W$127,A89-Inputs!B10)) | I89: =H89*Inputs!B14/12 | J89: =C89+E89+F89-I89 | K89: =IF(Inputs!B19=1,MAX(0,Inputs!B5*1000000000-AH88),0) | L89: =MAX(0,J89+K89) | M89: =Inputs!B8*1000000 | N89: =Inputs!B9 | O89: =MAX(1,SQRT(L89/MAX(M89*MAX(N89,0.01)/(1+Inputs!B11),1))) | P89: =MIN(1,A89/12) | Q89: =IF(Inputs!B7=1,MAX(N89,L89*(1+Inputs!B11)/MAX(M89,1)),N89+(N89*O89-N89)*P89) | R89: =IF(Inputs!B7=1,L89*(1+Inputs!B11),M89*Q89) | S89: =R89/(1+Inputs!B11) | T89: =IF(Inputs!B7=1,L89,MIN(S89,L89)) | U89: =IF(Inputs!B19=1,MAX(0,T89-J89),0) | V89: =T89*(1+Inputs!B11) | W89: =V89-T89 | X89: =V89*Inputs!B13*MIN(12,Inputs!B10)/12 | Y89: =W89*Inputs!B14/12 | Z89: =J89+U89-T89+X89-Y89 | AA89: =D89+E89-I89+U89+X89-Y89 | AB89: =IF(U89>0,AB88*(1+Inputs!B15/12)+U89,AB88*(1+Inputs!B15/12)) | AC89: =IF(Inputs!B21>0,AA89/Inputs!B21,0) | AD89: =G89+T89 | AE89: =H89+W89 | AF89: =AD89+AE89 | AG89: =IF(M89>0,V89/M89,0) | AH89: =AH88+U89 | AI89: =IFERROR((1+IRR(VSTACK($AJ$8:INDEX($AJ:$AJ,ROW()-1),-U89+AA89)))^12-1,0) | AJ89: =-U89
A90: =A89+1 | B90: Month 83 | C90: =Z89 | D90: =AA89 | E90: =IF(A90<=12,0,INDEX($V$8:$V$127,A90-12)*Inputs!B13*MAX(0,Inputs!B10-12)/12) | F90: =IF(A90<=Inputs!B10,0,INDEX($T$8:$T$127,A90-Inputs!B10)) | G90: =AD89-F90 | H90: =AE89-IF(A90<=Inputs!B10,0,INDEX($W$8:$W$127,A90-Inputs!B10)) | I90: =H90*Inputs!B14/12 | J90: =C90+E90+F90-I90 | K90: =IF(Inputs!B19=1,MAX(0,Inputs!B5*1000000000-AH89),0) | L90: =MAX(0,J90+K90) | M90: =Inputs!B8*1000000 | N90: =Inputs!B9 | O90: =MAX(1,SQRT(L90/MAX(M90*MAX(N90,0.01)/(1+Inputs!B11),1))) | P90: =MIN(1,A90/12) | Q90: =IF(Inputs!B7=1,MAX(N90,L90*(1+Inputs!B11)/MAX(M90,1)),N90+(N90*O90-N90)*P90) | R90: =IF(Inputs!B7=1,L90*(1+Inputs!B11),M90*Q90) | S90: =R90/(1+Inputs!B11) | T90: =IF(Inputs!B7=1,L90,MIN(S90,L90)) | U90: =IF(Inputs!B19=1,MAX(0,T90-J90),0) | V90: =T90*(1+Inputs!B11) | W90: =V90-T90 | X90: =V90*Inputs!B13*MIN(12,Inputs!B10)/12 | Y90: =W90*Inputs!B14/12 | Z90: =J90+U90-T90+X90-Y90 | AA90: =D90+E90-I90+U90+X90-Y90 | AB90: =IF(U90>0,AB89*(1+Inputs!B15/12)+U90,AB89*(1+Inputs!B15/12)) | AC90: =IF(Inputs!B21>0,AA90/Inputs!B21,0) | AD90: =G90+T90 | AE90: =H90+W90 | AF90: =AD90+AE90 | AG90: =IF(M90>0,V90/M90,0) | AH90: =AH89+U90 | AI90: =IFERROR((1+IRR(VSTACK($AJ$8:INDEX($AJ:$AJ,ROW()-1),-U90+AA90)))^12-1,0) | AJ90: =-U90
A91: =A90+1 | B91: Month 84 | C91: =Z90 | D91: =AA90 | E91: =IF(A91<=12,0,INDEX($V$8:$V$127,A91-12)*Inputs!B13*MAX(0,Inputs!B10-12)/12) | F91: =IF(A91<=Inputs!B10,0,INDEX($T$8:$T$127,A91-Inputs!B10)) | G91: =AD90-F91 | H91: =AE90-IF(A91<=Inputs!B10,0,INDEX($W$8:$W$127,A91-Inputs!B10)) | I91: =H91*Inputs!B14/12 | J91: =C91+E91+F91-I91 | K91: =IF(Inputs!B19=1,MAX(0,Inputs!B5*1000000000-AH90),0) | L91: =MAX(0,J91+K91) | M91: =Inputs!B8*1000000 | N91: =Inputs!B9 | O91: =MAX(1,SQRT(L91/MAX(M91*MAX(N91,0.01)/(1+Inputs!B11),1))) | P91: =MIN(1,A91/12) | Q91: =IF(Inputs!B7=1,MAX(N91,L91*(1+Inputs!B11)/MAX(M91,1)),N91+(N91*O91-N91)*P91) | R91: =IF(Inputs!B7=1,L91*(1+Inputs!B11),M91*Q91) | S91: =R91/(1+Inputs!B11) | T91: =IF(Inputs!B7=1,L91,MIN(S91,L91)) | U91: =IF(Inputs!B19=1,MAX(0,T91-J91),0) | V91: =T91*(1+Inputs!B11) | W91: =V91-T91 | X91: =V91*Inputs!B13*MIN(12,Inputs!B10)/12 | Y91: =W91*Inputs!B14/12 | Z91: =J91+U91-T91+X91-Y91 | AA91: =D91+E91-I91+U91+X91-Y91 | AB91: =IF(U91>0,AB90*(1+Inputs!B15/12)+U91,AB90*(1+Inputs!B15/12)) | AC91: =IF(Inputs!B21>0,AA91/Inputs!B21,0) | AD91: =G91+T91 | AE91: =H91+W91 | AF91: =AD91+AE91 | AG91: =IF(M91>0,V91/M91,0) | AH91: =AH90+U91 | AI91: =IFERROR((1+IRR(VSTACK($AJ$8:INDEX($AJ:$AJ,ROW()-1),-U91+AA91)))^12-1,0) | AJ91: =-U91
A92: =A91+1 | B92: Month 85 | C92: =Z91 | D92: =AA91 | E92: =IF(A92<=12,0,INDEX($V$8:$V$127,A92-12)*Inputs!B13*MAX(0,Inputs!B10-12)/12) | F92: =IF(A92<=Inputs!B10,0,INDEX($T$8:$T$127,A92-Inputs!B10)) | G92: =AD91-F92 | H92: =AE91-IF(A92<=Inputs!B10,0,INDEX($W$8:$W$127,A92-Inputs!B10)) | I92: =H92*Inputs!B14/12 | J92: =C92+E92+F92-I92 | K92: =IF(Inputs!B19=1,MAX(0,Inputs!B5*1000000000-AH91),0) | L92: =MAX(0,J92+K92) | M92: =Inputs!B8*1000000 | N92: =Inputs!B9 | O92: =MAX(1,SQRT(L92/MAX(M92*MAX(N92,0.01)/(1+Inputs!B11),1))) | P92: =MIN(1,A92/12) | Q92: =IF(Inputs!B7=1,MAX(N92,L92*(1+Inputs!B11)/MAX(M92,1)),N92+(N92*O92-N92)*P92) | R92: =IF(Inputs!B7=1,L92*(1+Inputs!B11),M92*Q92) | S92: =R92/(1+Inputs!B11) | T92: =IF(Inputs!B7=1,L92,MIN(S92,L92)) | U92: =IF(Inputs!B19=1,MAX(0,T92-J92),0) | V92: =T92*(1+Inputs!B11) | W92: =V92-T92 | X92: =V92*Inputs!B13*MIN(12,Inputs!B10)/12 | Y92: =W92*Inputs!B14/12 | Z92: =J92+U92-T92+X92-Y92 | AA92: =D92+E92-I92+U92+X92-Y92 | AB92: =IF(U92>0,AB91*(1+Inputs!B15/12)+U92,AB91*(1+Inputs!B15/12)) | AC92: =IF(Inputs!B21>0,AA92/Inputs!B21,0) | AD92: =G92+T92 | AE92: =H92+W92 | AF92: =AD92+AE92 | AG92: =IF(M92>0,V92/M92,0) | AH92: =AH91+U92 | AI92: =IFERROR((1+IRR(VSTACK($AJ$8:INDEX($AJ:$AJ,ROW()-1),-U92+AA92)))^12-1,0) | AJ92: =-U92
A93: =A92+1 | B93: Month 86 | C93: =Z92 | D93: =AA92 | E93: =IF(A93<=12,0,INDEX($V$8:$V$127,A93-12)*Inputs!B13*MAX(0,Inputs!B10-12)/12) | F93: =IF(A93<=Inputs!B10,0,INDEX($T$8:$T$127,A93-Inputs!B10)) | G93: =AD92-F93 | H93: =AE92-IF(A93<=Inputs!B10,0,INDEX($W$8:$W$127,A93-Inputs!B10)) | I93: =H93*Inputs!B14/12 | J93: =C93+E93+F93-I93 | K93: =IF(Inputs!B19=1,MAX(0,Inputs!B5*1000000000-AH92),0) | L93: =MAX(0,J93+K93) | M93: =Inputs!B8*1000000 | N93: =Inputs!B9 | O93: =MAX(1,SQRT(L93/MAX(M93*MAX(N93,0.01)/(1+Inputs!B11),1))) | P93: =MIN(1,A93/12) | Q93: =IF(Inputs!B7=1,MAX(N93,L93*(1+Inputs!B11)/MAX(M93,1)),N93+(N93*O93-N93)*P93) | R93: =IF(Inputs!B7=1,L93*(1+Inputs!B11),M93*Q93) | S93: =R93/(1+Inputs!B11) | T93: =IF(Inputs!B7=1,L93,MIN(S93,L93)) | U93: =IF(Inputs!B19=1,MAX(0,T93-J93),0) | V93: =T93*(1+Inputs!B11) | W93: =V93-T93 | X93: =V93*Inputs!B13*MIN(12,Inputs!B10)/12 | Y93: =W93*Inputs!B14/12 | Z93: =J93+U93-T93+X93-Y93 | AA93: =D93+E93-I93+U93+X93-Y93 | AB93: =IF(U93>0,AB92*(1+Inputs!B15/12)+U93,AB92*(1+Inputs!B15/12)) | AC93: =IF(Inputs!B21>0,AA93/Inputs!B21,0) | AD93: =G93+T93 | AE93: =H93+W93 | AF93: =AD93+AE93 | AG93: =IF(M93>0,V93/M93,0) | AH93: =AH92+U93 | AI93: =IFERROR((1+IRR(VSTACK($AJ$8:INDEX($AJ:$AJ,ROW()-1),-U93+AA93)))^12-1,0) | AJ93: =-U93
A94: =A93+1 | B94: Month 87 | C94: =Z93 | D94: =AA93 | E94: =IF(A94<=12,0,INDEX($V$8:$V$127,A94-12)*Inputs!B13*MAX(0,Inputs!B10-12)/12) | F94: =IF(A94<=Inputs!B10,0,INDEX($T$8:$T$127,A94-Inputs!B10)) | G94: =AD93-F94 | H94: =AE93-IF(A94<=Inputs!B10,0,INDEX($W$8:$W$127,A94-Inputs!B10)) | I94: =H94*Inputs!B14/12 | J94: =C94+E94+F94-I94 | K94: =IF(Inputs!B19=1,MAX(0,Inputs!B5*1000000000-AH93),0) | L94: =MAX(0,J94+K94) | M94: =Inputs!B8*1000000 | N94: =Inputs!B9 | O94: =MAX(1,SQRT(L94/MAX(M94*MAX(N94,0.01)/(1+Inputs!B11),1))) | P94: =MIN(1,A94/12) | Q94: =IF(Inputs!B7=1,MAX(N94,L94*(1+Inputs!B11)/MAX(M94,1)),N94+(N94*O94-N94)*P94) | R94: =IF(Inputs!B7=1,L94*(1+Inputs!B11),M94*Q94) | S94: =R94/(1+Inputs!B11) | T94: =IF(Inputs!B7=1,L94,MIN(S94,L94)) | U94: =IF(Inputs!B19=1,MAX(0,T94-J94),0) | V94: =T94*(1+Inputs!B11) | W94: =V94-T94 | X94: =V94*Inputs!B13*MIN(12,Inputs!B10)/12 | Y94: =W94*Inputs!B14/12 | Z94: =J94+U94-T94+X94-Y94 | AA94: =D94+E94-I94+U94+X94-Y94 | AB94: =IF(U94>0,AB93*(1+Inputs!B15/12)+U94,AB93*(1+Inputs!B15/12)) | AC94: =IF(Inputs!B21>0,AA94/Inputs!B21,0) | AD94: =G94+T94 | AE94: =H94+W94 | AF94: =AD94+AE94 | AG94: =IF(M94>0,V94/M94,0) | AH94: =AH93+U94 | AI94: =IFERROR((1+IRR(VSTACK($AJ$8:INDEX($AJ:$AJ,ROW()-1),-U94+AA94)))^12-1,0) | AJ94: =-U94
A95: =A94+1 | B95: Month 88 | C95: =Z94 | D95: =AA94 | E95: =IF(A95<=12,0,INDEX($V$8:$V$127,A95-12)*Inputs!B13*MAX(0,Inputs!B10-12)/12) | F95: =IF(A95<=Inputs!B10,0,INDEX($T$8:$T$127,A95-Inputs!B10)) | G95: =AD94-F95 | H95: =AE94-IF(A95<=Inputs!B10,0,INDEX($W$8:$W$127,A95-Inputs!B10)) | I95: =H95*Inputs!B14/12 | J95: =C95+E95+F95-I95 | K95: =IF(Inputs!B19=1,MAX(0,Inputs!B5*1000000000-AH94),0) | L95: =MAX(0,J95+K95) | M95: =Inputs!B8*1000000 | N95: =Inputs!B9 | O95: =MAX(1,SQRT(L95/MAX(M95*MAX(N95,0.01)/(1+Inputs!B11),1))) | P95: =MIN(1,A95/12) | Q95: =IF(Inputs!B7=1,MAX(N95,L95*(1+Inputs!B11)/MAX(M95,1)),N95+(N95*O95-N95)*P95) | R95: =IF(Inputs!B7=1,L95*(1+Inputs!B11),M95*Q95) | S95: =R95/(1+Inputs!B11) | T95: =IF(Inputs!B7=1,L95,MIN(S95,L95)) | U95: =IF(Inputs!B19=1,MAX(0,T95-J95),0) | V95: =T95*(1+Inputs!B11) | W95: =V95-T95 | X95: =V95*Inputs!B13*MIN(12,Inputs!B10)/12 | Y95: =W95*Inputs!B14/12 | Z95: =J95+U95-T95+X95-Y95 | AA95: =D95+E95-I95+U95+X95-Y95 | AB95: =IF(U95>0,AB94*(1+Inputs!B15/12)+U95,AB94*(1+Inputs!B15/12)) | AC95: =IF(Inputs!B21>0,AA95/Inputs!B21,0) | AD95: =G95+T95 | AE95: =H95+W95 | AF95: =AD95+AE95 | AG95: =IF(M95>0,V95/M95,0) | AH95: =AH94+U95 | AI95: =IFERROR((1+IRR(VSTACK($AJ$8:INDEX($AJ:$AJ,ROW()-1),-U95+AA95)))^12-1,0) | AJ95: =-U95
A96: =A95+1 | B96: Month 89 | C96: =Z95 | D96: =AA95 | E96: =IF(A96<=12,0,INDEX($V$8:$V$127,A96-12)*Inputs!B13*MAX(0,Inputs!B10-12)/12) | F96: =IF(A96<=Inputs!B10,0,INDEX($T$8:$T$127,A96-Inputs!B10)) | G96: =AD95-F96 | H96: =AE95-IF(A96<=Inputs!B10,0,INDEX($W$8:$W$127,A96-Inputs!B10)) | I96: =H96*Inputs!B14/12 | J96: =C96+E96+F96-I96 | K96: =IF(Inputs!B19=1,MAX(0,Inputs!B5*1000000000-AH95),0) | L96: =MAX(0,J96+K96) | M96: =Inputs!B8*1000000 | N96: =Inputs!B9 | O96: =MAX(1,SQRT(L96/MAX(M96*MAX(N96,0.01)/(1+Inputs!B11),1))) | P96: =MIN(1,A96/12) | Q96: =IF(Inputs!B7=1,MAX(N96,L96*(1+Inputs!B11)/MAX(M96,1)),N96+(N96*O96-N96)*P96) | R96: =IF(Inputs!B7=1,L96*(1+Inputs!B11),M96*Q96) | S96: =R96/(1+Inputs!B11) | T96: =IF(Inputs!B7=1,L96,MIN(S96,L96)) | U96: =IF(Inputs!B19=1,MAX(0,T96-J96),0) | V96: =T96*(1+Inputs!B11) | W96: =V96-T96 | X96: =V96*Inputs!B13*MIN(12,Inputs!B10)/12 | Y96: =W96*Inputs!B14/12 | Z96: =J96+U96-T96+X96-Y96 | AA96: =D96+E96-I96+U96+X96-Y96 | AB96: =IF(U96>0,AB95*(1+Inputs!B15/12)+U96,AB95*(1+Inputs!B15/12)) | AC96: =IF(Inputs!B21>0,AA96/Inputs!B21,0) | AD96: =G96+T96 | AE96: =H96+W96 | AF96: =AD96+AE96 | AG96: =IF(M96>0,V96/M96,0) | AH96: =AH95+U96 | AI96: =IFERROR((1+IRR(VSTACK($AJ$8:INDEX($AJ:$AJ,ROW()-1),-U96+AA96)))^12-1,0) | AJ96: =-U96
A97: =A96+1 | B97: Month 90 | C97: =Z96 | D97: =AA96 | E97: =IF(A97<=12,0,INDEX($V$8:$V$127,A97-12)*Inputs!B13*MAX(0,Inputs!B10-12)/12) | F97: =IF(A97<=Inputs!B10,0,INDEX($T$8:$T$127,A97-Inputs!B10)) | G97: =AD96-F97 | H97: =AE96-IF(A97<=Inputs!B10,0,INDEX($W$8:$W$127,A97-Inputs!B10)) | I97: =H97*Inputs!B14/12 | J97: =C97+E97+F97-I97 | K97: =IF(Inputs!B19=1,MAX(0,Inputs!B5*1000000000-AH96),0) | L97: =MAX(0,J97+K97) | M97: =Inputs!B8*1000000 | N97: =Inputs!B9 | O97: =MAX(1,SQRT(L97/MAX(M97*MAX(N97,0.01)/(1+Inputs!B11),1))) | P97: =MIN(1,A97/12) | Q97: =IF(Inputs!B7=1,MAX(N97,L97*(1+Inputs!B11)/MAX(M97,1)),N97+(N97*O97-N97)*P97) | R97: =IF(Inputs!B7=1,L97*(1+Inputs!B11),M97*Q97) | S97: =R97/(1+Inputs!B11) | T97: =IF(Inputs!B7=1,L97,MIN(S97,L97)) | U97: =IF(Inputs!B19=1,MAX(0,T97-J97),0) | V97: =T97*(1+Inputs!B11) | W97: =V97-T97 | X97: =V97*Inputs!B13*MIN(12,Inputs!B10)/12 | Y97: =W97*Inputs!B14/12 | Z97: =J97+U97-T97+X97-Y97 | AA97: =D97+E97-I97+U97+X97-Y97 | AB97: =IF(U97>0,AB96*(1+Inputs!B15/12)+U97,AB96*(1+Inputs!B15/12)) | AC97: =IF(Inputs!B21>0,AA97/Inputs!B21,0) | AD97: =G97+T97 | AE97: =H97+W97 | AF97: =AD97+AE97 | AG97: =IF(M97>0,V97/M97,0) | AH97: =AH96+U97 | AI97: =IFERROR((1+IRR(VSTACK($AJ$8:INDEX($AJ:$AJ,ROW()-1),-U97+AA97)))^12-1,0) | AJ97: =-U97
A98: =A97+1 | B98: Month 91 | C98: =Z97 | D98: =AA97 | E98: =IF(A98<=12,0,INDEX($V$8:$V$127,A98-12)*Inputs!B13*MAX(0,Inputs!B10-12)/12) | F98: =IF(A98<=Inputs!B10,0,INDEX($T$8:$T$127,A98-Inputs!B10)) | G98: =AD97-F98 | H98: =AE97-IF(A98<=Inputs!B10,0,INDEX($W$8:$W$127,A98-Inputs!B10)) | I98: =H98*Inputs!B14/12 | J98: =C98+E98+F98-I98 | K98: =IF(Inputs!B19=1,MAX(0,Inputs!B5*1000000000-AH97),0) | L98: =MAX(0,J98+K98) | M98: =Inputs!B8*1000000 | N98: =Inputs!B9 | O98: =MAX(1,SQRT(L98/MAX(M98*MAX(N98,0.01)/(1+Inputs!B11),1))) | P98: =MIN(1,A98/12) | Q98: =IF(Inputs!B7=1,MAX(N98,L98*(1+Inputs!B11)/MAX(M98,1)),N98+(N98*O98-N98)*P98) | R98: =IF(Inputs!B7=1,L98*(1+Inputs!B11),M98*Q98) | S98: =R98/(1+Inputs!B11) | T98: =IF(Inputs!B7=1,L98,MIN(S98,L98)) | U98: =IF(Inputs!B19=1,MAX(0,T98-J98),0) | V98: =T98*(1+Inputs!B11) | W98: =V98-T98 | X98: =V98*Inputs!B13*MIN(12,Inputs!B10)/12 | Y98: =W98*Inputs!B14/12 | Z98: =J98+U98-T98+X98-Y98 | AA98: =D98+E98-I98+U98+X98-Y98 | AB98: =IF(U98>0,AB97*(1+Inputs!B15/12)+U98,AB97*(1+Inputs!B15/12)) | AC98: =IF(Inputs!B21>0,AA98/Inputs!B21,0) | AD98: =G98+T98 | AE98: =H98+W98 | AF98: =AD98+AE98 | AG98: =IF(M98>0,V98/M98,0) | AH98: =AH97+U98 | AI98: =IFERROR((1+IRR(VSTACK($AJ$8:INDEX($AJ:$AJ,ROW()-1),-U98+AA98)))^12-1,0) | AJ98: =-U98
A99: =A98+1 | B99: Month 92 | C99: =Z98 | D99: =AA98 | E99: =IF(A99<=12,0,INDEX($V$8:$V$127,A99-12)*Inputs!B13*MAX(0,Inputs!B10-12)/12) | F99: =IF(A99<=Inputs!B10,0,INDEX($T$8:$T$127,A99-Inputs!B10)) | G99: =AD98-F99 | H99: =AE98-IF(A99<=Inputs!B10,0,INDEX($W$8:$W$127,A99-Inputs!B10)) | I99: =H99*Inputs!B14/12 | J99: =C99+E99+F99-I99 | K99: =IF(Inputs!B19=1,MAX(0,Inputs!B5*1000000000-AH98),0) | L99: =MAX(0,J99+K99) | M99: =Inputs!B8*1000000 | N99: =Inputs!B9 | O99: =MAX(1,SQRT(L99/MAX(M99*MAX(N99,0.01)/(1+Inputs!B11),1))) | P99: =MIN(1,A99/12) | Q99: =IF(Inputs!B7=1,MAX(N99,L99*(1+Inputs!B11)/MAX(M99,1)),N99+(N99*O99-N99)*P99) | R99: =IF(Inputs!B7=1,L99*(1+Inputs!B11),M99*Q99) | S99: =R99/(1+Inputs!B11) | T99: =IF(Inputs!B7=1,L99,MIN(S99,L99)) | U99: =IF(Inputs!B19=1,MAX(0,T99-J99),0) | V99: =T99*(1+Inputs!B11) | W99: =V99-T99 | X99: =V99*Inputs!B13*MIN(12,Inputs!B10)/12 | Y99: =W99*Inputs!B14/12 | Z99: =J99+U99-T99+X99-Y99 | AA99: =D99+E99-I99+U99+X99-Y99 | AB99: =IF(U99>0,AB98*(1+Inputs!B15/12)+U99,AB98*(1+Inputs!B15/12)) | AC99: =IF(Inputs!B21>0,AA99/Inputs!B21,0) | AD99: =G99+T99 | AE99: =H99+W99 | AF99: =AD99+AE99 | AG99: =IF(M99>0,V99/M99,0) | AH99: =AH98+U99 | AI99: =IFERROR((1+IRR(VSTACK($AJ$8:INDEX($AJ:$AJ,ROW()-1),-U99+AA99)))^12-1,0) | AJ99: =-U99
A100: =A99+1 | B100: Month 93 | C100: =Z99 | D100: =AA99 | E100: =IF(A100<=12,0,INDEX($V$8:$V$127,A100-12)*Inputs!B13*MAX(0,Inputs!B10-12)/12) | F100: =IF(A100<=Inputs!B10,0,INDEX($T$8:$T$127,A100-Inputs!B10)) | G100: =AD99-F100 | H100: =AE99-IF(A100<=Inputs!B10,0,INDEX($W$8:$W$127,A100-Inputs!B10)) | I100: =H100*Inputs!B14/12 | J100: =C100+E100+F100-I100 | K100: =IF(Inputs!B19=1,MAX(0,Inputs!B5*1000000000-AH99),0) | L100: =MAX(0,J100+K100) | M100: =Inputs!B8*1000000 | N100: =Inputs!B9 | O100: =MAX(1,SQRT(L100/MAX(M100*MAX(N100,0.01)/(1+Inputs!B11),1))) | P100: =MIN(1,A100/12) | Q100: =IF(Inputs!B7=1,MAX(N100,L100*(1+Inputs!B11)/MAX(M100,1)),N100+(N100*O100-N100)*P100) | R100: =IF(Inputs!B7=1,L100*(1+Inputs!B11),M100*Q100) | S100: =R100/(1+Inputs!B11) | T100: =IF(Inputs!B7=1,L100,MIN(S100,L100)) | U100: =IF(Inputs!B19=1,MAX(0,T100-J100),0) | V100: =T100*(1+Inputs!B11) | W100: =V100-T100 | X100: =V100*Inputs!B13*MIN(12,Inputs!B10)/12 | Y100: =W100*Inputs!B14/12 | Z100: =J100+U100-T100+X100-Y100 | AA100: =D100+E100-I100+U100+X100-Y100 | AB100: =IF(U100>0,AB99*(1+Inputs!B15/12)+U100,AB99*(1+Inputs!B15/12)) | AC100: =IF(Inputs!B21>0,AA100/Inputs!B21,0) | AD100: =G100+T100 | AE100: =H100+W100 | AF100: =AD100+AE100 | AG100: =IF(M100>0,V100/M100,0) | AH100: =AH99+U100 | AI100: =IFERROR((1+IRR(VSTACK($AJ$8:INDEX($AJ:$AJ,ROW()-1),-U100+AA100)))^12-1,0) | AJ100: =-U100
A101: =A100+1 | B101: Month 94 | C101: =Z100 | D101: =AA100 | E101: =IF(A101<=12,0,INDEX($V$8:$V$127,A101-12)*Inputs!B13*MAX(0,Inputs!B10-12)/12) | F101: =IF(A101<=Inputs!B10,0,INDEX($T$8:$T$127,A101-Inputs!B10)) | G101: =AD100-F101 | H101: =AE100-IF(A101<=Inputs!B10,0,INDEX($W$8:$W$127,A101-Inputs!B10)) | I101: =H101*Inputs!B14/12 | J101: =C101+E101+F101-I101 | K101: =IF(Inputs!B19=1,MAX(0,Inputs!B5*1000000000-AH100),0) | L101: =MAX(0,J101+K101) | M101: =Inputs!B8*1000000 | N101: =Inputs!B9 | O101: =MAX(1,SQRT(L101/MAX(M101*MAX(N101,0.01)/(1+Inputs!B11),1))) | P101: =MIN(1,A101/12) | Q101: =IF(Inputs!B7=1,MAX(N101,L101*(1+Inputs!B11)/MAX(M101,1)),N101+(N101*O101-N101)*P101) | R101: =IF(Inputs!B7=1,L101*(1+Inputs!B11),M101*Q101) | S101: =R101/(1+Inputs!B11) | T101: =IF(Inputs!B7=1,L101,MIN(S101,L101)) | U101: =IF(Inputs!B19=1,MAX(0,T101-J101),0) | V101: =T101*(1+Inputs!B11) | W101: =V101-T101 | X101: =V101*Inputs!B13*MIN(12,Inputs!B10)/12 | Y101: =W101*Inputs!B14/12 | Z101: =J101+U101-T101+X101-Y101 | AA101: =D101+E101-I101+U101+X101-Y101 | AB101: =IF(U101>0,AB100*(1+Inputs!B15/12)+U101,AB100*(1+Inputs!B15/12)) | AC101: =IF(Inputs!B21>0,AA101/Inputs!B21,0) | AD101: =G101+T101 | AE101: =H101+W101 | AF101: =AD101+AE101 | AG101: =IF(M101>0,V101/M101,0) | AH101: =AH100+U101 | AI101: =IFERROR((1+IRR(VSTACK($AJ$8:INDEX($AJ:$AJ,ROW()-1),-U101+AA101)))^12-1,0) | AJ101: =-U101
A102: =A101+1 | B102: Month 95 | C102: =Z101 | D102: =AA101 | E102: =IF(A102<=12,0,INDEX($V$8:$V$127,A102-12)*Inputs!B13*MAX(0,Inputs!B10-12)/12) | F102: =IF(A102<=Inputs!B10,0,INDEX($T$8:$T$127,A102-Inputs!B10)) | G102: =AD101-F102 | H102: =AE101-IF(A102<=Inputs!B10,0,INDEX($W$8:$W$127,A102-Inputs!B10)) | I102: =H102*Inputs!B14/12 | J102: =C102+E102+F102-I102 | K102: =IF(Inputs!B19=1,MAX(0,Inputs!B5*1000000000-AH101),0) | L102: =MAX(0,J102+K102) | M102: =Inputs!B8*1000000 | N102: =Inputs!B9 | O102: =MAX(1,SQRT(L102/MAX(M102*MAX(N102,0.01)/(1+Inputs!B11),1))) | P102: =MIN(1,A102/12) | Q102: =IF(Inputs!B7=1,MAX(N102,L102*(1+Inputs!B11)/MAX(M102,1)),N102+(N102*O102-N102)*P102) | R102: =IF(Inputs!B7=1,L102*(1+Inputs!B11),M102*Q102) | S102: =R102/(1+Inputs!B11) | T102: =IF(Inputs!B7=1,L102,MIN(S102,L102)) | U102: =IF(Inputs!B19=1,MAX(0,T102-J102),0) | V102: =T102*(1+Inputs!B11) | W102: =V102-T102 | X102: =V102*Inputs!B13*MIN(12,Inputs!B10)/12 | Y102: =W102*Inputs!B14/12 | Z102: =J102+U102-T102+X102-Y102 | AA102: =D102+E102-I102+U102+X102-Y102 | AB102: =IF(U102>0,AB101*(1+Inputs!B15/12)+U102,AB101*(1+Inputs!B15/12)) | AC102: =IF(Inputs!B21>0,AA102/Inputs!B21,0) | AD102: =G102+T102 | AE102: =H102+W102 | AF102: =AD102+AE102 | AG102: =IF(M102>0,V102/M102,0) | AH102: =AH101+U102 | AI102: =IFERROR((1+IRR(VSTACK($AJ$8:INDEX($AJ:$AJ,ROW()-1),-U102+AA102)))^12-1,0) | AJ102: =-U102
A103: =A102+1 | B103: Month 96 | C103: =Z102 | D103: =AA102 | E103: =IF(A103<=12,0,INDEX($V$8:$V$127,A103-12)*Inputs!B13*MAX(0,Inputs!B10-12)/12) | F103: =IF(A103<=Inputs!B10,0,INDEX($T$8:$T$127,A103-Inputs!B10)) | G103: =AD102-F103 | H103: =AE102-IF(A103<=Inputs!B10,0,INDEX($W$8:$W$127,A103-Inputs!B10)) | I103: =H103*Inputs!B14/12 | J103: =C103+E103+F103-I103 | K103: =IF(Inputs!B19=1,MAX(0,Inputs!B5*1000000000-AH102),0) | L103: =MAX(0,J103+K103) | M103: =Inputs!B8*1000000 | N103: =Inputs!B9 | O103: =MAX(1,SQRT(L103/MAX(M103*MAX(N103,0.01)/(1+Inputs!B11),1))) | P103: =MIN(1,A103/12) | Q103: =IF(Inputs!B7=1,MAX(N103,L103*(1+Inputs!B11)/MAX(M103,1)),N103+(N103*O103-N103)*P103) | R103: =IF(Inputs!B7=1,L103*(1+Inputs!B11),M103*Q103) | S103: =R103/(1+Inputs!B11) | T103: =IF(Inputs!B7=1,L103,MIN(S103,L103)) | U103: =IF(Inputs!B19=1,MAX(0,T103-J103),0) | V103: =T103*(1+Inputs!B11) | W103: =V103-T103 | X103: =V103*Inputs!B13*MIN(12,Inputs!B10)/12 | Y103: =W103*Inputs!B14/12 | Z103: =J103+U103-T103+X103-Y103 | AA103: =D103+E103-I103+U103+X103-Y103 | AB103: =IF(U103>0,AB102*(1+Inputs!B15/12)+U103,AB102*(1+Inputs!B15/12)) | AC103: =IF(Inputs!B21>0,AA103/Inputs!B21,0) | AD103: =G103+T103 | AE103: =H103+W103 | AF103: =AD103+AE103 | AG103: =IF(M103>0,V103/M103,0) | AH103: =AH102+U103 | AI103: =IFERROR((1+IRR(VSTACK($AJ$8:INDEX($AJ:$AJ,ROW()-1),-U103+AA103)))^12-1,0) | AJ103: =-U103
...

Sheet Notes
A1: Model Notes
A2: Contact Reif Tauati · 4176197004 · reif@thegoodproject.net
A4: What is modeled? | B4: This workbook mirrors the deterministic monthly Fund One model from /model over 120 months.
A5: Capital calls | B5: If Capital Calls On = 1 and Hardcore Mode = 0, LP capital is called only when needed. If Hardcore Mode = 1, the workbook assumes the full fund is funded upfront and redeployed immediately as cash returns.
A6: Borrower Rate vs Fund Take | B6: Borrower Rate is what the developer pays. Fund Take is the retained APY inside the fund after origination partners are paid.
A7: Debt / Equity | B7: A value of 0.25 means each $1.00 of LP equity supports $1.25 of loans through $0.25 of debt.
A8: How origination scales | B8: Desired origination volume is driven by pipeline capacity and deployable capital. In normal mode the model ramps scaling over 12 months. Hardcore Mode removes that gentler ramp and pushes available cash out immediately.
A9: IRR | B9: Projected IRR is solved from LP cash calls and terminal NAV. The Monthly_Model sheet also includes an IRR To Date column.
